sky/AHB_simple/code/spram_generic_wbe4.v
// ---------------------------------------------------------------------------//
// The confidential and proprietary information contained in this file may
// only be used by a person authorised under and to the extent permitted
// by a subsisting licensing agreement from SiliconThink.
//
//      (C) COPYRIGHT SiliconThink Limited or its affiliates
//                   ALL RIGHTS RESERVED
//
// This entire notice must be reproduced on all copies of this file
// and copies of this file may only be made by a person if such person is
// permitted to do so under the terms of a subsisting license agreement
// from SiliconThink or its affiliates.
// ---------------------------------------------------------------------------//

//----------------------------------------------------------------------------//
// File name    : spram_generic_wbe4.v
// Author       : sky@SiliconThink
// Email        : 
// Project      :
// Created      : 
// Copyright    : 
//
// Description  : 
// 1: Generic SP SRAM model.
//
//----------------------------------------------------------------------------//



module spram_generic_wbe4(
                    clk,
                    en,
                    we,
                    wbe,
            
                    addr,
                    din,
                    
                    dout
                    );    

parameter ADDR_BITS = 7;
parameter ADDR_AMOUNT = 128;
parameter DATA_BITS = 32;

input clk;
input en;
input we;
input [3:0]wbe;
input [ADDR_BITS-1:0]addr;
input [DATA_BITS-1:0]din;
output [DATA_BITS-1:0]dout;

reg [DATA_BITS-1:0]dout;
reg [DATA_BITS-1:0]mem[0 : ADDR_AMOUNT-1];

always@(posedge clk)
begin
	if(en) begin
        if(we==1'b1) begin
            if(wbe[0])
   	    	    mem[addr][0*8 +: 8] <= din[0*8 +: 8]; 

            if(wbe[1])
   	    	    mem[addr][1*8 +: 8] <= din[1*8 +: 8]; 

            if(wbe[2])
   	    	    mem[addr][2*8 +: 8] <= din[2*8 +: 8]; 

            if(wbe[3])
   	    	    mem[addr][3*8 +: 8] <= din[3*8 +: 8]; 
	    end else
        	dout<=mem[addr]; 
    end     
end


endmodule

sky/AHB_simple/code/ahb_sram.v
module ahb_sram(
    input                   clk,
    input                   rstn,
    input                   hsel,
    input  [mem_abit+2-1:0] haddr,
    input  [2:0]            hburst,
    input  [1:0]            htrans,
    input  [2:0]            hsize,
    input  [3:0]            hprot,
    input                   hwrite,
    input  [mem_dw-1:0]     hwdata,
    input                   hready,
    output                  hreadyout,
    output [31:0]           hrdata,
    output [1:0]            hresp 
);
    
parameter mem_depth = 1024;
parameter mem_abit = 10;
parameter mem_dw = 32;

reg [3:0] mem_wbe;
wire mem_cs;
wire mem_wr;
wire mem_rd;
wire [9:0]  mem_addr;
wire [31:0] mem_wdata;
wire [mem_dw-1:0] mem_rdata;

reg  bus_wr_phase;
wire bus_wr_phase_next;
reg [9:0] haddr_r;
reg hwrite_r;
wire bus_trans = hsel && hready && htrans[1];
wire bus_write = bus_trans && hwrite;
wire bus_read = (hready ? bus_trans : bus_trans_r) && (~hwrite);
assign hreadyout = !write2read_r;
assign hresp = 'd0;

//hsize
always @(posedge clk) begin
    if (!rstn) begin
        mem_wbe <= 4'b0000;
    end else if (hsel && hready) begin
        case (hsize)
            'd0:
                begin
                    case (haddr[1:0])
                        'd0: mem_wbe <= 4'b0001;
                        'd1: mem_wbe <= 4'b0010;
                        'd2: mem_wbe <= 4'b0100;
                        'd3: mem_wbe <= 4'b1000;
                    endcase
                end
            'd1:
                begin
                    if (haddr[1]) begin
                        mem_wbe <= 4'b1100;
                    end else begin
                        mem_wbe <= 4'b0011;
                    end
                end
            'd2: mem_wbe <= 4'b1111;
            'd3: mem_wbe <= 4'b1111;
             
        endcase
    end
end




// write

assign mem_wdata = hwdata;
assign bus_wr_phase_next = (!hreadyout && bus_wr_phase) | bus_write;
reg bus_trans_r;
always @(posedge clk or negedge rstn) begin
    if (!rstn) begin
        haddr_r <= 'b0;
        bus_trans_r <= 0;;
    end else if (bus_trans) begin
        haddr_r <= haddr[2+:mem_abit];
        bus_trans_r <= bus_trans;
    end
end

always @(posedge clk or negedge rstn) begin
    if (!rstn) begin
        hwrite_r <= 1'b0;
    end else if (bus_trans) begin
        hwrite_r <=  hwrite;
    end
end
always @(posedge clk or negedge rstn) begin
    if (!rstn) begin
        bus_wr_phase <= 1'b0;
    end else begin
        bus_wr_phase <= bus_wr_phase_next;//1：写命令的传输阶段
    end
end

wire write2read = bus_wr_phase && bus_read;
//写之后立马读产生读写矛盾
reg write2read_r;

assign hrdata = mem_rdata;

assign mem_rd = bus_read && (!bus_wr_phase);//读
assign mem_wr = bus_wr_phase && hready;

assign mem_cs = mem_rd | mem_wr;
assign mem_addr = (mem_wr | write2read_r) ? haddr_r : haddr[2 +: mem_abit];

always @(posedge clk or negedge rstn) begin
    if (!rstn) begin
        write2read_r <= 1'b0;
    end else begin
        write2read_r <= write2read;
    end
end

spram_generic_wbe4 #(.ADDR_BITS(mem_abit),.ADDR_AMOUNT(mem_depth),.DATA_BITS(mem_dw))
    u_mem(
        .clk   (clk        ),
        .en    (mem_cs     ),
        .we    (mem_wr     ),
        .wbe   (mem_wbe    ),

        .addr  (mem_addr   ),
        .din   (mem_wdata  ),
        .dout  (mem_rdata  )
    );



endmodule

sky/AHB_simple/code/tb_ahb_sram.v
module tb_ahb_sram;

// ahb_sram Parameters
parameter PERIOD     = 10  ;
parameter mem_depth  = 1024;
parameter mem_abit   = 10  ;
parameter mem_dw     = 32  ;

// ahb_sram Inputs
reg   clk                                  = 0 ;
reg   rstn                                 = 0 ;
reg   hsel                                 = 0 ;
reg   [mem_abit+2-1:0]  haddr              = 0 ;
reg   [2:0]  hburst                        = 0 ;
reg   [1:0]  htrans                        = 0 ;
reg   [2:0]  hsize                         = 0 ;
reg   [3:0]  hprot                         = 0 ;
reg   hwrite                               = 0 ;
reg   [mem_dw-1:0]  hwdata                 = 0 ;
wire   hready;
assign hready = hreadyout;               

// ahb_sram Outputs
wire  hreadyout                            ;
wire  [31:0]  hrdata                       ;
wire  [1:0]  hresp                         ;


initial
begin
    forever #(PERIOD/2)  clk=~clk;
end

initial
begin
    #(PERIOD*2) rstn  =  1;
    #2;
    hsel = 1;
    htrans = 2'b10;
    
   

end
reg [5:0] cnt;
always @(posedge clk or negedge rstn) begin
    if (!rstn) begin
        hwdata <= 'd0;
    end else if (hwrite) begin
        hwdata <= hwdata + 1;
    end
end

always @(posedge clk or negedge rstn) begin
    if (!rstn) begin
        hwrite <= 0;
        cnt <= 'd0;
    end else begin
        cnt <= cnt + 1;
        hsize <= 2'd3;
        if (cnt == 5'd31) begin
            hwrite <= 1'd0;
        end else if (cnt == 'd63) begin
            hwrite <= 1'b1;
        end        
    end
end

reg addr_flag;
always @(posedge clk or negedge rstn) begin
    if (!rstn) begin
        addr_flag <= 0;
    end else begin
        if (cnt == 'd32) begin
            addr_flag <= 1'b1;
        end else begin
            addr_flag <= 1'b0;
        end
    end
end

always @(posedge clk or negedge rstn) begin
    if (!rstn) begin
        haddr <= 'd0;
    end else begin
        
        if (cnt == 'd31) begin
            haddr <= 0;
        end else if (cnt == 'd63) begin
            haddr <= 0;
        end else if (addr_flag) begin
            haddr <= haddr;
        end else begin
            haddr <= haddr + 4;
        end
    end
end

integer i;
initial begin
    $dumpfile("test.vcd");
    $dumpvars;
    for (i = 0; i < 32; i = i + 1) begin
        $dumpvars(0,u_ahb_sram.u_mem.mem[i]);
    end
end

ahb_sram #(
    .mem_depth ( mem_depth ),
    .mem_abit  ( mem_abit  ),
    .mem_dw    ( mem_dw    ))
 u_ahb_sram (
    .clk                     ( clk                         ),
    .rstn                    ( rstn                        ),
    .hsel                    ( hsel                        ),
    .haddr                   ( haddr      [mem_abit+2-1:0] ),
    .hburst                  ( hburst     [2:0]            ),
    .htrans                  ( htrans     [1:0]            ),
    .hsize                   ( hsize      [2:0]            ),
    .hprot                   ( hprot      [3:0]            ),
    .hwrite                  ( hwrite                      ),
    .hwdata                  ( hwdata     [mem_dw-1:0]     ),
    .hready                  ( hready                      ),

    .hreadyout               ( hreadyout                   ),
    .hrdata                  ( hrdata     [31:0]           ),
    .hresp                   ( hresp      [1:0]            )
);

initial
begin
    #50000;
    $finish;
end

endmodule

sky/AHB_simple/sim/test.vcd
$date
	Sat Apr 08 23:44:38 2023
$end
$version
	Icarus Verilog
$end
$timescale
	1s
$end
$scope module tb_ahb_sram $end
$var wire 1 ! hready $end
$var wire 2 " hresp [1:0] $end
$var wire 1 # hreadyout $end
$var wire 32 $ hrdata [31:0] $end
$var reg 1 % addr_flag $end
$var reg 1 & clk $end
$var reg 6 ' cnt [5:0] $end
$var reg 12 ( haddr [11:0] $end
$var reg 3 ) hburst [2:0] $end
$var reg 4 * hprot [3:0] $end
$var reg 1 + hsel $end
$var reg 3 , hsize [2:0] $end
$var reg 2 - htrans [1:0] $end
$var reg 32 . hwdata [31:0] $end
$var reg 1 / hwrite $end
$var reg 1 0 rstn $end
$var integer 32 1 i [31:0] $end
$scope module u_ahb_sram $end
$var wire 1 2 bus_read $end
$var wire 1 3 bus_trans $end
$var wire 1 4 bus_wr_phase_next $end
$var wire 1 5 bus_write $end
$var wire 1 & clk $end
$var wire 12 6 haddr [11:0] $end
$var wire 3 7 hburst [2:0] $end
$var wire 4 8 hprot [3:0] $end
$var wire 32 9 hrdata [31:0] $end
$var wire 1 ! hready $end
$var wire 2 : hresp [1:0] $end
$var wire 1 + hsel $end
$var wire 3 ; hsize [2:0] $end
$var wire 2 < htrans [1:0] $end
$var wire 32 = hwdata [31:0] $end
$var wire 1 / hwrite $end
$var wire 1 > mem_cs $end
$var wire 1 ? mem_rd $end
$var wire 32 @ mem_wdata [31:0] $end
$var wire 1 A mem_wr $end
$var wire 1 0 rstn $end
$var wire 1 B write2read $end
$var wire 32 C mem_rdata [31:0] $end
$var wire 10 D mem_addr [9:0] $end
$var wire 1 # hreadyout $end
$var reg 1 E bus_trans_r $end
$var reg 1 F bus_wr_phase $end
$var reg 10 G haddr_r [9:0] $end
$var reg 1 H hwrite_r $end
$var reg 4 I mem_wbe [3:0] $end
$var reg 1 J write2read_r $end
$scope module u_mem $end
$var wire 10 K addr [9:0] $end
$var wire 1 & clk $end
$var wire 32 L din [31:0] $end
$var wire 1 > en $end
$var wire 4 M wbe [3:0] $end
$var wire 1 A we $end
$var reg 32 N dout [31:0] $end
$upscope $end
$upscope $end
$upscope $end
$scope module tb_ahb_sram $end
$scope module u_ahb_sram $end
$scope module u_mem $end
$var reg 32 O \mem[0] [31:0] $end
$upscope $end
$upscope $end
$upscope $end
$scope module tb_ahb_sram $end
$scope module u_ahb_sram $end
$scope module u_mem $end
$var reg 32 P \mem[1] [31:0] $end
$upscope $end
$upscope $end
$upscope $end
$scope module tb_ahb_sram $end
$scope module u_ahb_sram $end
$scope module u_mem $end
$var reg 32 Q \mem[2] [31:0] $end
$upscope $end
$upscope $end
$upscope $end
$scope module tb_ahb_sram $end
$scope module u_ahb_sram $end
$scope module u_mem $end
$var reg 32 R \mem[3] [31:0] $end
$upscope $end
$upscope $end
$upscope $end
$scope module tb_ahb_sram $end
$scope module u_ahb_sram $end
$scope module u_mem $end
$var reg 32 S \mem[4] [31:0] $end
$upscope $end
$upscope $end
$upscope $end
$scope module tb_ahb_sram $end
$scope module u_ahb_sram $end
$scope module u_mem $end
$var reg 32 T \mem[5] [31:0] $end
$upscope $end
$upscope $end
$upscope $end
$scope module tb_ahb_sram $end
$scope module u_ahb_sram $end
$scope module u_mem $end
$var reg 32 U \mem[6] [31:0] $end
$upscope $end
$upscope $end
$upscope $end
$scope module tb_ahb_sram $end
$scope module u_ahb_sram $end
$scope module u_mem $end
$var reg 32 V \mem[7] [31:0] $end
$upscope $end
$upscope $end
$upscope $end
$scope module tb_ahb_sram $end
$scope module u_ahb_sram $end
$scope module u_mem $end
$var reg 32 W \mem[8] [31:0] $end
$upscope $end
$upscope $end
$upscope $end
$scope module tb_ahb_sram $end
$scope module u_ahb_sram $end
$scope module u_mem $end
$var reg 32 X \mem[9] [31:0] $end
$upscope $end
$upscope $end
$upscope $end
$scope module tb_ahb_sram $end
$scope module u_ahb_sram $end
$scope module u_mem $end
$var reg 32 Y \mem[10] [31:0] $end
$upscope $end
$upscope $end
$upscope $end
$scope module tb_ahb_sram $end
$scope module u_ahb_sram $end
$scope module u_mem $end
$var reg 32 Z \mem[11] [31:0] $end
$upscope $end
$upscope $end
$upscope $end
$scope module tb_ahb_sram $end
$scope module u_ahb_sram $end
$scope module u_mem $end
$var reg 32 [ \mem[12] [31:0] $end
$upscope $end
$upscope $end
$upscope $end
$scope module tb_ahb_sram $end
$scope module u_ahb_sram $end
$scope module u_mem $end
$var reg 32 \ \mem[13] [31:0] $end
$upscope $end
$upscope $end
$upscope $end
$scope module tb_ahb_sram $end
$scope module u_ahb_sram $end
$scope module u_mem $end
$var reg 32 ] \mem[14] [31:0] $end
$upscope $end
$upscope $end
$upscope $end
$scope module tb_ahb_sram $end
$scope module u_ahb_sram $end
$scope module u_mem $end
$var reg 32 ^ \mem[15] [31:0] $end
$upscope $end
$upscope $end
$upscope $end
$scope module tb_ahb_sram $end
$scope module u_ahb_sram $end
$scope module u_mem $end
$var reg 32 _ \mem[16] [31:0] $end
$upscope $end
$upscope $end
$upscope $end
$scope module tb_ahb_sram $end
$scope module u_ahb_sram $end
$scope module u_mem $end
$var reg 32 ` \mem[17] [31:0] $end
$upscope $end
$upscope $end
$upscope $end
$scope module tb_ahb_sram $end
$scope module u_ahb_sram $end
$scope module u_mem $end
$var reg 32 a \mem[18] [31:0] $end
$upscope $end
$upscope $end
$upscope $end
$scope module tb_ahb_sram $end
$scope module u_ahb_sram $end
$scope module u_mem $end
$var reg 32 b \mem[19] [31:0] $end
$upscope $end
$upscope $end
$upscope $end
$scope module tb_ahb_sram $end
$scope module u_ahb_sram $end
$scope module u_mem $end
$var reg 32 c \mem[20] [31:0] $end
$upscope $end
$upscope $end
$upscope $end
$scope module tb_ahb_sram $end
$scope module u_ahb_sram $end
$scope module u_mem $end
$var reg 32 d \mem[21] [31:0] $end
$upscope $end
$upscope $end
$upscope $end
$scope module tb_ahb_sram $end
$scope module u_ahb_sram $end
$scope module u_mem $end
$var reg 32 e \mem[22] [31:0] $end
$upscope $end
$upscope $end
$upscope $end
$scope module tb_ahb_sram $end
$scope module u_ahb_sram $end
$scope module u_mem $end
$var reg 32 f \mem[23] [31:0] $end
$upscope $end
$upscope $end
$upscope $end
$scope module tb_ahb_sram $end
$scope module u_ahb_sram $end
$scope module u_mem $end
$var reg 32 g \mem[24] [31:0] $end
$upscope $end
$upscope $end
$upscope $end
$scope module tb_ahb_sram $end
$scope module u_ahb_sram $end
$scope module u_mem $end
$var reg 32 h \mem[25] [31:0] $end
$upscope $end
$upscope $end
$upscope $end
$scope module tb_ahb_sram $end
$scope module u_ahb_sram $end
$scope module u_mem $end
$var reg 32 i \mem[26] [31:0] $end
$upscope $end
$upscope $end
$upscope $end
$scope module tb_ahb_sram $end
$scope module u_ahb_sram $end
$scope module u_mem $end
$var reg 32 j \mem[27] [31:0] $end
$upscope $end
$upscope $end
$upscope $end
$scope module tb_ahb_sram $end
$scope module u_ahb_sram $end
$scope module u_mem $end
$var reg 32 k \mem[28] [31:0] $end
$upscope $end
$upscope $end
$upscope $end
$scope module tb_ahb_sram $end
$scope module u_ahb_sram $end
$scope module u_mem $end
$var reg 32 l \mem[29] [31:0] $end
$upscope $end
$upscope $end
$upscope $end
$scope module tb_ahb_sram $end
$scope module u_ahb_sram $end
$scope module u_mem $end
$var reg 32 m \mem[30] [31:0] $end
$upscope $end
$upscope $end
$upscope $end
$scope module tb_ahb_sram $end
$scope module u_ahb_sram $end
$scope module u_mem $end
$var reg 32 n \mem[31] [31:0] $end
$upscope $end
$upscope $end
$upscope $end
$enddefinitions $end
#0
$dumpvars
bx n
bx m
bx l
bx k
bx j
bx i
bx h
bx g
bx f
bx e
bx d
bx c
bx b
bx a
bx `
bx _
bx ^
bx ]
bx \
bx [
bx Z
bx Y
bx X
bx W
bx V
bx U
bx T
bx S
bx R
bx Q
bx P
bx O
bx N
bx M
b0 L
b0 K
0J
bx I
0H
b0 G
0F
0E
b0 D
bx C
0B
0A
b0 @
0?
0>
b0 =
b0 <
b0 ;
b0 :
bx 9
b0 8
b0 7
b0 6
05
04
03
02
b100000 1
00
0/
b0 .
b0 -
b0 ,
0+
b0 *
b0 )
b0 (
bx '
0&
x%
bx $
1#
b0 "
1!
$end
#5
b0 I
b0 M
b0 '
0%
1&
#10
0&
#15
1&
#20
0&
10
#22
1>
1?
12
13
b10 -
b10 <
1+
#25
b1 D
b1 K
b1 I
b1 M
b11 ,
b11 ;
b1 '
b100 (
b100 6
1E
1&
#30
0&
#35
b10 D
b10 K
b1111 I
b1111 M
b1 G
b1000 (
b1000 6
b10 '
1&
#40
0&
#45
b11 D
b11 K
b11 '
b1100 (
b1100 6
b10 G
1&
#50
0&
#55
b100 D
b100 K
b11 G
b10000 (
b10000 6
b100 '
1&
#60
0&
#65
b101 D
b101 K
b101 '
b10100 (
b10100 6
b100 G
1&
#70
0&
#75
b110 D
b110 K
b101 G
b11000 (
b11000 6
b110 '
1&
#80
0&
#85
b111 D
b111 K
b111 '
b11100 (
b11100 6
b110 G
1&
#90
0&
#95
b1000 D
b1000 K
b111 G
b100000 (
b100000 6
b1000 '
1&
#100
0&
#105
b1001 D
b1001 K
b1001 '
b100100 (
b100100 6
b1000 G
1&
#110
0&
#115
b1010 D
b1010 K
b1001 G
b101000 (
b101000 6
b1010 '
1&
#120
0&
#125
b1011 D
b1011 K
b1011 '
b101100 (
b101100 6
b1010 G
1&
#130
0&
#135
b1100 D
b1100 K
b1011 G
b110000 (
b110000 6
b1100 '
1&
#140
0&
#145
b1101 D
b1101 K
b1101 '
b110100 (
b110100 6
b1100 G
1&
#150
0&
#155
b1110 D
b1110 K
b1101 G
b111000 (
b111000 6
b1110 '
1&
#160
0&
#165
b1111 D
b1111 K
b1111 '
b111100 (
b111100 6
b1110 G
1&
#170
0&
#175
b10000 D
b10000 K
b1111 G
b1000000 (
b1000000 6
b10000 '
1&
#180
0&
#185
b10001 D
b10001 K
b10001 '
b1000100 (
b1000100 6
b10000 G
1&
#190
0&
#195
b10010 D
b10010 K
b10001 G
b1001000 (
b1001000 6
b10010 '
1&
#200
0&
#205
b10011 D
b10011 K
b10011 '
b1001100 (
b1001100 6
b10010 G
1&
#210
0&
#215
b10100 D
b10100 K
b10011 G
b1010000 (
b1010000 6
b10100 '
1&
#220
0&
#225
b10101 D
b10101 K
b10101 '
b1010100 (
b1010100 6
b10100 G
1&
#230
0&
#235
b10110 D
b10110 K
b10101 G
b1011000 (
b1011000 6
b10110 '
1&
#240
0&
#245
b10111 D
b10111 K
b10111 '
b1011100 (
b1011100 6
b10110 G
1&
#250
0&
#255
b11000 D
b11000 K
b10111 G
b1100000 (
b1100000 6
b11000 '
1&
#260
0&
#265
b11001 D
b11001 K
b11001 '
b1100100 (
b1100100 6
b11000 G
1&
#270
0&
#275
b11010 D
b11010 K
b11001 G
b1101000 (
b1101000 6
b11010 '
1&
#280
0&
#285
b11011 D
b11011 K
b11011 '
b1101100 (
b1101100 6
b11010 G
1&
#290
0&
#295
b11100 D
b11100 K
b11011 G
b1110000 (
b1110000 6
b11100 '
1&
#300
0&
#305
b11101 D
b11101 K
b11101 '
b1110100 (
b1110100 6
b11100 G
1&
#310
0&
#315
b11110 D
b11110 K
b11101 G
b1111000 (
b1111000 6
b11110 '
1&
#320
0&
#325
b11111 D
b11111 K
b11111 '
b1111100 (
b1111100 6
b11110 G
1&
#330
0&
#335
b0 D
b0 K
b11111 G
b0 (
b0 6
b100000 '
1&
#340
0&
#345
b1 D
b1 K
b100001 '
1%
b100 (
b100 6
b0 G
1&
#350
0&
#355
b1 G
0%
b100010 '
1&
#360
0&
#365
b10 D
b10 K
b100011 '
b1000 (
b1000 6
1&
#370
0&
#375
b11 D
b11 K
b10 G
b1100 (
b1100 6
b100100 '
1&
#380
0&
#385
b100 D
b100 K
b100101 '
b10000 (
b10000 6
b11 G
1&
#390
0&
#395
b101 D
b101 K
b100 G
b10100 (
b10100 6
b100110 '
1&
#400
0&
#405
b110 D
b110 K
b100111 '
b11000 (
b11000 6
b101 G
1&
#410
0&
#415
b111 D
b111 K
b110 G
b11100 (
b11100 6
b101000 '
1&
#420
0&
#425
b1000 D
b1000 K
b101001 '
b100000 (
b100000 6
b111 G
1&
#430
0&
#435
b1001 D
b1001 K
b1000 G
b100100 (
b100100 6
b101010 '
1&
#440
0&
#445
b1010 D
b1010 K
b101011 '
b101000 (
b101000 6
b1001 G
1&
#450
0&
#455
b1011 D
b1011 K
b1010 G
b101100 (
b101100 6
b101100 '
1&
#460
0&
#465
b1100 D
b1100 K
b101101 '
b110000 (
b110000 6
b1011 G
1&
#470
0&
#475
b1101 D
b1101 K
b1100 G
b110100 (
b110100 6
b101110 '
1&
#480
0&
#485
b1110 D
b1110 K
b101111 '
b111000 (
b111000 6
b1101 G
1&
#490
0&
#495
b1111 D
b1111 K
b1110 G
b111100 (
b111100 6
b110000 '
1&
#500
0&
#505
b10000 D
b10000 K
b110001 '
b1000000 (
b1000000 6
b1111 G
1&
#510
0&
#515
b10001 D
b10001 K
b10000 G
b1000100 (
b1000100 6
b110010 '
1&
#520
0&
#525
b10010 D
b10010 K
b110011 '
b1001000 (
b1001000 6
b10001 G
1&
#530
0&
#535
b10011 D
b10011 K
b10010 G
b1001100 (
b1001100 6
b110100 '
1&
#540
0&
#545
b10100 D
b10100 K
b110101 '
b1010000 (
b1010000 6
b10011 G
1&
#550
0&
#555
b10101 D
b10101 K
b10100 G
b1010100 (
b1010100 6
b110110 '
1&
#560
0&
#565
b10110 D
b10110 K
b110111 '
b1011000 (
b1011000 6
b10101 G
1&
#570
0&
#575
b10111 D
b10111 K
b10110 G
b1011100 (
b1011100 6
b111000 '
1&
#580
0&
#585
b11000 D
b11000 K
b111001 '
b1100000 (
b1100000 6
b10111 G
1&
#590
0&
#595
b11001 D
b11001 K
b11000 G
b1100100 (
b1100100 6
b111010 '
1&
#600
0&
#605
b11010 D
b11010 K
b111011 '
b1101000 (
b1101000 6
b11001 G
1&
#610
0&
#615
b11011 D
b11011 K
b11010 G
b1101100 (
b1101100 6
b111100 '
1&
#620
0&
#625
b11100 D
b11100 K
b111101 '
b1110000 (
b1110000 6
b11011 G
1&
#630
0&
#635
b11101 D
b11101 K
b11100 G
b1110100 (
b1110100 6
b111110 '
1&
#640
0&
#645
b11110 D
b11110 K
b111111 '
b1111000 (
b1111000 6
b11101 G
1&
#650
0&
#655
0>
0?
b0 D
b0 K
14
02
15
b11110 G
b0 (
b0 6
1/
b0 '
1&
#660
0&
#665
1>
1A
b1 @
b1 L
b1 .
b1 =
b1 '
b100 (
b100 6
1F
1H
b0 G
1&
#670
0&
#675
b1 D
b1 K
b1 O
b1 G
b1000 (
b1000 6
b10 '
b10 @
b10 L
b10 .
b10 =
1&
#680
0&
#685
b10 D
b10 K
b10 P
b11 @
b11 L
b11 .
b11 =
b11 '
b1100 (
b1100 6
b10 G
1&
#690
0&
#695
b11 D
b11 K
b11 Q
b11 G
b10000 (
b10000 6
b100 '
b100 @
b100 L
b100 .
b100 =
1&
#700
0&
#705
b100 D
b100 K
b100 R
b101 @
b101 L
b101 .
b101 =
b101 '
b10100 (
b10100 6
b100 G
1&
#710
0&
#715
b101 D
b101 K
b101 S
b101 G
b11000 (
b11000 6
b110 '
b110 @
b110 L
b110 .
b110 =
1&
#720
0&
#725
b110 D
b110 K
b110 T
b111 @
b111 L
b111 .
b111 =
b111 '
b11100 (
b11100 6
b110 G
1&
#730
0&
#735
b111 D
b111 K
b111 U
b111 G
b100000 (
b100000 6
b1000 '
b1000 @
b1000 L
b1000 .
b1000 =
1&
#740
0&
#745
b1000 D
b1000 K
b1000 V
b1001 @
b1001 L
b1001 .
b1001 =
b1001 '
b100100 (
b100100 6
b1000 G
1&
#750
0&
#755
b1001 D
b1001 K
b1001 W
b1001 G
b101000 (
b101000 6
b1010 '
b1010 @
b1010 L
b1010 .
b1010 =
1&
#760
0&
#765
b1010 D
b1010 K
b1010 X
b1011 @
b1011 L
b1011 .
b1011 =
b1011 '
b101100 (
b101100 6
b1010 G
1&
#770
0&
#775
b1011 D
b1011 K
b1011 Y
b1011 G
b110000 (
b110000 6
b1100 '
b1100 @
b1100 L
b1100 .
b1100 =
1&
#780
0&
#785
b1100 D
b1100 K
b1100 Z
b1101 @
b1101 L
b1101 .
b1101 =
b1101 '
b110100 (
b110100 6
b1100 G
1&
#790
0&
#795
b1101 D
b1101 K
b1101 [
b1101 G
b111000 (
b111000 6
b1110 '
b1110 @
b1110 L
b1110 .
b1110 =
1&
#800
0&
#805
b1110 D
b1110 K
b1110 \
b1111 @
b1111 L
b1111 .
b1111 =
b1111 '
b111100 (
b111100 6
b1110 G
1&
#810
0&
#815
b1111 D
b1111 K
b1111 ]
b1111 G
b1000000 (
b1000000 6
b10000 '
b10000 @
b10000 L
b10000 .
b10000 =
1&
#820
0&
#825
b10000 D
b10000 K
b10000 ^
b10001 @
b10001 L
b10001 .
b10001 =
b10001 '
b1000100 (
b1000100 6
b10000 G
1&
#830
0&
#835
b10001 D
b10001 K
b10001 _
b10001 G
b1001000 (
b1001000 6
b10010 '
b10010 @
b10010 L
b10010 .
b10010 =
1&
#840
0&
#845
b10010 D
b10010 K
b10010 `
b10011 @
b10011 L
b10011 .
b10011 =
b10011 '
b1001100 (
b1001100 6
b10010 G
1&
#850
0&
#855
b10011 D
b10011 K
b10011 a
b10011 G
b1010000 (
b1010000 6
b10100 '
b10100 @
b10100 L
b10100 .
b10100 =
1&
#860
0&
#865
b10100 D
b10100 K
b10100 b
b10101 @
b10101 L
b10101 .
b10101 =
b10101 '
b1010100 (
b1010100 6
b10100 G
1&
#870
0&
#875
b10101 D
b10101 K
b10101 c
b10101 G
b1011000 (
b1011000 6
b10110 '
b10110 @
b10110 L
b10110 .
b10110 =
1&
#880
0&
#885
b10110 D
b10110 K
b10110 d
b10111 @
b10111 L
b10111 .
b10111 =
b10111 '
b1011100 (
b1011100 6
b10110 G
1&
#890
0&
#895
b10111 D
b10111 K
b10111 e
b10111 G
b1100000 (
b1100000 6
b11000 '
b11000 @
b11000 L
b11000 .
b11000 =
1&
#900
0&
#905
b11000 D
b11000 K
b11000 f
b11001 @
b11001 L
b11001 .
b11001 =
b11001 '
b1100100 (
b1100100 6
b11000 G
1&
#910
0&
#915
b11001 D
b11001 K
b11001 g
b11001 G
b1101000 (
b1101000 6
b11010 '
b11010 @
b11010 L
b11010 .
b11010 =
1&
#920
0&
#925
b11010 D
b11010 K
b11010 h
b11011 @
b11011 L
b11011 .
b11011 =
b11011 '
b1101100 (
b1101100 6
b11010 G
1&
#930
0&
#935
b11011 D
b11011 K
b11011 i
b11011 G
b1110000 (
b1110000 6
b11100 '
b11100 @
b11100 L
b11100 .
b11100 =
1&
#940
0&
#945
b11100 D
b11100 K
b11100 j
b11101 @
b11101 L
b11101 .
b11101 =
b11101 '
b1110100 (
b1110100 6
b11100 G
1&
#950
0&
#955
b11101 D
b11101 K
b11101 k
b11101 G
b1111000 (
b1111000 6
b11110 '
b11110 @
b11110 L
b11110 .
b11110 =
1&
#960
0&
#965
b11110 D
b11110 K
b11110 l
b11111 @
b11111 L
b11111 .
b11111 =
b11111 '
b1111100 (
b1111100 6
b11110 G
1&
#970
0&
#975
1B
04
12
b11111 D
b11111 K
05
b11111 m
b11111 G
b0 (
b0 6
0/
b100000 '
b100000 @
b100000 L
b100000 .
b100000 =
1&
#980
0&
#985
03
1?
0A
0B
b0 D
b0 K
b100000 n
b100001 '
1%
b100 (
b100 6
0!
0#
1J
0F
0H
b0 G
1&
#990
0&
#995
1>
1?
13
12
b1 D
b1 K
b1 $
b1 9
b1 C
b1 N
1!
1#
0J
0%
b100010 '
1&
#1000
0&
#1005
b10 D
b10 K
b10 $
b10 9
b10 C
b10 N
b100011 '
b1000 (
b1000 6
b1 G
1&
#1010
0&
#1015
b11 D
b11 K
b11 $
b11 9
b11 C
b11 N
b10 G
b1100 (
b1100 6
b100100 '
1&
#1020
0&
#1025
b100 D
b100 K
b100 $
b100 9
b100 C
b100 N
b100101 '
b10000 (
b10000 6
b11 G
1&
#1030
0&
#1035
b101 D
b101 K
b101 $
b101 9
b101 C
b101 N
b100 G
b10100 (
b10100 6
b100110 '
1&
#1040
0&
#1045
b110 D
b110 K
b110 $
b110 9
b110 C
b110 N
b100111 '
b11000 (
b11000 6
b101 G
1&
#1050
0&
#1055
b111 D
b111 K
b111 $
b111 9
b111 C
b111 N
b110 G
b11100 (
b11100 6
b101000 '
1&
#1060
0&
#1065
b1000 D
b1000 K
b1000 $
b1000 9
b1000 C
b1000 N
b101001 '
b100000 (
b100000 6
b111 G
1&
#1070
0&
#1075
b1001 D
b1001 K
b1001 $
b1001 9
b1001 C
b1001 N
b1000 G
b100100 (
b100100 6
b101010 '
1&
#1080
0&
#1085
b1010 D
b1010 K
b1010 $
b1010 9
b1010 C
b1010 N
b101011 '
b101000 (
b101000 6
b1001 G
1&
#1090
0&
#1095
b1011 D
b1011 K
b1011 $
b1011 9
b1011 C
b1011 N
b1010 G
b101100 (
b101100 6
b101100 '
1&
#1100
0&
#1105
b1100 D
b1100 K
b1100 $
b1100 9
b1100 C
b1100 N
b101101 '
b110000 (
b110000 6
b1011 G
1&
#1110
0&
#1115
b1101 D
b1101 K
b1101 $
b1101 9
b1101 C
b1101 N
b1100 G
b110100 (
b110100 6
b101110 '
1&
#1120
0&
#1125
b1110 D
b1110 K
b1110 $
b1110 9
b1110 C
b1110 N
b101111 '
b111000 (
b111000 6
b1101 G
1&
#1130
0&
#1135
b1111 D
b1111 K
b1111 $
b1111 9
b1111 C
b1111 N
b1110 G
b111100 (
b111100 6
b110000 '
1&
#1140
0&
#1145
b10000 D
b10000 K
b10000 $
b10000 9
b10000 C
b10000 N
b110001 '
b1000000 (
b1000000 6
b1111 G
1&
#1150
0&
