AMBA/AXI/AXI-stream/remove/code/stream_remove.v
/*unaligned address :0xA
unaligned keep = 4'b1111
nearest aligned address = 0x8
aligned keep = 4'b00 11

data len = 7  0xA
1.unaligned(output 2 beat)

first beat
unali keep 4'b1111 ：10 11 12 13
last beat
ali keep 4'b1110 14 15 16 17（第八个数据不需要）

2.aligned (input 3 beat)
nearest addr : 0x8
aligned keep :4'b0011  
addr : 10 11
next addr: 0x12
aligned keep :4'b1111 
addr : 12 -15 
last addr :
aligned keep :4'b1000 -- 16

data len = 9    addr:0xA
1.unaligned(output 3 beat)
first beat:
unali keep 4'b1111 
addr:10 11 12 13
second beat
unali keep 4'b1111 
addr : 14 15 16 17
last beat:
unali keep 4'b1000
addr : 18

2.aligned  (input 3 beat)
nearest addr : 0x8
aligned keep :4'b0011 -- 10 11
next addr: 0x12
aligned keep :4'b1111 --12 -15
last addr :
aligned keep :4'b1000 -- 16


*/

module stream_remove #(
    parameter DATA_WD = 32,
    parameter DATA_BYTE_WD = DATA_WD / 8,
    parameter BYTE_CNT_WD = $clog2(DATA_BYTE_WD)
)(
    input                           clk,
    input                           rstn,

    input                           valid_in,
    input   [DATA_WD-1 : 0]         data_in,
    input                           last_in,
    input   [DATA_BYTE_WD-1 : 0]    keep_in,
    output                          ready_in,

    output                          valid_out,
    output  [DATA_WD-1 : 0]         data_out,
    output                          last_out,
    output   [DATA_BYTE_WD-1 : 0]   keep_out,
    input                           ready_out,
    
    input                           valid_remove,
    input   [BYTE_CNT_WD-1 : 0]     byte_remove_cnt,
    output                          ready_remove
    
);
localparam DATA_BIT_WD = log2(DATA_WD);
wire                            fire_in;
wire                            fire_out;
wire                            fire_remove;
wire    [2*DATA_WD-1 : 0]       d_data;    
wire    [2*DATA_BYTE_WD-1 : 0]  d_keep;
wire    [2*DATA_BYTE_WD-1 : 0]  d_keep_last;           
wire    [BYTE_CNT_WD : 0]     byte_shift_cnt;
wire    [DATA_BIT_WD-1 : 0]     bit_shift_cnt;

wire                            extra_beat;
wire                            has_extra_keep;

reg [DATA_WD-1 : 0]         data_r;
reg [DATA_BYTE_WD-1 : 0]    keep_r;
reg                         valid_r;
reg                         extra_beat_r;
reg                         remove_r;
reg                         last_out_r;
wire                        has_extra_beat;
assign has_extra_keep = | (keep_in << byte_remove_cnt) ;
assign extra_beat = has_extra_beat && fire_in;
assign has_extra_beat = last_in && has_extra_keep;
    
assign fire_in = valid_in && ready_in;
assign fire_out = valid_out && ready_out;
assign fire_remove = valid_remove && ready_remove;


assign d_data = {data_r,data_in};
assign d_keep = {keep_r,keep_in};
assign d_keep_last = {keep_r,{DATA_BYTE_WD{1'b0}}};
assign byte_shift_cnt = DATA_BYTE_WD - byte_remove_cnt;
assign bit_shift_cnt = byte_shift_cnt << 3;

assign data_out = d_data >> bit_shift_cnt;
assign keep_out = extra_beat_r ? (d_keep_last >> byte_shift_cnt) : (d_keep >> byte_shift_cnt);

assign ready_in = !valid_r | (ready_out && valid_remove);
//assign last_out = last_in ? !extra_beat : extra_beat_r;
//assign ready_remove = (last_out && fire_out) ? 1'b1 : remove_r;
assign ready_remove = (last_out && fire_out);
assign valid_out = extra_beat_r ? valid_r : valid_r && valid_remove && valid_in;//要用当前数据必须要valid_in

assign last_out = last_in ? !has_extra_beat : extra_beat_r;


always@(posedge clk or negedge rstn) begin
    if (!rstn) begin
        data_r <= 'b0;
        keep_r <= 'b0;
        valid_r <= 1'b0;
    end else begin
        if (fire_out) begin
            valid_r <= 1'b0;
        end
        if (fire_in && last_in) begin
            valid_r <= extra_beat;
        end else if (fire_in) begin
            valid_r <= 1'b1;
        end
        if (fire_in) begin
            data_r <= data_in;
            keep_r <= keep_in;
        end
    end
end

always@(posedge clk or negedge rstn) begin
    if (!rstn) begin
        extra_beat_r <= 1'b0;
        remove_r <= 1'b0;
        last_out_r <= 1'b0;
    end else begin
        if (extra_beat) begin
            extra_beat_r <= 1'b1;
        end else if (fire_out) begin
            extra_beat_r <= 1'b0;
        end
        
    end
end



function integer log2(input integer x);
begin
    log2 = 0;
    while (x >> log2) begin
        log2 = log2 + 1;
    end
end
        
endfunction




endmodule //stream_remove

AMBA/AXI/AXI-stream/remove/code/tb_stream_remove.v
//`include "stream_remove.v"
`timescale  1ns / 1ps

module tb_stream_remove;

// stream_remove Parameters
parameter PERIOD        = 10               ;
parameter DATA_WD       = 32               ;
parameter DATA_BYTE_WD  = DATA_WD / 8      ;
parameter BYTE_CNT_WD   = $clog2(DATA_BYTE_WD);

// stream_remove Inputs
reg   clk                                  ;
reg   rstn                                 ;
reg   valid_in                             ;
reg   [DATA_WD-1 : 0]  data_in             ;
wire   last_in                              ;
wire   [DATA_BYTE_WD-1 : 0]  keep_in        ;
wire   [DATA_BYTE_WD-1 : 0]  keep_out       ;
reg   ready_out                            ;
reg   valid_remove                         ;
reg   [BYTE_CNT_WD-1 : 0]  byte_remove_cnt ;

// stream_remove Outputs
wire  ready_in                             ;
wire  valid_out                            ;
wire  [DATA_WD-1 : 0]  data_out            ;
wire  last_out                             ;
wire  ready_remove                         ;


reg   [BYTE_CNT_WD-1:0]        last_byte_cnt;
//reg   [BYTE_CNT_WD-1:0]        remove_cnt;
wire                            fire_in;
wire                            fire_out;
wire                            fire_remove;
assign fire_in = valid_in && ready_in;
assign fire_out = valid_out && ready_out;
assign fire_remove = valid_remove && ready_remove;

reg [1:0] data_beat_cnt;
assign last_in = &data_beat_cnt;
assign keep_in = last_in ? ~((1 << last_byte_cnt) - 1) 
                : ((1 << DATA_BYTE_WD ) -1);

always@(posedge clk or negedge rstn) begin
    if (!rstn) begin
        byte_remove_cnt <= 1'b0;
    end else if (fire_remove) begin
        byte_remove_cnt <= byte_remove_cnt + 1;
    end
end

always@(posedge clk or negedge rstn) begin
    if (!rstn) begin
        data_beat_cnt <= 'b0;
        last_byte_cnt <= 'b0;
    end else begin
        data_beat_cnt <= data_beat_cnt + fire_in;
        last_byte_cnt <= last_byte_cnt + (fire_out && last_out);
    end
end

always@(posedge clk or negedge rstn) begin
    if (!rstn) begin
        data_in <= $random;
    end else if (fire_in) begin
        data_in <= $random;        
    end
end
localparam  RANDOM = 1'b1;
generate if (RANDOM) begin
    always@(posedge clk or negedge rstn) begin
        if (!rstn) begin
            valid_remove <= 1'b0;
            valid_in <= 1'b0;
            ready_out <= 1'b1;
        end else begin
            if (!valid_remove || ready_remove) begin
                valid_remove <= $random;
            end
            if (!valid_in || ready_in) begin
                valid_in <= $random;
            end
            ready_out <= $random;
        end
    end
end else begin
    always@(posedge clk or negedge rstn) begin
        if (!rstn) begin
            valid_remove <= 1'b0;
            valid_in <= 1'b0;
            ready_out <= 1'b1;
        end else begin
            
            valid_remove <= 1'b1;
            valid_in <= 1'b1;
            ready_out <= 1'b1;
        end
    end
end
    
endgenerate



initial
begin
    clk = 0;
    forever #(PERIOD/2)  clk=~clk;
end

initial
begin
    rstn = 0;
    #(PERIOD*2) rstn  =  1;
end
initial begin
    $dumpfile("test.vcd");
    $dumpvars;
end


stream_remove #(
    .DATA_WD      ( DATA_WD      ),
    .DATA_BYTE_WD ( DATA_BYTE_WD ))
 u_stream_remove (
    .clk                     ( clk             ),
    .rstn                    ( rstn            ),
    .valid_in                ( valid_in        ),
    .data_in                 ( data_in         ),
    .last_in                 ( last_in         ),
    .keep_in                 ( keep_in         ),
    .keep_out                ( keep_out        ),
    .ready_out               ( ready_out       ),
    .valid_remove            ( valid_remove    ),
    .byte_remove_cnt         ( byte_remove_cnt ),

    .ready_in                ( ready_in        ),
    .valid_out               ( valid_out       ),
    .data_out                ( data_out        ),
    .last_out                ( last_out        ),
    .ready_remove            ( ready_remove    )
);

initial
begin
    #5000;
    $finish;
end

endmodule

AMBA/AXI/AXI-stream/remove/sim/test.vcd
$date
	Tue Mar 21 22:06:08 2023
$end
$version
	Icarus Verilog
$end
$timescale
	1ps
$end
$scope module tb_stream_remove $end
$var wire 1 ! fire_in $end
$var wire 1 " fire_out $end
$var wire 1 # fire_remove $end
$var wire 1 $ valid_out $end
$var wire 1 % ready_remove $end
$var wire 1 & ready_in $end
$var wire 1 ' last_out $end
$var wire 1 ( last_in $end
$var wire 4 ) keep_out [3:0] $end
$var wire 4 * keep_in [3:0] $end
$var wire 32 + data_out [31:0] $end
$var reg 2 , byte_remove_cnt [1:0] $end
$var reg 1 - clk $end
$var reg 2 . data_beat_cnt [1:0] $end
$var reg 32 / data_in [31:0] $end
$var reg 2 0 last_byte_cnt [1:0] $end
$var reg 1 1 ready_out $end
$var reg 1 2 rstn $end
$var reg 1 3 valid_in $end
$var reg 1 4 valid_remove $end
$scope begin genblk1 $end
$upscope $end
$scope module u_stream_remove $end
$var wire 2 5 byte_remove_cnt [1:0] $end
$var wire 1 - clk $end
$var wire 32 6 data_in [31:0] $end
$var wire 1 7 extra_beat $end
$var wire 1 8 fire_in $end
$var wire 1 9 fire_out $end
$var wire 1 : fire_remove $end
$var wire 1 ; has_extra_beat $end
$var wire 4 < keep_in [3:0] $end
$var wire 1 ( last_in $end
$var wire 1 & ready_in $end
$var wire 1 1 ready_out $end
$var wire 1 % ready_remove $end
$var wire 1 2 rstn $end
$var wire 1 3 valid_in $end
$var wire 1 4 valid_remove $end
$var wire 1 $ valid_out $end
$var wire 1 ' last_out $end
$var wire 4 = keep_out [3:0] $end
$var wire 1 > has_extra_keep $end
$var wire 32 ? data_out [31:0] $end
$var wire 8 @ d_keep_last [7:0] $end
$var wire 8 A d_keep [7:0] $end
$var wire 64 B d_data [63:0] $end
$var wire 3 C byte_shift_cnt [2:0] $end
$var wire 6 D bit_shift_cnt [5:0] $end
$var reg 32 E data_r [31:0] $end
$var reg 1 F extra_beat_r $end
$var reg 4 G keep_r [3:0] $end
$var reg 1 H last_out_r $end
$var reg 1 I remove_r $end
$var reg 1 J valid_r $end
$scope function log2 $end
$var integer 32 K x [31:0] $end
$upscope $end
$upscope $end
$upscope $end
$enddefinitions $end
#0
$dumpvars
bx K
0J
0I
0H
b0 G
0F
b0 E
b100000 D
b100 C
b10010000101010011010100100100 B
b1111 A
b0 @
b0 ?
1>
b0 =
b1111 <
0;
0:
09
08
07
b10010000101010011010100100100 6
b0 5
04
03
02
11
b0 0
b10010000101010011010100100100 /
b0 .
0-
b0 ,
b0 +
b1111 *
b0 )
0(
0'
1&
0%
0$
0#
0"
0!
$end
#5000
b11000000100010010101111010000001 B
b11000000100010010101111010000001 /
b11000000100010010101111010000001 6
1-
#10000
0-
#15000
b10000100100001001101011000001001 B
b10000100100001001101011000001001 /
b10000100100001001101011000001001 6
1-
#20000
0-
12
#25000
18
1!
13
14
1-
#30000
0-
#35000
b1111 )
b1111 =
08
0!
b10000100100001001101011000001001 +
b10000100100001001101011000001001 ?
03
b11111111 A
b11110000 @
b1111 G
b10000100100001001101011000001001 E
1J
b1 .
b1000010010000100110101100000100110110010110000101000010001100101 B
b10110010110000101000010001100101 /
b10110010110000101000010001100101 6
1-
#40000
0-
#45000
0&
1$
08
0!
01
13
1-
#50000
0-
#55000
18
1!
1&
19
1"
11
1-
#60000
0-
#65000
08
0!
b10110010110000101000010001100101 +
b10110010110000101000010001100101 ?
0&
09
0"
b1111100111111011110100111111001 /
b1111100111111011110100111111001 6
b10 .
b1011001011000010100001000110010101111100111111011110100111111001 B
b10110010110000101000010001100101 E
1J
01
1-
#70000
0-
#75000
1-
#80000
0-
#85000
18
1!
1&
19
1"
11
1-
#90000
0-
#95000
0:
0#
17
0%
b1111100111111011110100111111001 +
b1111100111111011110100111111001 ?
1;
0'
b1111100111111011110100111111001 E
1J
1(
b11 .
b111110011111101111010011111100111010101000100111101001010101010 B
b11010101000100111101001010101010 /
b11010101000100111101001010101010 6
1-
#100000
0-
#105000
1:
1#
1%
07
0;
1'
b11010101000100111101001010101010 +
b11010101000100111101001010101010 ?
08
0!
b1111001001100000110100111110010 /
b1111001001100000110100111110010 6
0(
b0 .
1F
b1101010100010011110100101010101001111001001100000110100111110010 B
b11010101000100111101001010101010 E
1J
03
1-
#110000
0-
#115000
b10011110100101010101001111001 +
b10011110100101010101001111001 ?
09
0"
0%
b11000 D
0:
0#
0$
0'
b11 C
04
0J
0F
b1 ,
b1 5
b1 0
1-
#120000
0-
#125000
18
1!
13
1-
#130000
0-
#135000
08
0!
0&
b110000011010011111001010110010 +
b110000011010011111001010110010 ?
01
03
14
b1111001001100000110100111110010 E
1J
b1 .
b111100100110000011010011111001010110010101001110010011001100101 B
b10110010101001110010011001100101 /
b10110010101001110010011001100101 6
1-
#140000
0-
#145000
1-
#150000
0-
#155000
1$
13
1-
#160000
0-
#165000
18
1!
1&
19
1"
11
1-
#170000
0-
#175000
b10100111001001100110010110000110 +
b10100111001001100110010110000110 ?
b10110010101001110010011001100101 E
1J
b10 .
b1011001010100111001001100110010110000110101111000011100000001101 B
b10000110101111000011100000001101 /
b10000110101111000011100000001101 6
1-
#180000
0-
#185000
08
0!
b11111110 A
b1110 *
b1110 <
1;
0'
b10111100001110000000110111010111 +
b10111100001110000000110111010111 ?
0&
09
0"
b11010111010101100011111010101110 /
b11010111010101100011111010101110 6
1(
b11 .
b1000011010111100001110000000110111010111010101100011111010101110 B
b10000110101111000011100000001101 E
1J
01
1-
#190000
0-
#195000
17
18
1!
1&
19
1"
11
1-
#200000
0-
#205000
1:
1#
07
1%
b1100 )
b1100 =
b1111 *
b1111 <
0;
1'
b1010110001111101010111000000101 +
b1010110001111101010111000000101 ?
b101000010010110010100001010 /
b101000010010110010100001010 6
0(
b0 .
1F
b11101111 A
b11100000 @
b1110 G
b1101011101010110001111101010111000000101000010010110010100001010 B
b11010111010101100011111010101110 E
1J
1-
#210000
0-
#215000
0$
0&
b1111 )
b1111 =
0%
b10000 D
09
0"
08
0!
0:
0#
0'
b10 C
b1100101000010101110010101110011 +
b1100101000010101110010101110011 ?
01
03
04
b11111111 A
b11110000 @
b1111 G
b101000010010110010100001010 E
1J
0F
b10 ,
b10 5
b10 0
b1 .
b10100001001011001010000101011100101011100110000101011001010 B
b11100101011100110000101011001010 /
b11100101011100110000101011001010 6
1-
#220000
0-
#225000
14
1-
#230000
0-
#235000
18
1!
19
1"
1&
1$
11
13
1-
#240000
0-
#245000
0$
b1010110010100101011100010101 +
b1010110010100101011100010101 ?
0&
09
0"
08
0!
b1010111000101010001001110101110 /
b1010111000101010001001110101110 6
b10 .
b1110010101110011000010101100101001010111000101010001001110101110 B
b11100101011100110000101011001010 E
1J
01
03
1-
#250000
0-
#255000
1-
#260000
0-
#265000
18
1!
19
1"
1&
1$
11
13
1-
#270000
0-
#275000
1:
1#
07
1%
0>
b11111100 A
b1100 *
b1100 <
0;
1'
b10011101011100100001011110010 +
b10011101011100100001011110010 ?
b1010111000101010001001110101110 E
1J
1(
b11 .
b101011100010101000100111010111001000010111100100100000110000101 B
b1000010111100100100000110000101 /
b1000010111100100100000110000101 6
1-
#280000
0-
#285000
09
0"
0%
b1000 D
b111 )
b111 =
0$
1>
b1111 *
b1111 <
0'
b1 C
b10000101011110001101100110011011 +
b10000101011110001101100110011011 ?
08
0!
0:
0#
b1111000110110011001101111110001 /
b1111000110110011001101111110001 6
b11 0
0(
b0 .
b11 ,
b11 5
b11001111 A
b11000000 @
b1100 G
b100001011110010010000011000010101111000110110011001101111110001 B
b1000010111100100100000110000101 E
0J
03
04
1-
#290000
0-
#295000
01
14
1-
#300000
0-
#305000
18
1!
11
13
1-
#310000
0-
#315000
19
1"
1$
b1111 )
b1111 =
b11110001011111000110110110101001 +
b11110001011111000110110110101001 ?
b11111111 A
b11110000 @
b1111 G
b1111000110110011001101111110001 E
1J
b1 .
b111100011011001100110111111000101111100011011011010100111111000 B
b1111100011011011010100111111000 /
b1111100011011011010100111111000 6
1-
#320000
0-
#325000
09
0"
0$
b11111000010001001101111000110111 +
b11111000010001001101111000110111 ?
08
0!
b1000100110111100011011110001001 /
b1000100110111100011011110001001 6
b10 .
b111110001101101101010011111100001000100110111100011011110001001 B
b1111100011011011010100111111000 E
1J
03
1-
#330000
0-
#335000
0&
1$
08
0!
01
13
1-
#340000
0-
#345000
18
1!
1&
19
1"
11
1-
#350000
0-
#355000
b1100 )
b1100 =
0&
0$
09
0"
08
0!
0>
b11111000 A
b1000 *
b1000 <
0;
1'
b10001001101010001100011111111100 +
b10001001101010001100011111111100 ?
01
03
b1000100110111100011011110001001 E
1J
1(
b11 .
b100010011011110001101111000100110101000110001111111110001010001 B
b10101000110001111111110001010001 /
b10101000110001111111110001010001 6
1-
#360000
0-
#365000
1-
#370000
0-
#375000
1:
1#
1%
18
1!
19
1"
1&
1$
11
13
1-
#380000
0-
#385000
09
0"
0%
b100000 D
b1000 )
b1000 =
0$
b1111 *
b1111 <
0'
b100 C
b10101000110001111111110001010001 +
b10101000110001111111110001010001 ?
08
0!
0:
0#
b11100110110011110011100111001 /
b11100110110011110011100111001 6
b0 0
0(
b0 .
1>
b0 ,
b0 5
b10001111 A
b10000000 @
b1000 G
b1010100011000111111111000101000100011100110110011110011100111001 B
b10101000110001111111110001010001 E
0J
03
04
1-
#390000
0-
#395000
18
1!
13
14
1-
#400000
0-
#405000
b1111 )
b1111 =
b11100110110011110011100111001 +
b11100110110011110011100111001 ?
08
0!
b100100100010110100101101001001 /
b100100100010110100101101001001 6
b1 .
b11111111 A
b11110000 @
b1111 G
b1110011011001111001110011100100100100100010110100101101001001 B
b11100110110011110011100111001 E
1J
03
1-
#410000
0-
#415000
0&
1$
08
0!
01
13
1-
#420000
0-
#425000
1-
#430000
0-
#435000
1-
#440000
0-
#445000
1-
#450000
0-
#455000
1-
#460000
0-
#465000
1-
#470000
0-
#475000
1-
#480000
0-
#485000
18
1!
1&
19
1"
11
1-
#490000
0-
#495000
b100100100010110100101101001001 +
b100100100010110100101101001001 ?
b100100100010110100101101001001 E
1J
b10 .
b10010010001011010010110100100111010001100010111011010010100011 B
b11010001100010111011010010100011 /
b11010001100010111011010010100011 6
1-
#500000
0-
#505000
08
0!
1;
0'
b11010001100010111011010010100011 +
b11010001100010111011010010100011 ?
0&
09
0"
b1111011111110001111110111110111 /
b1111011111110001111110111110111 6
1(
b11 .
b1101000110001011101101001010001101111011111110001111110111110111 B
b11010001100010111011010010100011 E
1J
01
1-
#510000
0-
#515000
17
18
1!
1&
19
1"
11
1-
#520000
0-
#525000
07
0;
1'
b1111011111110001111110111110111 +
b1111011111110001111110111110111 ?
0&
09
0"
08
0!
b10100110011111100000100101001 /
b10100110011111100000100101001 6
0(
b0 .
1F
b111101111111000111111011111011100010100110011111100000100101001 B
b1111011111110001111110111110111 E
1J
01
03
1-
#530000
0-
#535000
13
1-
#540000
0-
#545000
1:
1#
18
1!
1%
1&
19
1"
11
1-
#550000
0-
#555000
08
0!
0:
0#
0&
0%
b11000 D
09
0"
b11001111110000010010100111011010 +
b11001111110000010010100111011010 ?
0'
b11 C
01
b10100110011111100000100101001 E
1J
0F
b1 ,
b1 5
b1 0
b1 .
b1010011001111110000010010100111011010100010101110001010110101 B
b11011010100010101110001010110101 /
b11011010100010101110001010110101 6
1-
#560000
0-
#565000
1-
#570000
0-
#575000
1-
#580000
0-
#585000
18
1!
1&
19
1"
11
1-
#590000
0-
#595000
0&
0$
09
0"
08
0!
b10001010111000101011010100000111 +
b10001010111000101011010100000111 ?
01
03
b11011010100010101110001010110101 E
1J
b10 .
b1101101010001010111000101011010100000111011011111100111100001110 B
b111011011111100111100001110 /
b111011011111100111100001110 6
1-
#600000
0-
#605000
18
1!
19
1"
1&
1$
11
13
1-
#610000
0-
#615000
09
0"
0:
0#
0$
0%
08
0!
b11111110 A
b1110 *
b1110 <
1;
0'
b1101111110011110000111000101011 +
b1101111110011110000111000101011 ?
03
b111011011111100111100001110 E
1J
1(
b11 .
b11101101111110011110000111000101011000011101110110101010110 B
b101011000011101110110101010110 /
b101011000011101110110101010110 6
1-
#620000
0-
#625000
0&
01
1-
#630000
0-
#635000
1&
11
1-
#640000
0-
#645000
0&
01
1-
#650000
0-
#655000
1$
13
1-
#660000
0-
#665000
17
18
1!
1&
19
1"
11
1-
#670000
0-
#675000
1:
1#
b1100 )
b1100 =
07
1%
b1111 *
b1111 <
0;
1'
b1110111011010101011001101101 +
b1110111011010101011001101101 ?
b11101111 A
b11100000 @
b1110 G
b101011000011101110110101010110 E
1J
1F
0(
b0 .
b10101100001110111011010101011001101101110010110110100111011011 B
b1101101110010110110100111011011 /
b1101101110010110110100111011011 6
1-
#680000
0-
#685000
0:
0#
b10000 D
b1111 )
b1111 =
0%
b10 C
0'
b1101001110110110101101100010111 +
b1101001110110110101101100010111 ?
0&
0$
09
0"
08
0!
b1011011000101110010110110110110 /
b1011011000101110010110110110110 6
b10 0
b1 .
b10 ,
b10 5
0F
b11111111 A
b11110000 @
b1111 G
b110110111001011011010011101101101011011000101110010110110110110 B
b1101101110010110110100111011011 E
1J
01
03
1-
#690000
0-
#695000
1$
13
1-
#700000
0-
#705000
1-
#710000
0-
#715000
18
1!
1&
19
1"
11
1-
#720000
0-
#725000
08
0!
b101101101101100100010000000001 +
b101101101101100100010000000001 ?
0&
09
0"
b1000100000000011000110110001000 /
b1000100000000011000110110001000 6
b10 .
b101101100010111001011011011011001000100000000011000110110001000 B
b1011011000101110010110110110110 E
1J
01
1-
#730000
0-
#735000
1-
#740000
0-
#745000
18
1!
1&
19
1"
11
1-
#750000
0-
#755000
0&
0$
09
0"
08
0!
0>
b11111100 A
b1100 *
b1100 <
0;
1'
b10001101100010001110001111000101 +
b10001101100010001110001111000101 ?
01
03
b1000100000000011000110110001000 E
1J
1(
b11 .
b100010000000001100011011000100011100011110001010011000011000111 B
b11100011110001010011000011000111 /
b11100011110001010011000011000111 6
1-
#760000
0-
#765000
1&
11
1-
#770000
0-
#775000
0&
1$
08
0!
01
13
1-
#780000
0-
#785000
1-
#790000
0-
#795000
1-
#800000
0-
#805000
1:
1#
18
1!
1%
1&
19
1"
11
1-
#810000
0-
#815000
0$
b111 )
b111 =
b1000 D
0%
09
0"
0:
0#
b1 C
1>
b1111 *
b1111 <
0'
b11000111001100110100111010100111 +
b11000111001100110100111010100111 ?
01
04
b11001111 A
b11000000 @
b1100 G
b11100011110001010011000011000111 E
0J
b11 ,
b11 5
b11 0
0(
b0 .
b1110001111000101001100001100011100110011010011101010011101100110 B
b110011010011101010011101100110 /
b110011010011101010011101100110 6
1-
#820000
0-
#825000
b1111 )
b1111 =
b1100110100011010010010011110110 +
b1100110100011010010010011110110 ?
0&
08
0!
b10001101001001001111011000011010 /
b10001101001001001111011000011010 6
b1 .
b11111111 A
b11110000 @
b1111 G
b11001101001110101001110110011010001101001001001111011000011010 B
b110011010011101010011101100110 E
1J
11
03
1-
#830000
0-
#835000
1$
01
13
14
1-
#840000
0-
#845000
1-
#850000
0-
#855000
1-
#860000
0-
#865000
1-
#870000
0-
#875000
18
1!
1&
19
1"
11
1-
#880000
0-
#885000
0$
b11010001111000000001111111111 +
b11010001111000000001111111111 ?
0&
09
0"
08
0!
b111100000000111111111101111000 /
b111100000000111111111101111000 6
b10 .
b1000110100100100111101100001101000111100000000111111111101111000 B
b10001101001001001111011000011010 E
1J
01
03
1-
#890000
0-
#895000
1&
11
1-
#900000
0-
#905000
19
1"
1$
18
1!
13
1-
#910000
0-
#915000
b1100 )
b1100 =
1:
1#
07
1%
0>
b11111000 A
b1000 *
b1000 <
0;
1'
b1111000111111010010100011100100 +
b1111000111111010010100011100100 ?
b111100000000111111111101111000 E
1J
1(
b11 .
b11110000000011111111110111100011111101001010001110010011111010 B
b11111101001010001110010011111010 /
b11111101001010001110010011111010 6
1-
#920000
0-
#925000
0:
0#
b100000 D
b1000 )
b1000 =
0%
0$
b1111 *
b1111 <
0'
b100 C
b11111101001010001110010011111010 +
b11111101001010001110010011111010 ?
09
0"
08
0!
b1111010100011000101100111110101 /
b1111010100011000101100111110101 6
b0 0
0(
b0 .
1>
b0 ,
b0 5
b10001111 A
b10000000 @
b1000 G
b1111110100101000111001001111101001111010100011000101100111110101 B
b11111101001010001110010011111010 E
0J
01
03
1-
#930000
0-
#935000
18
1!
11
13
1-
#940000
0-
#945000
19
1"
1$
b1111 )
b1111 =
b1111010100011000101100111110101 +
b1111010100011000101100111110101 ?
b11001100000000011011010010011000 /
b11001100000000011011010010011000 6
b1 .
b11111111 A
b11110000 @
b1111 G
b111101010001100010110011111010111001100000000011011010010011000 B
b1111010100011000101100111110101 E
1J
1-
#950000
0-
#955000
08
0!
0&
09
0"
b11001100000000011011010010011000 +
b11001100000000011011010010011000 ?
01
b11001100000000011011010010011000 E
1J
b10 .
b1100110000000001101101001001100000100101101100100111101101001011 B
b100101101100100111101101001011 /
b100101101100100111101101001011 6
1-
#960000
0-
#965000
1-
#970000
0-
#975000
1-
#980000
0-
#985000
1-
#990000
0-
#995000
18
1!
1&
19
1"
11
1-
#1000000
0-
#1005000
08
0!
1;
0'
b100101101100100111101101001011 +
b100101101100100111101101001011 ?
0&
09
0"
b11110011001101000110011011100110 /
b11110011001101000110011011100110 6
1(
b11 .
b10010110110010011110110100101111110011001101000110011011100110 B
b100101101100100111101101001011 E
1J
01
1-
#1010000
0-
#1015000
17
18
1!
1&
19
1"
11
1-
#1020000
0-
#1025000
07
0;
1'
b11110011001101000110011011100110 +
b11110011001101000110011011100110 ?
0&
09
0"
08
0!
b11000110101101011111010010001101 /
b11000110101101011111010010001101 6
0(
b0 .
1F
b1111001100110100011001101110011011000110101101011111010010001101 B
b11110011001101000110011011100110 E
1J
01
03
1-
#1030000
0-
#1035000
1-
#1040000
0-
#1045000
13
1-
#1050000
0-
#1055000
1-
#1060000
0-
#1065000
1:
1#
18
1!
1%
1&
19
1"
11
1-
#1070000
0-
#1075000
0:
0#
0&
0$
0%
b11000 D
09
0"
08
0!
b10110101111101001000110100110101 +
b10110101111101001000110100110101 ?
0'
b11 C
01
03
b11000110101101011111010010001101 E
1J
0F
b1 ,
b1 5
b1 0
b1 .
b1100011010110101111101001000110100110101101000001100100101101011 B
b110101101000001100100101101011 /
b110101101000001100100101101011 6
1-
#1080000
0-
#1085000
1&
11
1-
#1090000
0-
#1095000
0&
01
1-
#1100000
0-
#1105000
1$
13
1-
#1110000
0-
#1115000
1-
#1120000
0-
#1125000
1-
#1130000
0-
#1135000
1-
#1140000
0-
#1145000
18
1!
1&
19
1"
11
1-
#1150000
0-
#1155000
0&
0$
09
0"
08
0!
b10100000110010010110101101000010 +
b10100000110010010110101101000010 ?
01
03
b110101101000001100100101101011 E
1J
b10 .
b11010110100000110010010110101101000010010011111100110110000100 B
b1000010010011111100110110000100 /
b1000010010011111100110110000100 6
1-
#1160000
0-
#1165000
18
1!
19
1"
1&
1$
11
13
1-
#1170000
0-
#1175000
0:
0#
17
0%
b11111110 A
b1110 *
b1110 <
1;
0'
b1001111110011011000010001000111 +
b1001111110011011000010001000111 ?
b1000010010011111100110110000100 E
1J
1(
b11 .
b100001001001111110011011000010001000111011001011010100110001110 B
b1000111011001011010100110001110 /
b1000111011001011010100110001110 6
1-
#1180000
0-
#1185000
1:
1#
07
1%
b1100 )
b1100 =
b1111 *
b1111 <
0;
1'
b1100101101010011000111000011011 +
b1100101101010011000111000011011 ?
b11011011000001110010100110110 /
b11011011000001110010100110110 6
0(
b0 .
1F
b11101111 A
b11100000 @
b1110 G
b100011101100101101010011000111000011011011000001110010100110110 B
b1000111011001011010100110001110 E
1J
1-
#1190000
0-
#1195000
08
0!
0:
0#
0&
b1111 )
b1111 =
0%
b10000 D
09
0"
0'
b10 C
b11100101001101101011101010110001 +
b11100101001101101011101010110001 ?
01
b11111111 A
b11110000 @
b1111 G
b11011011000001110010100110110 E
1J
0F
b10 ,
b10 5
b10 0
b1 .
b1101101100000111001010011011010111010101100010100100001110101 B
b10111010101100010100100001110101 /
b10111010101100010100100001110101 6
1-
#1200000
0-
#1205000
1-
#1210000
0-
#1215000
18
1!
1&
19
1"
11
1-
#1220000
0-
#1225000
0$
b1001000011101011001011010000100 +
b1001000011101011001011010000100 ?
0&
09
0"
08
0!
b10010110100001001110000000101101 /
b10010110100001001110000000101101 6
b10 .
b1011101010110001010010000111010110010110100001001110000000101101 B
b10111010101100010100100001110101 E
1J
01
03
1-
#1230000
0-
#1235000
1$
13
1-
#1240000
0-
#1245000
1-
#1250000
0-
#1255000
18
1!
1&
19
1"
11
1-
#1260000
0-
#1265000
0$
0>
b11111100 A
b1100 *
b1100 <
0;
1'
b11100000001011010110100010101110 +
b11100000001011010110100010101110 ?
0&
09
0"
08
0!
b1101000101011100001101111010001 /
b1101000101011100001101111010001 6
1(
b11 .
b1001011010000100111000000010110101101000101011100001101111010001 B
b10010110100001001110000000101101 E
1J
01
03
1-
#1270000
0-
#1275000
1&
11
1-
#1280000
0-
#1285000
0&
1$
08
0!
01
13
1-
#1290000
0-
#1295000
1:
1#
18
1!
1%
1&
19
1"
11
1-
#1300000
0-
#1305000
0$
b1000 D
b111 )
b111 =
0%
1>
b1111 *
b1111 <
0'
b1 C
b11010001100000100111001111100010 +
b11010001100000100111001111100010 ?
09
0"
0:
0#
b10000010011100111110001000000100 /
b10000010011100111110001000000100 6
b11 0
0(
b0 .
b11 ,
b11 5
b11001111 A
b11000000 @
b1100 G
b110100010101110000110111101000110000010011100111110001000000100 B
b1101000101011100001101111010001 E
0J
01
04
1-
#1310000
0-
#1315000
b1111 )
b1111 =
08
0!
0&
b100001110011010110000000011 +
b100001110011010110000000011 ?
03
b11111111 A
b11110000 @
b1111 G
b10000010011100111110001000000100 E
1J
b1 .
b1000001001110011111000100000010000111001101011000000001101110011 B
b111001101011000000001101110011 /
b111001101011000000001101110011 6
1-
#1320000
0-
#1325000
19
1"
18
1!
1$
1&
11
13
14
1-
#1330000
0-
