FIFO/async_fifo/code/dpram.v
module dpram #(
    parameter DATESIZE = 8,
    parameter ADDRSIZE = 4
)(
    input clka,
    input ena,
    input wea,
    input [DATESIZE-1:0] dina,
    input [ADDRSIZE-1:0] addra,

    input clkb,
    input enb,
    input [ADDRSIZE-1:0] addrb,
    output  reg [DATESIZE-1:0]doutb
);
    parameter DEPTH = 1<<ADDRSIZE;
    reg [DATESIZE-1:0] mem [DEPTH-1:0];

    always @(posedge clkb) begin  //read
        if(enb) 
            doutb <= mem[addrb];
    end

    always @(posedge clka) begin //write
        if (ena) begin
            if(wea) 
                mem[addra] <= dina;
        end
    end






endmodule //dpram

FIFO/async_fifo/code/async_fifo.v
module async_fifo #(
    parameter DATESIZE  = 8,
    parameter ADDRSIZE  = 4,
    parameter ALMOST    = 3
) 
(
    input [DATESIZE-1:0] wdata,
    input winc, wclk, w_rstn,
    input rinc, rclk, r_rstn,
    output wire [DATESIZE-1:0] rdata,
    output reg wfull,
    output reg rempty,
    output reg almost_full,
    output reg almost_empty
);
    parameter DEPTH = 1<<ADDRSIZE;
    wire [ADDRSIZE-1 : 0] waddr,raddr;  
    reg  [ADDRSIZE : 0] wptr,rptr;
    
    //read pointer to write clk sync
    reg [ADDRSIZE:0] wq1_rptr,wq2_rptr;
    always @(posedge wclk or negedge w_rstn) begin
        if (!w_rstn) begin
            {wq2_rptr,wq1_rptr} <= 0 ;
        end else begin
            {wq2_rptr,wq1_rptr} <= {wq1_rptr,rptr};
        end
    end

    // write pointer to read clk domain

    reg [ADDRSIZE:0] wq1_wptr,wq2_wptr;
    always @(posedge rclk or negedge r_rstn) begin
        if (!r_rstn) begin
            {wq2_wptr,wq1_wptr} <= 0 ;
        end else begin
            {wq2_wptr,wq1_wptr} <= {wq1_wptr,wptr};
        end
    end


    // full and empty logic
    reg [ADDRSIZE:0] wbin;
    wire [ADDRSIZE:0] wbin_next,wptr_next;
    wire mem_wr;
    assign mem_wr = winc & (!wfull);
    assign waddr = wbin[ADDRSIZE-1:0];
    assign wbin_next = wbin+mem_wr;
    //bin to gray code
    assign wptr_next = (wbin_next>>1) ^ wbin_next;
    //寄存器输出
    always @(posedge wclk or negedge w_rstn ) begin
        if (!w_rstn) begin
            {wptr,wbin} <= 0;
        end else begin
            {wptr,wbin} <= {wptr_next,wbin_next};
        end       
    end

    // full logic  MSB 不同 LSB相同
    //同步过来的读信号为wq2_rptr(gray code),wq2_rptr与下一个wptr的值进行比较
    //因为wq2_rptr是即将要读的，所以是比较下一个wptr，因为这拍完成之后，才符合full
    //例如wq2_rptr=0 此时wptr=7，
    //那么此时如果写数据有效(winc有效)的话，此时7这拍肯定写了，下一拍wptr就是8也就是满，
    //那么此时如果写数据无效(！winc有效)的话，此时7这拍肯定没写（将写），下一拍wptr还是7，也不会满
    //所以提前一拍判断是不是写满
    wire wfull_val;
    assign wfull_val = (wptr_next == {~wq2_rptr[ADDRSIZE:ADDRSIZE-1],wq2_rptr[ADDRSIZE-2:0]} );
    always @(posedge wclk or negedge w_rstn ) begin
        if (!w_rstn) begin
            wfull <= 0;
        end else begin
            wfull  <= wfull_val;
        end
    end

//empty 同理
    reg [ADDRSIZE:0] rbin;
    wire [ADDRSIZE:0] rptr_next, rbin_next;
    always @(posedge rclk or negedge r_rstn)
        if (!r_rstn) begin
            {rbin, rptr} <= 0;
        end
        else {rbin, rptr} <= {rbin_next, rptr_next};
    wire mem_rd;
    assign mem_rd = rinc & (~rempty);
    assign raddr = rbin[ADDRSIZE-1:0];
    assign rbin_next = rbin + mem_rd;
    assign rptr_next = (rbin_next>>1) ^ rbin_next;
    //empty logic
    assign rempty_val = (rptr_next == wq2_wptr);

    always @(posedge rclk or negedge r_rstn) begin
        if (!r_rstn) rempty <= 1'b1;
        else rempty <= rempty_val ;
    end

    //almost full and empty logic
    //需要将同步过来的格雷码转换成二进制去判断将空将满
    //gray to bin
    wire [ADDRSIZE:0] wq2_rptr_bin,wq2_wptr_bin;
    assign wq2_rptr_bin[ADDRSIZE] = wq2_rptr[ADDRSIZE];
    assign wq2_wptr_bin [ADDRSIZE] = wq2_wptr[ADDRSIZE];
    genvar i;
    generate
        for ( i=ADDRSIZE-1 ; i>= 0 ; i=i-1 ) begin
            assign wq2_rptr_bin[i] = wq2_rptr[i] ^ wq2_rptr_bin[i+1];
            assign wq2_wptr_bin[i] = wq2_wptr[i] ^ wq2_wptr_bin[i+1];
        end
    endgenerate

    //almost empty and full
    wire almost_empty_val,almost_full_val;
    //empty
    wire [ADDRSIZE:0] wgap;
    assign wgap = wq2_wptr_bin-rbin;
    assign almost_empty_val = (wgap <= ALMOST);
    always @(posedge rclk or negedge r_rstn) begin
        if (!r_rstn) begin
            almost_empty <= 1'b1;
        end else begin
            almost_empty <= almost_empty_val;
        end
    end


    //full
    wire [ADDRSIZE:0] rcap;
    assign rcap = (wq2_rptr_bin[ADDRSIZE] != wbin[ADDRSIZE]) ? 
                 (wq2_rptr_bin[ADDRSIZE-1:0] - wbin[ADDRSIZE-1:0]) : (DEPTH-(wbin - wq2_rptr_bin)) ;
    assign almost_full_val = (rcap <= ALMOST);
    always @(posedge wclk or negedge w_rstn) begin
        if (!w_rstn) 
            almost_full <= 1'b0;
        else 
            almost_full <= almost_full_val;       
    end     
    dpram #(.ADDRSIZE(ADDRSIZE),.DATESIZE(DATESIZE)) u_dpram(
        .clkb(rclk),
        .enb(mem_rd),
        .addrb(raddr),
        .doutb(rdata),

        .clka(wclk),
        .ena(mem_wr),
        .wea(mem_wr),
        .dina(wdata),
        .addra(waddr)

    );
    
endmodule //async_fifo

FIFO/async_fifo/code/async_fifo_tb.v
`timescale 1ns/1ps
module async_fifo_tb();

    parameter DATESIZE = 8;
    parameter ADDRSIZE = 3;
    parameter ALMOST = 2; 
    reg [DATESIZE-1:0]wdata;
    reg w_rstn;
    reg winc;
    reg rinc;
    reg wclk;
    reg rclk;
    reg r_rstn;
    wire [DATESIZE-1:0]rdata;
    wire wfull;
    wire rempty;
    wire almost_empty;
    wire almost_full;

    reg [3:0]a;
    reg [3:0]b;
    reg [4:0]c;
    reg x;
    initial begin
        $dumpfile("test.vcd");
        $dumpvars;
        for (i=0; i < 8; i = i + 1) begin
        $dumpvars(0, u_async_fifo.u_dpram.mem[i]);
    end
        wdata = 0;
        w_rstn = 0;
        rinc = 0;
        rclk = 0;
        r_rstn = 0;
        wclk = 0;
        winc = 0;
    

        #2;w_rstn = 0; r_rstn = 0;
        #4;w_rstn = 1; r_rstn = 1;

        #6;  winc = 1;
        #35; rinc = 1;
        #10; winc = 0;
        #60; rinc = 0;
        #5;  rinc = 1; winc = 1;
      
        #100;
        $finish();

    end
integer i;
    initial begin
        wait(winc==1);
        //#11;       
        for(i=0;i<=100;i=i+1) begin
            wdata = i;
            @(negedge wclk);
        end 
    end
 
    always #1   wclk = ~wclk;
    always #4   rclk = ~rclk;


    async_fifo #(
    .DATESIZE                       ( DATESIZE     ),
    .ADDRSIZE                       ( ADDRSIZE     ) )
 u_async_fifo(
    .wdata                          ( wdata ),
    .winc                           ( winc  ),
    .wclk                           ( wclk  ),
    .w_rstn                         ( w_rstn),
    .rinc                           ( rinc  ),
    .rclk                           ( rclk  ),
    .r_rstn                         ( r_rstn),
    .rdata                          ( rdata ),
    .rempty                         (rempty),
    .wfull                           (wfull),

    .almost_empty                   (almost_empty),
    .almost_full                     (almost_full)
    
);


endmodule

FIFO/async_fifo/sim/test.vcd
$date
	Fri Aug 18 21:59:04 2023
$end
$version
	Icarus Verilog
$end
$timescale
	1ps
$end
$scope module async_fifo_tb $end
$var wire 1 ! wfull $end
$var wire 1 " rempty $end
$var wire 8 # rdata [7:0] $end
$var wire 1 $ almost_full $end
$var wire 1 % almost_empty $end
$var reg 1 & r_rstn $end
$var reg 1 ' rclk $end
$var reg 1 ( rinc $end
$var reg 1 ) w_rstn $end
$var reg 1 * wclk $end
$var reg 8 + wdata [7:0] $end
$var reg 1 , winc $end
$var integer 32 - i [31:0] $end
$scope module u_async_fifo $end
$var wire 1 . mem_rd $end
$var wire 1 / mem_wr $end
$var wire 1 & r_rstn $end
$var wire 1 ' rclk $end
$var wire 1 ( rinc $end
$var wire 4 0 rptr_next [3:0] $end
$var wire 1 ) w_rstn $end
$var wire 1 * wclk $end
$var wire 8 1 wdata [7:0] $end
$var wire 1 , winc $end
$var wire 4 2 wptr_next [3:0] $end
$var wire 4 3 wq2_wptr_bin [3:0] $end
$var wire 4 4 wq2_rptr_bin [3:0] $end
$var wire 4 5 wgap [3:0] $end
$var wire 1 6 wfull_val $end
$var wire 4 7 wbin_next [3:0] $end
$var wire 3 8 waddr [2:0] $end
$var wire 1 9 rempty_val $end
$var wire 8 : rdata [7:0] $end
$var wire 4 ; rcap [3:0] $end
$var wire 4 < rbin_next [3:0] $end
$var wire 3 = raddr [2:0] $end
$var wire 1 > almost_full_val $end
$var wire 1 ? almost_empty_val $end
$var reg 1 % almost_empty $end
$var reg 1 $ almost_full $end
$var reg 4 @ rbin [3:0] $end
$var reg 1 " rempty $end
$var reg 4 A rptr [3:0] $end
$var reg 4 B wbin [3:0] $end
$var reg 1 ! wfull $end
$var reg 4 C wptr [3:0] $end
$var reg 4 D wq1_rptr [3:0] $end
$var reg 4 E wq1_wptr [3:0] $end
$var reg 4 F wq2_rptr [3:0] $end
$var reg 4 G wq2_wptr [3:0] $end
$scope begin genblk1[0] $end
$upscope $end
$scope begin genblk1[1] $end
$upscope $end
$scope begin genblk1[2] $end
$upscope $end
$scope module u_dpram $end
$var wire 3 H addra [2:0] $end
$var wire 3 I addrb [2:0] $end
$var wire 1 * clka $end
$var wire 1 ' clkb $end
$var wire 8 J dina [7:0] $end
$var wire 1 / ena $end
$var wire 1 . enb $end
$var wire 1 / wea $end
$var reg 8 K doutb [7:0] $end
$upscope $end
$upscope $end
$upscope $end
$scope module async_fifo_tb $end
$scope module u_async_fifo $end
$scope module u_dpram $end
$var reg 8 L \mem[0] [7:0] $end
$upscope $end
$upscope $end
$upscope $end
$scope module async_fifo_tb $end
$scope module u_async_fifo $end
$scope module u_dpram $end
$var reg 8 M \mem[1] [7:0] $end
$upscope $end
$upscope $end
$upscope $end
$scope module async_fifo_tb $end
$scope module u_async_fifo $end
$scope module u_dpram $end
$var reg 8 N \mem[2] [7:0] $end
$upscope $end
$upscope $end
$upscope $end
$scope module async_fifo_tb $end
$scope module u_async_fifo $end
$scope module u_dpram $end
$var reg 8 O \mem[3] [7:0] $end
$upscope $end
$upscope $end
$upscope $end
$scope module async_fifo_tb $end
$scope module u_async_fifo $end
$scope module u_dpram $end
$var reg 8 P \mem[4] [7:0] $end
$upscope $end
$upscope $end
$upscope $end
$scope module async_fifo_tb $end
$scope module u_async_fifo $end
$scope module u_dpram $end
$var reg 8 Q \mem[5] [7:0] $end
$upscope $end
$upscope $end
$upscope $end
$scope module async_fifo_tb $end
$scope module u_async_fifo $end
$scope module u_dpram $end
$var reg 8 R \mem[6] [7:0] $end
$upscope $end
$upscope $end
$upscope $end
$scope module async_fifo_tb $end
$scope module u_async_fifo $end
$scope module u_dpram $end
$var reg 8 S \mem[7] [7:0] $end
$upscope $end
$upscope $end
$upscope $end
$enddefinitions $end
#0
$dumpvars
bx S
bx R
bx Q
bx P
bx O
bx N
bx M
bx L
bx K
b0 J
b0 I
b0 H
b0 G
b0 F
b0 E
b0 D
b0 C
b0 B
b0 A
b0 @
1?
0>
b0 =
b0 <
b1000 ;
bx :
19
b0 8
b0 7
06
b0 5
b0 4
b0 3
b0 2
b0 1
b0 0
0/
0.
b1000 -
0,
b0 +
0*
0)
0(
0'
0&
1%
0$
bx #
1"
0!
$end
#1000
1*
#2000
0*
#3000
1*
#4000
0*
1'
#5000
1*
#6000
0*
1&
1)
#7000
1*
#8000
0*
0'
#9000
1*
#10000
0*
#11000
1*
#12000
b1 2
b1 7
1/
b0 -
0*
1'
1,
#13000
b111 ;
b1 8
b1 H
b11 2
b0 L
b1 C
b10 7
b1 B
1*
#14000
b1 +
b1 1
b1 J
b1 -
0*
#15000
b110 ;
b10 8
b10 H
b10 2
b1 M
b11 C
b11 7
b10 B
1*
#16000
b10 +
b10 1
b10 J
b10 -
0*
0'
#17000
b101 ;
b11 8
b11 H
b110 2
b10 N
b10 C
b100 7
b11 B
1*
#18000
b11 +
b11 1
b11 J
b11 -
0*
#19000
b100 ;
b100 8
b100 H
b111 2
b11 O
b110 C
b101 7
b100 B
1*
#20000
b110 E
b100 +
b100 1
b100 J
b100 -
0*
1'
#21000
1>
b11 ;
b101 8
b101 H
b101 2
b100 P
b111 C
b110 7
b101 B
1*
#22000
b101 +
b101 1
b101 J
b101 -
0*
#23000
b10 ;
b110 8
b110 H
b100 2
b101 Q
b101 C
b111 7
b110 B
1$
1*
#24000
b110 +
b110 1
b110 J
b110 -
0*
0'
#25000
16
b1 ;
b111 8
b111 H
b1100 2
b110 R
b100 C
b1000 7
b111 B
1*
#26000
b111 +
b111 1
b111 J
b111 -
0*
#27000
b0 ;
b0 8
b0 H
0/
b111 S
b1100 C
b1000 7
b1000 B
1!
1*
#28000
0?
b100 5
b100 3
09
b110 G
b1100 E
b1000 +
b1000 1
b1000 J
b1000 -
0*
1'
#29000
1*
#30000
b1001 +
b1001 1
b1001 J
b1001 -
0*
#31000
1*
#32000
b1010 +
b1010 1
b1010 J
b1010 -
0*
0'
#33000
1*
#34000
b1011 +
b1011 1
b1011 J
b1011 -
0*
#35000
1*
#36000
b1000 5
b1000 3
0%
0"
b1100 G
b1100 +
b1100 1
b1100 J
b1100 -
0*
1'
#37000
1*
#38000
b1101 +
b1101 1
b1101 J
b1101 -
0*
#39000
1*
#40000
b1110 +
b1110 1
b1110 J
b1110 -
0*
0'
#41000
1*
#42000
b1111 +
b1111 1
b1111 J
b1111 -
0*
#43000
1*
#44000
b10000 +
b10000 1
b10000 J
b10000 -
0*
1'
#45000
1*
#46000
b10001 +
b10001 1
b10001 J
b10001 -
0*
#47000
b1 0
b1 <
1.
1*
1(
#48000
b10010 +
b10010 1
b10010 J
b10010 -
0*
0'
#49000
1*
#50000
b10011 +
b10011 1
b10011 J
b10011 -
0*
#51000
1*
#52000
b1 =
b1 I
b11 0
b0 #
b0 :
b0 K
b10 <
b111 5
b1 @
b1 A
b10100 +
b10100 1
b10100 J
b10100 -
0*
1'
#53000
b1 D
1*
#54000
b10101 +
b10101 1
b10101 J
b10101 -
0*
#55000
b1 ;
b1 4
06
b1 F
1*
#56000
b10110 +
b10110 1
b10110 J
b10110 -
0*
0'
#57000
0!
1*
0,
#58000
b10111 +
b10111 1
b10111 J
b10111 -
0*
#59000
1*
#60000
b10 =
b10 I
b10 0
b1 #
b1 :
b1 K
b11 <
b110 5
b10 @
b11 A
b11000 +
b11000 1
b11000 J
b11000 -
0*
1'
#61000
b11 D
1*
#62000
b11001 +
b11001 1
b11001 J
b11001 -
0*
#63000
b10 ;
b10 4
b11 F
1*
#64000
b11010 +
b11010 1
b11010 J
b11010 -
0*
0'
#65000
1*
#66000
b11011 +
b11011 1
b11011 J
b11011 -
0*
#67000
1*
#68000
b11 =
b11 I
b110 0
b10 #
b10 :
b10 K
b100 <
b101 5
b11 @
b10 A
b11100 +
b11100 1
b11100 J
b11100 -
0*
1'
#69000
b10 D
1*
#70000
b11101 +
b11101 1
b11101 J
b11101 -
0*
#71000
b11 ;
b11 4
b10 F
1*
#72000
b11110 +
b11110 1
b11110 J
b11110 -
0*
0'
#73000
1*
#74000
b11111 +
b11111 1
b11111 J
b11111 -
0*
#75000
1*
#76000
b100 =
b100 I
b111 0
b11 #
b11 :
b11 K
b101 <
b100 5
b100 @
b110 A
b100000 +
b100000 1
b100000 J
b100000 -
0*
1'
#77000
b110 D
1*
#78000
b100001 +
b100001 1
b100001 J
b100001 -
0*
#79000
0>
b100 ;
b100 4
b110 F
1*
#80000
b100010 +
b100010 1
b100010 J
b100010 -
0*
0'
#81000
0$
1*
#82000
b100011 +
b100011 1
b100011 J
b100011 -
0*
#83000
1*
#84000
b101 =
b101 I
b101 0
b100 #
b100 :
b100 K
b110 <
1?
b11 5
b101 @
b111 A
b100100 +
b100100 1
b100100 J
b100100 -
0*
1'
#85000
b111 D
1*
#86000
b100101 +
b100101 1
b100101 J
b100101 -
0*
#87000
b101 ;
b101 4
b111 F
1*
#88000
b100110 +
b100110 1
b100110 J
b100110 -
0*
0'
#89000
1*
#90000
b100111 +
b100111 1
b100111 J
b100111 -
0*
#91000
1*
#92000
b110 =
b110 I
b100 0
b101 #
b101 :
b101 K
b111 <
b10 5
b110 @
b101 A
1%
b101000 +
b101000 1
b101000 J
b101000 -
0*
1'
#93000
b101 D
1*
#94000
b101001 +
b101001 1
b101001 J
b101001 -
0*
#95000
b110 ;
b110 4
b101 F
1*
#96000
b101010 +
b101010 1
b101010 J
b101010 -
0*
0'
#97000
1*
#98000
b101011 +
b101011 1
b101011 J
b101011 -
0*
#99000
1*
#100000
19
b111 =
b111 I
b1100 0
b110 #
b110 :
b110 K
b1000 <
b1 5
b111 @
b100 A
b101100 +
b101100 1
b101100 J
b101100 -
0*
1'
#101000
b100 D
1*
#102000
b101101 +
b101101 1
b101101 J
b101101 -
0*
#103000
b111 ;
b111 4
b100 F
1*
#104000
b101110 +
b101110 1
b101110 J
b101110 -
0*
0'
#105000
1*
#106000
b101111 +
b101111 1
b101111 J
b101111 -
0*
#107000
1*
#108000
0.
b0 =
b0 I
19
b1100 0
b111 #
b111 :
b111 K
b1000 <
b0 5
b1000 @
b1100 A
1"
b110000 +
b110000 1
b110000 J
b110000 -
0*
1'
#109000
b1100 D
1*
#110000
b110001 +
b110001 1
b110001 J
b110001 -
0*
#111000
b1000 ;
b1000 4
b1100 F
1*
#112000
b110010 +
b110010 1
b110010 J
b110010 -
0*
0'
#113000
1*
#114000
b110011 +
b110011 1
b110011 J
b110011 -
0*
#115000
1*
#116000
b110100 +
b110100 1
b110100 J
b110100 -
0*
1'
#117000
1*
0(
#118000
b110101 +
b110101 1
b110101 J
b110101 -
0*
#119000
1*
#120000
b110110 +
b110110 1
b110110 J
b110110 -
0*
0'
#121000
1*
#122000
b1101 2
b110111 +
b110111 1
b110111 J
b110111 -
b1001 7
1/
0*
1,
1(
#123000
b111 ;
b1 8
b1 H
b1111 2
b110111 L
b1101 C
b1010 7
b1001 B
1*
#124000
b1101 E
b111000 +
b111000 1
b111000 J
b111000 -
0*
1'
#125000
b110 ;
b10 8
b10 H
b1110 2
b111000 M
b1111 C
b1011 7
b1010 B
1*
#126000
b111001 +
b111001 1
b111001 J
b111001 -
0*
#127000
b101 ;
b11 8
b11 H
b1010 2
b111001 N
b1110 C
b1100 7
b1011 B
1*
#128000
b111010 +
b111010 1
b111010 J
b111010 -
0*
0'
#129000
b100 ;
b100 8
b100 H
b1011 2
b111010 O
b1010 C
b1101 7
b1100 B
1*
#130000
b111011 +
b111011 1
b111011 J
b111011 -
0*
#131000
1>
b11 ;
b101 8
b101 H
b1001 2
b111011 P
b1011 C
b1110 7
b1101 B
1*
#132000
b1 5
b1001 3
09
b1101 G
b1011 E
b111100 +
b111100 1
b111100 J
b111100 -
0*
1'
#133000
b10 ;
b110 8
b110 H
b1000 2
b111100 Q
1$
b1001 C
b1111 7
b1110 B
1*
#134000
b111101 +
b111101 1
b111101 J
b111101 -
0*
#135000
16
b1 ;
b111 8
b111 H
b0 2
b111101 R
b1000 C
b0 7
b1111 B
1*
#136000
b111110 +
b111110 1
b111110 J
b111110 -
0*
0'
#137000
b0 ;
0/
b0 8
b0 H
16
b0 2
b111110 S
1!
b0 C
b0 7
b0 B
1*
#138000
b111111 +
b111111 1
b111111 J
b111111 -
0*
#139000
1*
#140000
b1101 0
0?
b101 5
b1101 3
b1001 <
1.
b1011 G
b0 E
0"
b1000000 +
b1000000 1
b1000000 J
b1000000 -
0*
1'
#141000
1*
#142000
b1000001 +
b1000001 1
b1000001 J
b1000001 -
0*
#143000
1*
#144000
b1000010 +
b1000010 1
b1000010 J
b1000010 -
0*
0'
#145000
1*
#146000
b1000011 +
b1000011 1
b1000011 J
b1000011 -
0*
#147000
1*
#148000
b1 =
b1 I
b1111 0
b0 3
b110111 #
b110111 :
b110111 K
0%
b1010 <
b111 5
b1001 @
b1101 A
b0 G
b1000100 +
b1000100 1
b1000100 J
b1000100 -
0*
1'
#149000
b1101 D
1*
#150000
b1000101 +
b1000101 1
b1000101 J
b1000101 -
0*
#151000
b1 ;
b1001 4
06
b1101 F
1*
#152000
b1000110 +
b1000110 1
b1000110 J
b1000110 -
0*
0'
#153000
16
b1 2
b1 7
1/
0!
1*
#154000
b1000111 +
b1000111 1
b1000111 J
b1000111 -
0*
#155000
b0 ;
b1 8
b1 H
0/
b1000111 L
b1 C
b1 7
b1 B
1!
1*
#156000
b10 =
b10 I
b1110 0
b111000 #
b111000 :
b111000 K
b1 E
b1011 <
b110 5
b1010 @
b1111 A
b1001000 +
b1001000 1
b1001000 J
b1001000 -
0*
1'
#157000
b1111 D
1*
#158000
b1001001 +
b1001001 1
b1001001 J
b1001001 -
0*
#159000
b1 ;
b1010 4
06
b1111 F
1*
#160000
b1001010 +
b1001010 1
b1001010 J
b1001010 -
0*
0'
#161000
16
b11 2
b10 7
1/
0!
1*
#162000
b1001011 +
b1001011 1
b1001011 J
b1001011 -
0*
#163000
b0 ;
b10 8
b10 H
0/
b1001011 M
b11 C
b10 7
b10 B
1!
1*
#164000
b1 3
b11 =
b11 I
b1010 0
b111001 #
b111001 :
b111001 K
b1100 <
b110 5
b1011 @
b1110 A
b1 G
b11 E
b1001100 +
b1001100 1
b1001100 J
b1001100 -
0*
1'
#165000
b1110 D
1*
#166000
b1001101 +
b1001101 1
b1001101 J
b1001101 -
0*
#167000
b1 ;
b1011 4
06
b1110 F
1*
#168000
b1001110 +
b1001110 1
b1001110 J
b1001110 -
0*
0'
#169000
16
b10 2
b11 7
1/
0!
1*
#170000
b1001111 +
b1001111 1
b1001111 J
b1001111 -
0*
#171000
b0 ;
b11 8
b11 H
0/
b1001111 N
b10 C
b11 7
b11 B
1!
1*
#172000
b10 3
b100 =
b100 I
b1011 0
b111010 #
b111010 :
b111010 K
b11 G
b10 E
b1101 <
b110 5
b1100 @
b1010 A
b1010000 +
b1010000 1
b1010000 J
b1010000 -
0*
1'
#173000
b1010 D
1*
#174000
b1010001 +
b1010001 1
b1010001 J
b1010001 -
0*
#175000
1>
b1 ;
b1100 4
06
b1010 F
1*
#176000
b1010010 +
b1010010 1
b1010010 J
b1010010 -
0*
0'
#177000
16
b110 2
b100 7
1/
0!
1*
#178000
b1010011 +
b1010011 1
b1010011 J
b1010011 -
0*
#179000
b0 ;
b100 8
b100 H
0/
b1010011 O
b110 C
b100 7
b100 B
1!
1*
#180000
b11 3
b101 =
b101 I
b1001 0
b111011 #
b111011 :
b111011 K
b1110 <
b110 5
b1101 @
b1011 A
b10 G
b110 E
b1010100 +
b1010100 1
b1010100 J
b1010100 -
0*
1'
#181000
b1011 D
1*
#182000
b1010101 +
b1010101 1
b1010101 J
b1010101 -
0*
#183000
b1 ;
b1101 4
06
b1011 F
1*
#184000
b1010110 +
b1010110 1
b1010110 J
b1010110 -
0*
0'
#185000
16
b111 2
b101 7
1/
0!
1*
#186000
b1010111 +
b1010111 1
b1010111 J
b1010111 -
0*
#187000
b0 ;
b101 8
b101 H
0/
b1010111 P
b111 C
b101 7
b101 B
1!
1*
#188000
b100 3
b110 =
b110 I
b1000 0
b111100 #
b111100 :
b111100 K
b110 G
b111 E
b1111 <
b110 5
b1110 @
b1001 A
b1011000 +
b1011000 1
b1011000 J
b1011000 -
0*
1'
#189000
b1001 D
1*
#190000
b1011001 +
b1011001 1
b1011001 J
b1011001 -
0*
#191000
b1 ;
b1110 4
06
b1001 F
1*
#192000
b1011010 +
b1011010 1
b1011010 J
b1011010 -
0*
0'
#193000
16
b101 2
b110 7
1/
0!
1*
#194000
b1011011 +
b1011011 1
b1011011 J
b1011011 -
0*
#195000
b0 ;
b110 8
b110 H
0/
b1011011 Q
b101 C
b110 7
b110 B
1!
1*
#196000
b101 3
b111 =
b111 I
09
b0 0
b111101 #
b111101 :
b111101 K
b0 <
b110 5
b1111 @
b1000 A
b111 G
b101 E
b1011100 +
b1011100 1
b1011100 J
b1011100 -
0*
1'
#197000
b1000 D
1*
#198000
b1011101 +
b1011101 1
b1011101 J
b1011101 -
0*
#199000
b1 ;
b1111 4
06
b1000 F
1*
#200000
b1011110 +
b1011110 1
b1011110 J
b1011110 -
0*
0'
#201000
16
b100 2
b111 7
1/
0!
1*
#202000
b1011111 +
b1011111 1
b1011111 J
b1011111 -
0*
#203000
b0 ;
b111 8
b111 H
0/
b1011111 R
b100 C
b111 7
b111 B
1!
1*
#204000
b110 3
b0 =
b0 I
b1 0
b111110 #
b111110 :
b111110 K
b101 G
b100 E
b1 <
b110 5
b0 @
b0 A
b1100000 +
b1100000 1
b1100000 J
b1100000 -
0*
1'
#205000
b0 D
1*
#206000
b1100001 +
b1100001 1
b1100001 J
b1100001 -
0*
#207000
1>
b1 ;
06
b0 4
b0 F
1*
#208000
b1100010 +
b1100010 1
b1100010 J
b1100010 -
0*
0'
#209000
16
b1100 2
b1000 7
1/
0!
1*
#210000
b1100011 +
b1100011 1
b1100011 J
b1100011 -
0*
#211000
b0 ;
b0 8
b0 H
0/
b1100011 S
b1100 C
b1000 7
b1000 B
1!
1*
#212000
b111 3
b1 =
b1 I
b11 0
b1000111 #
b1000111 :
b1000111 K
b10 <
b110 5
b1 @
b1 A
b100 G
b1100 E
b1100100 +
b1100100 1
b1100100 J
b1100100 -
0*
1'
#213000
b1 D
1*
#214000
b1100101 -
0*
#215000
b1 ;
b1 4
06
b1 F
1*
#216000
0*
0'
#217000
16
b1101 2
b1001 7
1/
0!
1*
#218000
0*
#219000
b0 ;
b1 8
b1 H
0/
b1100100 L
b1101 C
b1001 7
b1001 B
1!
1*
#220000
b1000 3
b10 =
b10 I
b10 0
b1001011 #
b1001011 :
b1001011 K
b1100 G
b1101 E
b11 <
b110 5
b10 @
b11 A
0*
1'
#221000
b11 D
1*
