AMBA/AXI/AXI-stream/insert/code/stream_insert.v
/*
first beat:
keep_in:1111  keep_insert =0011;
keepout = 1111

last beat :
keep_in : 1000 keep_insert 0011
keepout :1110 ---> not has extra beat
keep_in : 1110 keep_insert 0011
keep_out : 1111
keep_out : 1000-->has extra beat
*/
module stream_insert #(
    parameter DATA_WD = 32,
    parameter DATA_BYTE_WD = DATA_WD / 8,
    parameter BYTE_CNT_WD = $clog2(DATA_BYTE_WD)
)(
    input                           clk,
    input                           rstn,

    input                           valid_in,
    input   [DATA_WD-1 : 0]         data_in,
    input                           last_in,
    input   [DATA_BYTE_WD-1 : 0]    keep_in,
    output                          ready_in,

    output                          valid_out,
    output  [DATA_WD-1 : 0]         data_out,
    output                          last_out,
    output   [DATA_BYTE_WD-1 : 0]   keep_out,
    input                           ready_out,

    input                           valid_insert,
    input   [DATA_WD-1 : 0]         data_insert,
    input   [DATA_BYTE_WD-1 : 0]    keep_insert,
    input   [BYTE_CNT_WD-1 : 0]     byte_insert_cnt,
    output                          ready_insert      
); 

localparam DATA_BIT_WD = $clog2(DATA_WD);

wire                            fire_in;
wire                            fire_out;
wire                            fire_insert;
wire    [2*DATA_WD-1 : 0]       d_data; 
wire    [2*DATA_WD-1 : 0]       d_data_first;  

wire    [2*DATA_BYTE_WD-1 : 0]  d_keep;
wire    [2*DATA_BYTE_WD-1 : 0]  d_keep_last;  
wire    [2*DATA_BYTE_WD-1 : 0]  d_keep_first;         
wire    [BYTE_CNT_WD : 0]       byte_shift_cnt;
wire    [DATA_BIT_WD-1 : 0]     bit_shift_cnt;

wire                            extra_beat;
wire                            has_extra_keep;
wire                            has_extra_beat;
wire [DATA_WD-1 : 0]            first_data;

reg                             extra_beat_r;
reg [DATA_WD-1 : 0]             data_r;
reg [DATA_BYTE_WD-1 : 0]        keep_r;
reg                             valid_r;
reg                             last_out_r;
reg                             first_beat;

assign has_extra_keep = | (keep_in << (3'b100 - byte_insert_cnt));
assign extra_beat = has_extra_beat && fire_in;
assign has_extra_beat = last_in && (has_extra_keep);

assign fire_in = valid_in && ready_in;
assign fire_out = valid_out && ready_out;
assign fire_insert = valid_insert && ready_insert;


assign d_data = {data_r,data_in};
assign d_data_first = {data_insert,data_in};


assign d_keep = {keep_r,keep_in};
assign d_keep_last = {keep_r,{DATA_BYTE_WD{1'b0}}};
assign d_keep_first = {keep_insert,keep_in};

assign byte_shift_cnt = byte_insert_cnt;
assign bit_shift_cnt = byte_shift_cnt << 3;

assign data_out = first_beat ? (d_data_first >> bit_shift_cnt) 
                    : (d_data>>bit_shift_cnt);
                    
//assign keep_out = extra_beat_r ? (d_keep_last >> byte_shift_cnt) : (d_keep >> byte_shift_cnt);
assign keep_out = first_beat ? (d_keep_first >> byte_shift_cnt) 
                    : (extra_beat_r ? (d_keep_last >> byte_shift_cnt) 
                    : (d_keep >> byte_shift_cnt));

assign ready_in = !valid_r || (ready_out && valid_insert && !extra_beat_r);

assign ready_insert = last_out && fire_out;


assign last_out = last_in ? !has_extra_beat : extra_beat_r;

assign valid_out = first_beat ? valid_insert && valid_in : 
                    (extra_beat_r ? valid_r : 
                        (valid_r && valid_in && valid_insert) ); //第一拍可以同时fire


always@(posedge clk or negedge rstn) begin
    if (!rstn) begin
        first_beat <= 1'b1;
    end else if (fire_out && last_out) begin
        first_beat <= 1'b1;
    end else if (fire_out) begin
        first_beat <= 1'b0;
    end
end



always@(posedge clk or negedge rstn) begin
    if (!rstn) begin
        extra_beat_r <= 1'b0;
        last_out_r <= 1'b0;
    end else begin
        if (extra_beat) begin
            extra_beat_r <= 1'b1;
        end else if (fire_out) begin
            extra_beat_r <= 1'b0;
        end
        
    end
end


always@(posedge clk or negedge rstn) begin
    if (!rstn) begin
        data_r <= 'b0;
        keep_r <= 'b0;
        valid_r <= 1'b0;
    end else begin
        if (fire_out) begin
            valid_r <= 1'b0;
        end
        if (has_extra_beat && fire_in) begin
            valid_r <= 1'b1;
        end else if (!has_extra_beat && fire_in) begin
            valid_r <= 1'b1;
        end else if (fire_in) begin
            valid_r <= 1'b1;
        end
        if (fire_in) begin
            data_r <= data_in;
            keep_r <= keep_in;
        end
    end
end










endmodule //stream_insert

AMBA/AXI/AXI-stream/insert/code/tb_stream_insert.v
module tb_stream_insert;

// stream_insert Parameters
parameter PERIOD        = 10                 ;
parameter DATA_WD       = 32                 ;
parameter DATA_BYTE_WD  = DATA_WD / 8        ;
parameter BYTE_CNT_WD   = $clog2(DATA_BYTE_WD);

// stream_insert Inputs
reg   clk                                 ;
reg   rstn                                ;
reg   valid_in                            ;
reg   [DATA_WD-1 : 0]  data_in            ;
wire   last_in                             ;
wire   [DATA_BYTE_WD-1 : 0]  keep_in       ;
reg   ready_out                           ;
reg   valid_insert                        ;
reg   [DATA_WD-1 : 0]  data_insert        ;
wire   [DATA_BYTE_WD-1 : 0]  keep_insert   ;
reg   [BYTE_CNT_WD-1 : 0]  byte_insert_cnt;

// stream_insert Outputs
wire  ready_in                             ;
wire  valid_out                            ;
wire  [DATA_WD-1 : 0]  data_out            ;
wire  last_out                             ;
wire  [DATA_BYTE_WD-1 : 0]  keep_out       ;
wire  ready_insert                         ;
reg   [BYTE_CNT_WD-1:0] last_invalid_byte_cnt;
reg [1:0] data_beat_cnt;
assign last_in = & data_beat_cnt;
assign keep_in = last_in ? ~((1 << last_invalid_byte_cnt) - 1) : ((1 << DATA_BYTE_WD ) -1);
assign keep_insert = (1 << DATA_BYTE_WD ) -1;
//
wire                            fire_in;
wire                            fire_out;
wire                            fire_insert;
assign fire_in = valid_in && ready_in;
assign fire_out = valid_out && ready_out;
assign fire_insert = valid_insert && ready_insert;

always@(posedge clk or negedge rstn) begin
    if (!rstn) begin
        data_in <= $random;
        data_insert <= $random;
    end else begin 
        if (fire_in) begin
            data_in <= $random; 
        end
        if (fire_insert) begin
            data_insert <= $random;
        end

    end
end

always@(posedge clk or negedge rstn) begin
    if (!rstn) begin
        byte_insert_cnt <= 'b0;
        data_beat_cnt <= 'b0;
        last_invalid_byte_cnt <= 'b0;
    end else begin
        byte_insert_cnt <= byte_insert_cnt + fire_insert;
        data_beat_cnt <= data_beat_cnt + fire_in;
        if (fire_out && last_out && (&byte_insert_cnt)) begin
             last_invalid_byte_cnt <= last_invalid_byte_cnt + 1'b1; 
             if (last_invalid_byte_cnt == DATA_BYTE_WD - 1) begin
                last_invalid_byte_cnt <= 'b0;
            end
        end            
    end
end

localparam  RANDOM = 1'b0;
generate if (RANDOM) begin
    always@(posedge clk or negedge rstn) begin
        if (!rstn) begin
            valid_insert <= 1'b0;
            valid_in <= 1'b0;
            ready_out <= 1'b1;
        end else begin
            if (!valid_insert || ready_insert) begin
                valid_insert <= $random;
            end
            if (!valid_in || ready_in) begin
                valid_in <= $random;
            end
            ready_out <= $random;
        end
    end
end else begin
    always@(posedge clk or negedge rstn) begin
        if (!rstn) begin
            valid_insert <= 1'b0;
            valid_in <= 1'b0;
            ready_out <= 1'b1;
        end else begin
            
            valid_insert <= 1'b1;
            valid_in <= 1'b1;
            ready_out <= 1'b1;
        end
    end
end
    
endgenerate







initial
begin
    clk = 0;
    forever #(PERIOD/2)  clk=~clk;
end

initial
begin
    rstn = 0;
    #(PERIOD*2) rstn  =  1;
end
initial begin
    $dumpfile("test.vcd");
    $dumpvars;
end

stream_insert #(
    .DATA_WD      ( DATA_WD      ),
    .DATA_BYTE_WD ( DATA_BYTE_WD ),
    .BYTE_CNT_WD  ( BYTE_CNT_WD  ))
 u_stream_insert (
    .clk                     ( clk                                   ),
    .rstn                    ( rstn                                  ),
    .valid_in                ( valid_in                              ),
    .data_in                 ( data_in          [DATA_WD-1 : 0]      ),
    .last_in                 ( last_in                               ),
    .keep_in                 ( keep_in          [DATA_BYTE_WD-1 : 0] ),
    .ready_out               ( ready_out                             ),
    .valid_insert            ( valid_insert                          ),
    .data_insert             ( data_insert      [DATA_WD-1 : 0]      ),
    .keep_insert             ( keep_insert      [DATA_BYTE_WD-1 : 0] ),
    .byte_insert_cnt         ( byte_insert_cnt  [BYTE_CNT_WD-1 : 0]  ),

    .ready_in                ( ready_in                              ),
    .valid_out               ( valid_out                             ),
    .data_out                ( data_out         [DATA_WD-1 : 0]      ),
    .last_out                ( last_out                              ),
    .keep_out                ( keep_out         [DATA_BYTE_WD-1 : 0] ),
    .ready_insert            ( ready_insert                          )
);

initial
begin
    #5000
    $finish;
end

endmodule

AMBA/AXI/AXI-stream/insert/sim/test.vcd
$date
	Thu Mar 02 00:30:45 2023
$end
$version
	Icarus Verilog
$end
$timescale
	1s
$end
$scope module tb_stream_insert $end
$var wire 1 ! fire_in $end
$var wire 1 " fire_insert $end
$var wire 1 # fire_out $end
$var wire 4 $ keep_insert [3:0] $end
$var wire 1 % valid_out $end
$var wire 1 & ready_insert $end
$var wire 1 ' ready_in $end
$var wire 1 ( last_out $end
$var wire 1 ) last_in $end
$var wire 4 * keep_out [3:0] $end
$var wire 4 + keep_in [3:0] $end
$var wire 32 , data_out [31:0] $end
$var reg 2 - byte_insert_cnt [1:0] $end
$var reg 1 . clk $end
$var reg 2 / data_beat_cnt [1:0] $end
$var reg 32 0 data_in [31:0] $end
$var reg 32 1 data_insert [31:0] $end
$var reg 2 2 last_invalid_byte_cnt [1:0] $end
$var reg 1 3 ready_out $end
$var reg 1 4 rstn $end
$var reg 1 5 valid_in $end
$var reg 1 6 valid_insert $end
$scope begin genblk2 $end
$upscope $end
$scope module u_stream_insert $end
$var wire 2 7 byte_insert_cnt [1:0] $end
$var wire 1 . clk $end
$var wire 32 8 data_in [31:0] $end
$var wire 32 9 data_insert [31:0] $end
$var wire 1 : extra_beat $end
$var wire 1 ; fire_in $end
$var wire 1 < fire_insert $end
$var wire 1 = fire_out $end
$var wire 1 > has_extra_beat $end
$var wire 4 ? keep_in [3:0] $end
$var wire 4 @ keep_insert [3:0] $end
$var wire 1 ) last_in $end
$var wire 1 ' ready_in $end
$var wire 1 & ready_insert $end
$var wire 1 3 ready_out $end
$var wire 1 4 rstn $end
$var wire 1 5 valid_in $end
$var wire 1 6 valid_insert $end
$var wire 1 % valid_out $end
$var wire 1 ( last_out $end
$var wire 4 A keep_out [3:0] $end
$var wire 1 B has_extra_keep $end
$var wire 32 C data_out [31:0] $end
$var wire 8 D d_keep_last [7:0] $end
$var wire 8 E d_keep_first [7:0] $end
$var wire 8 F d_keep [7:0] $end
$var wire 64 G d_data_first [63:0] $end
$var wire 64 H d_data [63:0] $end
$var wire 3 I byte_shift_cnt [2:0] $end
$var wire 5 J bit_shift_cnt [4:0] $end
$var reg 32 K data_r [31:0] $end
$var reg 1 L extra_beat_r $end
$var reg 1 M first_beat $end
$var reg 4 N keep_r [3:0] $end
$var reg 1 O last_out_r $end
$var reg 1 P valid_r $end
$upscope $end
$upscope $end
$enddefinitions $end
#0
$dumpvars
0P
0O
b0 N
1M
0L
b0 K
b0 J
b0 I
b10010000101010011010100100100 H
b1100000010001001010111101000000100010010000101010011010100100100 G
b1111 F
b11111111 E
b0 D
b10010000101010011010100100100 C
0B
b1111 A
b1111 @
b1111 ?
0>
0=
0<
0;
0:
b11000000100010010101111010000001 9
b10010000101010011010100100100 8
b0 7
06
05
04
13
b0 2
b11000000100010010101111010000001 1
b10010000101010011010100100100 0
b0 /
0.
b0 -
b10010000101010011010100100100 ,
b1111 +
b1111 *
0)
0(
1'
0&
0%
b1111 $
0#
0"
0!
$end
#5
b10000100100001001101011000001001 ,
b10000100100001001101011000001001 C
b10110001111100000101011001100011 1
b10110001111100000101011001100011 9
b10000100100001001101011000001001 H
b1011000111110000010101100110001110000100100001001101011000001001 G
b10000100100001001101011000001001 0
b10000100100001001101011000001001 8
1.
#10
0.
#15
b110101110010111101100001101 ,
b110101110010111101100001101 C
b1000110110111111001100110001101 1
b1000110110111111001100110001101 9
b110101110010111101100001101 H
b100011011011111100110011000110100000110101110010111101100001101 G
b110101110010111101100001101 0
b110101110010111101100001101 8
1.
#20
0.
14
#25
1=
1#
1%
1;
1!
15
16
1.
#30
0.
#35
1=
1#
b10110010110000101000010001100101 ,
b10110010110000101000010001100101 C
1%
0M
b11111111 F
b11110000 D
b1111 N
b110101110010111101100001101 K
1P
b11010111001011110110000110110110010110000101000010001100101 H
b100011011011111100110011000110110110010110000101000010001100101 G
b10110010110000101000010001100101 0
b10110010110000101000010001100101 8
b1 /
1.
#40
0.
#45
b10001001001101110101001000010010 ,
b10001001001101110101001000010010 C
b10 /
b100011011011111100110011000110110001001001101110101001000010010 G
b10001001001101110101001000010010 0
b10001001001101110101001000010010 8
b1011001011000010100001000110010110001001001101110101001000010010 H
b10110010110000101000010001100101 K
1P
1.
#50
0.
#55
1<
1"
b111100111110001100000001 ,
b111100111110001100000001 C
1&
1(
b10001001001101110101001000010010 K
1P
b1000100100110111010100100001001000000000111100111110001100000001 H
b100011011011111100110011000110100000000111100111110001100000001 G
b111100111110001100000001 0
b111100111110001100000001 8
1)
b11 /
1.
#60
0.
#65
0<
0"
0&
b1110110000001101101011111001101 ,
b1110110000001101101011111001101 C
0(
b1000 J
0)
b0 /
1B
b1 I
b1 -
b1 7
b111011001000111111000101110110 1
b111011001000111111000101110110 9
b11101100100011111100010111011000000110110101111100110100001101 G
b110110101111100110100001101 0
b110110101111100110100001101 8
b11110011111000110000000100000110110101111100110100001101 H
b111100111110001100000001 K
1P
1M
1.
#70
0.
#75
b1101000111101000110111001101 ,
b1101000111101000110111001101 C
0M
b110110101111100110100001101 K
1P
b11011010111110011010000110100011110100011011100110100111101 H
b11101100100011111100010111011000011110100011011100110100111101 G
b11110100011011100110100111101 0
b11110100011011100110100111101 8
b1 /
1.
#80
0.
#85
b111101011101101101010001010111 ,
b111101011101101101010001010111 C
b10 /
b11101100100011111100010111011001110110110101000101011111101101 G
b1110110110101000101011111101101 0
b1110110110101000101011111101101 8
b1111010001101110011010011110101110110110101000101011111101101 H
b11110100011011100110100111101 K
1P
1.
#90
0.
#95
0<
0"
b11101101010001100010110111110111 ,
b11101101010001100010110111110111 C
1:
0&
1>
0(
b1110110110101000101011111101101 K
1P
b111011011010100010101111110110101000110001011011111011110001100 H
b11101100100011111100010111011001000110001011011111011110001100 G
b1000110001011011111011110001100 0
b1000110001011011111011110001100 8
1)
b11 /
1.
#100
0.
#105
1<
1"
b1000 *
b1000 A
0:
1&
b10001100011111001111110111101001 ,
b10001100011111001111110111101001 C
0;
0!
0>
1(
0'
0)
b0 /
b11101100100011111100010111011001111100111111011110100111111001 G
b1111100111111011110100111111001 0
b1111100111111011110100111111001 8
b100011000101101111101111000110001111100111111011110100111111001 H
b1000110001011011111011110001100 K
1P
1L
1.
#110
0.
#115
0<
0"
b100100110001100111110011111101 ,
b100100110001100111110011111101 C
b1111 *
b1111 A
0&
1;
1!
0(
1'
b10000 J
1M
0L
0P
b1110001100110111001001001100011001111100111111011110100111111001 G
b11100011001101110010010011000110 1
b11100011001101110010010011000110 9
b10 I
b10 -
b10 7
1.
#120
0.
#125
b11101001111110011110001011110111 ,
b11101001111110011110001011110111 C
1=
1#
1%
b1 /
b1110001100110111001001001100011011100010111101111000010011000101 G
b11100010111101111000010011000101 0
b11100010111101111000010011000101 8
b111110011111101111010011111100111100010111101111000010011000101 H
b1111100111111011110100111111001 K
1P
0M
1.
#130
0.
#135
b10000100110001011101010100010011 ,
b10000100110001011101010100010011 C
b11100010111101111000010011000101 K
1P
b1110001011110111100001001100010111010101000100111101001010101010 H
b1110001100110111001001001100011011010101000100111101001010101010 G
b11010101000100111101001010101010 0
b11010101000100111101001010101010 8
b10 /
1.
#140
0.
#145
0<
0"
1:
0&
b11010010101010100111001010101111 ,
b11010010101010100111001010101111 C
1>
0(
1)
b11 /
b1110001100110111001001001100011001110010101011111111011111100101 G
b1110010101011111111011111100101 0
b1110010101011111111011111100101 8
b1101010100010011110100101010101001110010101011111111011111100101 H
b11010101000100111101001010101010 K
1P
1.
#150
0.
#155
b1100 *
b1100 A
0;
0!
1<
1"
0'
b11110111111001011011101111010010 ,
b11110111111001011011101111010010 C
0:
1&
0>
1(
1L
b1110010101011111111011111100101 K
1P
b111001010101111111101111110010110111011110100100111001001110111 H
b1110001100110111001001001100011010111011110100100111001001110111 G
b10111011110100100111001001110111 0
b10111011110100100111001001110111 8
0)
b0 /
1.
#160
0.
#165
0<
0"
1;
1!
0&
b110010110101100001001010111011 ,
b110010110101100001001010111011 C
b1111 *
b1111 A
b11000 J
1'
0(
b11 I
b11 -
b11 7
b1000100100110010110101100001001010111011110100100111001001110111 G
b10001001001100101101011000010010 1
b10001001001100101101011000010010 9
0P
0L
1M
1.
#170
0.
#175
1=
1#
b11010010011100100111011101000111 ,
b11010010011100100111011101000111 C
1%
0M
b10111011110100100111001001110111 K
1P
b1011101111010010011100100111011101000111111011001101101110001111 H
b1000100100110010110101100001001001000111111011001101101110001111 G
b1000111111011001101101110001111 0
b1000111111011001101101110001111 8
b1 /
1.
#180
0.
#185
b11101100110110111000111101111001 ,
b11101100110110111000111101111001 C
b10 /
b1000100100110010110101100001001001111001001100000110100111110010 G
b1111001001100000110100111110010 0
b1111001001100000110100111110010 8
b100011111101100110110111000111101111001001100000110100111110010 H
b1000111111011001101101110001111 K
1P
1.
#190
0.
#195
0<
0"
b110000011010011111001011100111 ,
b110000011010011111001011100111 C
1:
0&
1>
0(
b1111001001100000110100111110010 K
1P
b111100100110000011010011111001011100111011101101001011011001110 H
b1000100100110010110101100001001011100111011101101001011011001110 G
b11100111011101101001011011001110 0
b11100111011101101001011011001110 8
1)
b11 /
1.
#200
0.
#205
1<
1"
b1110 *
b1110 A
0:
1&
b1110110100101101100111011110100 ,
b1110110100101101100111011110100 C
0;
0!
0>
1(
0'
0)
b0 /
b1000100100110010110101100001001011110100000000000111101011101000 G
b11110100000000000111101011101000 0
b11110100000000000111101011101000 8
b1110011101110110100101101100111011110100000000000111101011101000 H
b11100111011101101001011011001110 K
1P
1L
1.
#210
0.
#215
0<
0"
b11110100000000000111101011101000 ,
b11110100000000000111101011101000 C
b1111 *
b1111 A
0&
1;
1!
0(
1'
b0 J
1M
0L
0P
b1110001011001010010011101100010111110100000000000111101011101000 G
b11100010110010100100111011000101 1
b11100010110010100100111011000101 9
b1 2
0B
b0 I
b0 -
b0 7
1.
#220
0.
#225
b101110010110000100100101011100 ,
b101110010110000100100101011100 C
1=
1#
1%
b1 /
b1110001011001010010011101100010100101110010110000100100101011100 G
b101110010110000100100101011100 0
b101110010110000100100101011100 8
b1111010000000000011110101110100000101110010110000100100101011100 H
b11110100000000000111101011101000 K
1P
0M
1.
#230
0.
#235
b11011110100011100010100010111101 ,
b11011110100011100010100010111101 C
b101110010110000100100101011100 K
1P
b10111001011000010010010101110011011110100011100010100010111101 H
b1110001011001010010011101100010111011110100011100010100010111101 G
b11011110100011100010100010111101 0
b11011110100011100010100010111101 8
b10 /
1.
#240
0.
#245
b1110 *
b1110 A
1<
1"
1&
b10010110101010110101100000101101 ,
b10010110101010110101100000101101 C
b11111110 F
b11111110 E
b1110 +
b1110 ?
1(
1)
b11 /
b1110001011001010010011101100010110010110101010110101100000101101 G
b10010110101010110101100000101101 0
b10010110101010110101100000101101 8
b1101111010001110001010001011110110010110101010110101100000101101 H
b11011110100011100010100010111101 K
1P
1.
#250
0.
#255
0<
0"
b1111 *
b1111 A
b1100011101100101010011100100110 ,
b1100011101100101010011100100110 C
0&
1B
b11111111 E
b1111 +
b1111 ?
0(
b1000 J
1M
b11101111 F
b11100000 D
b1110 N
b10010110101010110101100000101101 K
1P
b10110001111011110110001001100011 1
b10110001111011110110001001100011 9
b1001011010101011010110000010110110110010101001110010011001100101 H
b1011000111101111011000100110001110110010101001110010011001100101 G
b10110010101001110010011001100101 0
b10110010101001110010011001100101 8
0)
b0 /
b1 I
b1 -
b1 7
1.
#260
0.
#265
b1100101000001010111001110000111 ,
b1100101000001010111001110000111 C
b1111 *
b1111 A
b1 /
b1011000111101111011000100110001100000101011100111000011100001010 G
b101011100111000011100001010 0
b101011100111000011100001010 8
b11111111 F
b11110000 D
b1111 N
b1011001010100111001001100110010100000101011100111000011100001010 H
b10110010101001110010011001100101 K
1P
0M
1.
#270
0.
#275
b1010110000000011101100100010 ,
b1010110000000011101100100010 C
b101011100111000011100001010 K
1P
b10101110011100001110000101011000000001110110010001010000000 H
b1011000111101111011000100110001111000000001110110010001010000000 G
b11000000001110110010001010000000 0
b11000000001110110010001010000000 8
b10 /
1.
#280
0.
#285
1<
1"
0:
1&
b10000000000100000110010000100001 ,
b10000000000100000110010000100001 C
0B
b11111110 F
b11111110 E
b1110 +
b1110 ?
0>
1(
1)
b11 /
b1011000111101111011000100110001100010000011001000010000100100000 G
b10000011001000010000100100000 0
b10000011001000010000100100000 8
b1100000000111011001000101000000000010000011001000010000100100000 H
b11000000001110110010001010000000 K
1P
1.
#290
0.
#295
0<
0"
b11001100100111010101010101111000 ,
b11001100100111010101010101111000 C
0&
b11111111 E
b1111 +
b1111 ?
0(
b10000 J
1M
b11101111 F
b11100000 D
b1110 N
b10000011001000010000100100000 K
1P
b11001110110011001100110010011101 1
b11001110110011001100110010011101 9
b1000001100100001000010010000001010101011110000100010110101010 H
b1100111011001100110011001001110101010101011110000100010110101010 G
b1010101011110000100010110101010 0
b1010101011110000100010110101010 8
0)
b0 /
1B
b10 I
b10 -
b10 7
1.
#300
0.
#305
b1000101101010101100101100100000 ,
b1000101101010101100101100100000 C
b1111 *
b1111 A
b1 /
b1100111011001100110011001001110111001011001000000011111010010110 G
b11001011001000000011111010010110 0
b11001011001000000011111010010110 8
b11111111 F
b11110000 D
b1111 N
b101010101111000010001011010101011001011001000000011111010010110 H
b1010101011110000100010110101010 K
1P
0M
1.
#310
0.
#315
b111110100101101000100110000011 ,
b111110100101101000100110000011 C
b11001011001000000011111010010110 K
1P
b1100101100100000001111101001011010001001100000111011100000010011 H
b1100111011001100110011001001110110001001100000111011100000010011 G
b10001001100000111011100000010011 0
b10001001100000111011100000010011 8
b10 /
1.
#320
0.
#325
0<
0"
1:
0&
b10111000000100111000011010111100 ,
b10111000000100111000011010111100 C
b11111110 F
b11111110 E
b1110 +
b1110 ?
1>
0(
1)
b11 /
b1100111011001100110011001001110110000110101111000011100000001101 G
b10000110101111000011100000001101 0
b10000110101111000011100000001101 8
b1000100110000011101110000001001110000110101111000011100000001101 H
b10001001100000111011100000010011 K
1P
1.
#330
0.
#335
0;
0!
b1000 *
b1000 A
1<
1"
0'
b111000000011011010100110100111 ,
b111000000011011010100110100111 C
0:
1&
b11111111 E
b1111 +
b1111 ?
0>
1(
1L
b11101111 F
b11100000 D
b1110 N
b10000110101111000011100000001101 K
1P
b1000011010111100001110000000110110101001101001111101011001010011 H
b1100111011001100110011001001110110101001101001111101011001010011 G
b10101001101001111101011001010011 0
b10101001101001111101011001010011 8
0)
b0 /
1.
#340
0.
#345
0<
0"
1;
1!
0&
b10011111110111010110101110101001 ,
b10011111110111010110101110101001 C
b1111 *
b1111 A
b11000 J
1'
0(
b11 I
b11 -
b11 7
b11010110011111110111010110101110101001101001111101011001010011 G
b110101100111111101110101101011 1
b110101100111111101110101101011 9
0P
0L
1M
1.
#350
0.
#355
1=
1#
b10100111110101100101001111101010 ,
b10100111110101100101001111101010 C
1%
0M
b11111111 F
b11110000 D
b1111 N
b10101001101001111101011001010011 K
1P
b1010100110100111110101100101001111101010101001100010101011010101 H
b11010110011111110111010110101111101010101001100010101011010101 G
b11101010101001100010101011010101 0
b11101010101001100010101011010101 8
b1 /
1.
#360
0.
#365
b10100110001010101101010110000001 ,
b10100110001010101101010110000001 C
b10 /
b11010110011111110111010110101110000001000101110100101000000010 G
b10000001000101110100101000000010 0
b10000001000101110100101000000010 8
b1110101010100110001010101101010110000001000101110100101000000010 H
b11101010101001100010101011010101 K
1P
1.
#370
0.
#375
0<
0"
b10111010010100000001011010111 ,
b10111010010100000001011010111 C
1:
0&
b11111110 F
b11111110 E
b1110 +
b1110 ?
1>
0(
b10000001000101110100101000000010 K
1P
b1000000100010111010010100000001011010111010101100011111010101110 H
b11010110011111110111010110101111010111010101100011111010101110 G
b11010111010101100011111010101110 0
b11010111010101100011111010101110 8
1)
b11 /
1.
#380
0.
#385
1<
1"
b1100 *
b1100 A
0:
1&
b1010110001111101010111000001110 ,
b1010110001111101010111000001110 C
0;
0!
b11111111 E
b1111 +
b1111 ?
0>
1(
0'
0)
b0 /
b11010110011111110111010110101100001110111111111110100100011101 G
b1110111111111110100100011101 0
b1110111111111110100100011101 8
b11101111 F
b11100000 D
b1110 N
b1101011101010110001111101010111000001110111111111110100100011101 H
b11010111010101100011111010101110 K
1P
1L
1.
#390
0.
#395
0<
0"
b1110111111111110100100011101 ,
b1110111111111110100100011101 C
b1111 *
b1111 A
0&
1;
1!
0(
1'
b0 J
1M
0L
0P
b1110011111000101011100101100111100001110111111111110100100011101 G
b11100111110001010111001011001111 1
b11100111110001010111001011001111 9
b10 2
0B
b0 I
b0 -
b0 7
1.
#400
0.
#405
b10001100001000100100100100011 ,
b10001100001000100100100100011 C
1=
1#
1%
b1 /
b1110011111000101011100101100111100010001100001000100100100100011 G
b10001100001000100100100100011 0
b10001100001000100100100100011 8
b11111111 F
b11110000 D
b1111 N
b111011111111111010010001110100010001100001000100100100100011 H
b1110111111111110100100011101 K
1P
0M
1.
#410
0.
#415
b101000010010110010100001010 ,
b101000010010110010100001010 C
b10001100001000100100100100011 K
1P
b1000110000100010010010010001100000101000010010110010100001010 H
b1110011111000101011100101100111100000101000010010110010100001010 G
b101000010010110010100001010 0
b101000010010110010100001010 8
b10 /
1.
#420
0.
#425
b1100 *
b1100 A
1<
1"
1&
b11100101011100110000101011001010 ,
b11100101011100110000101011001010 C
b11111100 F
b11111100 E
b1100 +
b1100 ?
1(
1)
b11 /
b1110011111000101011100101100111111100101011100110000101011001010 G
b11100101011100110000101011001010 0
b11100101011100110000101011001010 8
b10100001001011001010000101011100101011100110000101011001010 H
b101000010010110010100001010 K
1P
1.
#430
0.
#435
0<
0"
b1111 *
b1111 A
b11110010100111100011000101001100 ,
b11110010100111100011000101001100 C
0&
1B
b11111111 E
b1111 +
b1111 ?
0(
b1000 J
1M
b11001111 F
b11000000 D
b1100 N
b11100101011100110000101011001010 K
1P
b1111001011010001011110111110010 1
b1111001011010001011110111110010 9
b1110010101110011000010101100101010011110001100010100110000111100 H
b111100101101000101111011111001010011110001100010100110000111100 G
b10011110001100010100110000111100 0
b10011110001100010100110000111100 8
0)
b0 /
b1 I
b1 -
b1 7
1.
#440
0.
#445
b111100010001010010111001100001 ,
b111100010001010010111001100001 C
b1111 *
b1111 A
b1 /
b111100101101000101111011111001001000101001011100110000110001010 G
b1000101001011100110000110001010 0
b1000101001011100110000110001010 8
b11111111 F
b11110000 D
b1111 N
b1001111000110001010011000011110001000101001011100110000110001010 H
b10011110001100010100110000111100 K
1P
0M
1.
#450
0.
#455
b10001010001000001100010010110011 ,
b10001010001000001100010010110011 C
b1000101001011100110000110001010 K
1P
b100010100101110011000011000101000100000110001001011001101000001 H
b111100101101000101111011111001000100000110001001011001101000001 G
b100000110001001011001101000001 0
b100000110001001011001101000001 8
b10 /
1.
#460
0.
#465
b1110 *
b1110 A
1<
1"
0:
1&
b1000001111011000100101100110100 ,
b1000001111011000100101100110100 C
0B
b11111100 F
b11111100 E
b1100 +
b1100 ?
0>
1(
1)
b11 /
b111100101101000101111011111001011101100010010110011010011011000 G
b11101100010010110011010011011000 0
b11101100010010110011010011011000 8
b10000011000100101100110100000111101100010010110011010011011000 H
b100000110001001011001101000001 K
1P
1.
#470
0.
#475
0<
0"
b1111 *
b1111 A
b10010100010010011110000100000 ,
b10010100010010011110000100000 C
0&
1B
b11111111 E
b1111 +
b1111 ?
0(
b10000 J
1M
b11001111 F
b11000000 D
b1100 N
b11101100010010110011010011011000 K
1P
b11000100100010100001001010001001 1
b11000100100010100001001010001001 9
b1110110001001011001101001101100000111100001000001111001101111000 H
b1100010010001010000100101000100100111100001000001111001101111000 G
b111100001000001111001101111000 0
b111100001000001111001101111000 8
0)
b0 /
b10 I
b10 -
b10 7
1.
#480
0.
#485
b11110011011110000111010111000101 ,
b11110011011110000111010111000101 C
b1111 *
b1111 A
b1 /
b1100010010001010000100101000100101110101110001010000110111101011 G
b1110101110001010000110111101011 0
b1110101110001010000110111101011 8
b11111111 F
b11110000 D
b1111 N
b11110000100000111100110111100001110101110001010000110111101011 H
b111100001000001111001101111000 K
1P
0M
1.
#490
0.
#495
b1101111010110101101100000010 ,
b1101111010110101101100000010 C
b1110101110001010000110111101011 K
1P
b111010111000101000011011110101101011011000000100110010110110110 H
b1100010010001010000100101000100101011011000000100110010110110110 G
b1011011000000100110010110110110 0
b1011011000000100110010110110110 8
b10 /
1.
#500
0.
#505
1<
1"
0:
1&
b1100101101101100110001101001011 ,
b1100101101101100110001101001011 C
0B
b11111100 F
b11111100 E
b1100 +
b1100 ?
0>
1(
1)
b11 /
b1100010010001010000100101000100101100011010010111111100111000110 G
b1100011010010111111100111000110 0
b1100011010010111111100111000110 8
b101101100000010011001011011011001100011010010111111100111000110 H
b1011011000000100110010110110110 K
1P
1.
#510
0.
#515
0<
0"
b1110101000000101011110001010111 ,
b1110101000000101011110001010111 C
0&
b11111111 E
b1111 +
b1111 ?
0(
b11000 J
1M
b11001111 F
b11000000 D
b1100 N
b1100011010010111111100111000110 K
1P
b11011110011101010000001010111100 1
b11011110011101010000001010111100 9
b110001101001011111110011100011001010111000101010001001110101110 H
b1101111001110101000000101011110001010111000101010001001110101110 G
b1010111000101010001001110101110 0
b1010111000101010001001110101110 8
0)
b0 /
1B
b11 I
b11 -
b11 7
1.
#520
0.
