mcp/code/sync2.v
module sync2 (
    input clk,
    input rstn,
    input din,
    
    output  dout
);
   

    reg sync0,sync1 ;

    always @(posedge clk or negedge rstn) begin
        if(~rstn)
            sync0 <= 1'b0;
        else 
            sync0 <= din;    
    end

    always @(posedge clk or negedge rstn) begin
        if (~rstn) begin
            sync1 <= 1'b0;
        end
        else
            sync1 <= sync0 ;     
    end

    assign  dout = sync1;

endmodule

mcp/code/mcp.v
module mcp #(
    parameter DWIDTH = 8
)
 (
    input clk_a,
    input [DWIDTH-1:0]adatain,
    input asend,
    input rstn_a,
    output aready,

    input clk_b,
    input rstn_b,
    input bload,
    output bvalid,
    output reg [DWIDTH-1:0] bdata
);

//-----------------clk_a domain-----------------------//
    wire din_cap; // 1 cycle pluse
    reg [DWIDTH-1:0] adata;
    reg a_en;

    assign din_cap = asend & aready;
    always @(posedge clk_a ) begin
        if (din_cap) 
            adata <= adatain;
    end

    //pluse--->level
    always @(posedge clk_a or negedge rstn_a) begin
        if(~rstn_a)
            a_en <= 0;
        else if (din_cap)
            a_en <= ~a_en;    
    end


    //level --> pluse
    wire b_ack_sync2;
    reg  b_ack_sync3;
    wire a_ack;
    reg   b_ack;

    sync2 b_ack_1 (
        .clk  ( clk_a  ),
        .rstn ( rstn_a ),
        .din  ( b_ack  ),
        .dout ( b_ack_sync2 ) 
    );

    always @(posedge clk_a or negedge rstn_a) begin
        if(~rstn_a) 
            b_ack_sync3 <= 0;
        else 
            b_ack_sync3 <= b_ack_sync2;    
    end

    assign a_ack = b_ack_sync2 ^ b_ack_sync3;

    //FSM
    /*
    a_fsm afsm (
        .clk_a  ( clk_a  ),
        .rstn_a ( rstn_a ),
        .asend  ( asend  ),
        .a_ack  ( a_ack  ),
        .aready ( aready )

    );*/

    reg aready_m;
    always @(posedge clk_a or negedge rstn_a) begin
       if(~rstn_a) 
            aready_m <= 1;
        else if (asend) begin
            aready_m <= 0;
        end  else if (a_ack) begin
            aready_m <= 1;
        end
    end
    assign aready = aready_m;


//-------------------clk_b domain----------------------------//
    wire  a_en_sync2;
    reg   a_en_sync3;
    wire  b_en;
    wire  bload_data;
    

    // level-->pluse
    sync2 a_en_1 (
        .clk(clk_b),
        .rstn(rstn_b),
        .din (a_en),
        .dout(a_en_sync2)
    );
    
    always @(posedge clk_b or negedge rstn_b) begin
        if(~rstn_b)
            a_en_sync3 <= 0;
        else 
            a_en_sync3 <= a_en_sync2;
    end

    assign b_en = a_en_sync2 ^ a_en_sync3; 
//FSM
 /*   b_fsm bfsm (
        .clk_b  (clk_b),
        .rstn_b ( rstn_b),
        .b_en   ( b_en  ),
        .bload  ( bload ),
        .bvalid ( bvalid )
    );  */

    reg bvalid_m ;
    always @(posedge clk_b or negedge rstn_b) begin
        if (~rstn_b)
            bvalid_m <= 0;
        else if (b_en) begin
            bvalid_m <= 1;
        end else if (bload) begin
            bvalid_m <= 0;
        end
    end
    assign bvalid = bvalid_m;


    assign bload_data = bvalid & bload;//pluse

    always @(posedge clk_b ) begin
        if (bload_data)
            bdata <= adata;
    end

    always @(posedge clk_b or negedge rstn_b) begin
        if(~rstn_b)
            b_ack <= 0;
        else if (bload_data)
            b_ack <= ~b_ack;    
    end




endmodule //mcp

mcp/code/mcp_tb.v
module mcp_tb ();
    parameter  DWIDTH = 8;
    reg clk_a;
    reg [DWIDTH-1:0] adatain;
    reg asend;
    reg rstn_a;
    wire aready;

    reg clk_b;
    reg rstn_b;
    reg bload;
    wire bvalid;
    wire  [DWIDTH-1:0] bdata;

    always #1 clk_a = ~clk_a;
    always #4 clk_b = ~clk_b;
    initial begin
        clk_a = 0;
        clk_b = 0;
        asend = 0;
        rstn_a = 0;
        rstn_b = 0;
        adatain = 0;
        bload  = 0;

        #1;rstn_a = 1;rstn_b = 1;
        @(posedge clk_a)#0.1;
        asend = 1;
        @(posedge clk_a)#0.1;
        asend = 0;
        adatain = 8'd1;
        //wait(b_en == 1); bload = 1;
        repeat(4) @(posedge clk_a);
        @(posedge clk_b);
        bload = 1;
        repeat(3) @(posedge clk_b);
        bload = 0;



        //wait(a_ack == 1);
        @(posedge clk_b);
        repeat(2) @(posedge clk_a)#0.1;
        asend   = 1;
        @(posedge clk_a)#0.1;
        adatain = 8'd2;
         asend = 0;
        //wait(b_en == 1); bload = 1;
        repeat(4) @(posedge clk_a);
        bload = 1;
        repeat(3) @(posedge clk_b);
        bload = 0;

        @(posedge clk_b);
        repeat(2) @(posedge clk_a);#0.1
        asend   = 1;
        @(posedge clk_a);#0.1
        adatain = 8'd3;
        asend = 0;
        //wait(b_en == 1); bload = 1;
        repeat(4) @(posedge clk_a);
        bload = 1;
        repeat(3) @(posedge clk_b);
        bload = 0;

        @(posedge clk_b);
        repeat(2) @(posedge clk_a);#0.1
        asend   = 1;
        @(posedge clk_a);#0.1
        adatain = 8'd4;
         asend = 0;
        //wait(b_en == 1); bload = 1;
        repeat(4) @(posedge clk_a);
        bload = 1;
        repeat(3) @(posedge clk_b);
        bload = 0;

        @(posedge clk_b);
        repeat(2) @(posedge clk_a);#0.1
        asend   = 1;
        @(posedge clk_a);#0.1
        adatain = 8'd5;
         asend = 0;
        //wait(b_en == 1); bload = 1;
        repeat(4) @(posedge clk_a);
        bload = 1;
        repeat(3) @(posedge clk_b);
        bload = 0;

        @(posedge clk_b);
        repeat(2) @(posedge clk_a);
        asend   = 1;
        @(posedge clk_a);#0.1
        adatain = 8'd6;
         asend = 0;
        //wait(b_en == 1); bload = 1;
        repeat(4) @(posedge clk_a);
        bload = 1;
        repeat(3) @(posedge clk_b);
        bload = 0;

        @(posedge clk_b);
        repeat(2) @(posedge clk_a);#0.1
        asend   = 1;
        @(posedge clk_a);#0.1
        //adatain = 8'd7;
         asend = 0;
        //wait(b_en == 1); bload = 1;
        repeat(4) @(posedge clk_a);
        bload = 1;
        repeat(3) @(posedge clk_b);
        bload = 0;



        #200
        $finish();

        
    end

    initial begin
		$dumpfile("test.vcd");
        $dumpvars;
	end

    mcp u_mcp (
        .clk_a   (clk_a),
        .adatain (adatain),
        .asend   (asend),
        .rstn_a  (rstn_a),
        .aready  (aready),

        .clk_b   (clk_b),
        .rstn_b  (rstn_b),
        .bload   (bload),
        .bvalid  (bvalid),
        .bdata   (bdata)
    );


endmodule //mcp_tb

mcp/code/b_fsm.v
module b_fsm (
    input  clk_b,
    input  rstn_b,
    input  b_en,
    input  bload,
    output bvalid    
);

    parameter WAIT = 1'b0, READY = 1'b1;
    reg c_state,n_state;

    always @(posedge clk_b or negedge rstn_b) begin
        if(~rstn_b)
            c_state <= WAIT;
        else 
            c_state <= n_state;
    end

    always @(*) begin
        case(c_state)
        WAIT:
            begin
                if(b_en) n_state = READY;
                else     n_state = WAIT;
            end
        READY:
            begin
                if(bload) n_state = WAIT;
                else      n_state = READY;
            end   

        endcase
    end
    
    assign bvalid = c_state;


endmodule //b_fsm

mcp/code/a_fsm.v
module a_fsm (
    input clk_a,
    input rstn_a,
    input asend,
    input a_ack,
    output aready

);
    parameter READY = 1'b1, BUSY = 1'b0;
    reg c_state,n_state;

    always @(posedge clk_a or negedge rstn_a) begin
        if(~rstn_a) 
            c_state <= READY;
        else
            c_state <= n_state;    
    end

  always @(*) begin
    case(c_state)
    READY:
        begin
            if(asend) n_state = BUSY;
            else      n_state = READY;
        end
    BUSY:
        begin
            if(a_ack) n_state = READY;
            else      n_state = BUSY;
        end     
        
    endcase
  end

  assign aready = c_state;

endmodule //a_fsm

mcp/sim/test.vcd
$date
	Sat Sep 23 11:40:27 2023
$end
$version
	Icarus Verilog
$end
$timescale
	1s
$end
$scope module a_fsm $end
$var wire 1 ! a_ack $end
$var wire 1 " aready $end
$var wire 1 # asend $end
$var wire 1 $ clk_a $end
$var wire 1 % rstn_a $end
$var reg 1 & c_state $end
$var reg 1 ' n_state $end
$upscope $end
$scope module b_fsm $end
$var wire 1 ( b_en $end
$var wire 1 ) bload $end
$var wire 1 * bvalid $end
$var wire 1 + clk_b $end
$var wire 1 , rstn_b $end
$var reg 1 - c_state $end
$var reg 1 . n_state $end
$upscope $end
$scope module mcp_tb $end
$var wire 1 / bvalid $end
$var wire 8 0 bdata [7:0] $end
$var wire 1 1 aready $end
$var reg 8 2 adatain [7:0] $end
$var reg 1 3 asend $end
$var reg 1 4 bload $end
$var reg 1 5 clk_a $end
$var reg 1 6 clk_b $end
$var reg 1 7 rstn_a $end
$var reg 1 8 rstn_b $end
$scope module u_mcp $end
$var wire 1 9 a_ack $end
$var wire 8 : adatain [7:0] $end
$var wire 1 3 asend $end
$var wire 1 ; b_en $end
$var wire 1 4 bload $end
$var wire 1 < bload_data $end
$var wire 1 5 clk_a $end
$var wire 1 6 clk_b $end
$var wire 1 = din_cap $end
$var wire 1 7 rstn_a $end
$var wire 1 8 rstn_b $end
$var wire 1 / bvalid $end
$var wire 1 > b_ack_sync2 $end
$var wire 1 1 aready $end
$var wire 1 ? a_en_sync2 $end
$var reg 1 @ a_en $end
$var reg 1 A a_en_sync3 $end
$var reg 8 B adata [7:0] $end
$var reg 1 1 aready_m $end
$var reg 1 C b_ack $end
$var reg 1 D b_ack_sync3 $end
$var reg 8 E bdata [7:0] $end
$var reg 1 / bvalid_m $end
$scope module a_en_1 $end
$var wire 1 6 clk $end
$var wire 1 @ din $end
$var wire 1 8 rstn $end
$var wire 1 ? dout $end
$var reg 1 F sync0 $end
$var reg 1 ? sync1 $end
$upscope $end
$scope module b_ack_1 $end
$var wire 1 5 clk $end
$var wire 1 C din $end
$var wire 1 7 rstn $end
$var wire 1 > dout $end
$var reg 1 G sync0 $end
$var reg 1 > sync1 $end
$upscope $end
$upscope $end
$upscope $end
$enddefinitions $end
#0
$dumpvars
0G
0F
bx E
0D
0C
bx B
0A
0@
0?
0>
0=
0<
0;
b0 :
09
08
07
06
05
04
03
b0 2
11
bx 0
0/
x.
x-
z,
z+
x*
z)
z(
x'
x&
z%
z$
z#
x"
z!
$end
#1
18
17
15
#2
05
#3
1=
13
15
#4
05
16
#5
01
1@
b0 B
0=
b1 2
b1 :
03
15
#6
05
#7
15
#8
05
06
#9
15
#10
05
#11
15
#12
1F
05
16
#13
15
#14
05
#15
15
#16
05
06
#17
15
#18
05
#19
15
#20
1;
1?
14
05
16
#21
15
#22
05
#23
15
#24
05
06
#25
15
#26
05
#27
15
#28
0;
1<
1A
1/
05
16
#29
15
#30
05
#31
15
#32
05
06
#33
15
#34
05
#35
15
#36
0<
1C
0/
b0 0
b0 E
05
16
#37
1G
15
#38
05
#39
19
1>
15
#40
05
06
#41
09
11
1D
15
#42
05
#43
15
#44
04
05
16
#45
15
#46
05
#47
15
#48
05
06
#49
15
#50
05
#51
15
#52
05
16
#53
15
#54
05
#55
1=
13
15
#56
05
06
#57
01
0@
b1 B
0=
03
b10 2
b10 :
15
#58
05
#59
15
#60
0F
05
16
#61
15
#62
05
#63
15
#64
05
06
#65
14
15
#66
05
#67
15
#68
1;
0?
05
16
#69
15
#70
05
#71
15
#72
05
06
#73
15
#74
05
#75
15
#76
0;
1<
0A
1/
05
16
#77
15
#78
05
#79
15
#80
05
06
#81
15
#82
05
#83
15
#84
0C
b1 0
b1 E
0<
04
05
16
#85
0G
15
#86
05
#87
19
0>
15
#88
05
06
#89
09
11
0D
15
#90
05
#91
15
#92
05
16
#93
15
#94
05
#95
1=
13
15
#96
05
06
#97
01
1@
b10 B
0=
03
b11 2
b11 :
15
#98
05
#99
15
#100
1F
05
16
#101
15
#102
05
#103
15
#104
05
06
#105
1<
14
15
#106
05
#107
15
#108
1;
0<
1?
0/
1C
b10 0
b10 E
05
16
#109
1G
15
#110
05
#111
19
1>
15
#112
05
06
#113
09
11
1D
15
#114
05
#115
15
#116
1<
0;
1/
1A
05
16
#117
15
#118
05
#119
15
#120
05
06
#121
15
#122
05
#123
15
#124
0C
0<
04
05
16
#125
0G
15
#126
05
#127
19
0>
15
#128
05
06
#129
09
0D
15
#130
05
#131
15
#132
05
16
#133
15
#134
05
#135
1=
13
15
#136
05
06
#137
01
0@
b11 B
0=
03
b100 2
b100 :
15
#138
05
#139
15
#140
0F
05
16
#141
15
#142
05
#143
15
#144
05
06
#145
1<
14
15
#146
05
#147
15
#148
0<
1;
1C
0/
0?
b11 0
b11 E
05
16
#149
1G
15
#150
05
#151
19
1>
15
#152
05
06
#153
09
11
1D
15
#154
05
#155
15
#156
0;
1<
0A
1/
05
16
#157
15
#158
05
#159
15
#160
05
06
#161
15
#162
05
#163
15
#164
0C
0<
04
05
16
#165
0G
15
#166
05
#167
19
0>
15
#168
05
06
#169
09
0D
15
#170
05
#171
15
#172
05
16
#173
15
#174
05
#175
1=
13
15
#176
05
06
#177
01
1@
b100 B
0=
03
b101 2
b101 :
15
#178
05
#179
15
#180
1F
05
16
#181
15
#182
05
#183
15
#184
05
06
#185
1<
14
15
#186
05
#187
15
#188
1;
0<
1?
0/
1C
b100 0
b100 E
05
16
#189
1G
15
#190
05
#191
19
1>
15
#192
05
06
#193
09
11
1D
15
#194
05
#195
15
#196
1<
0;
1/
1A
05
16
#197
15
#198
05
#199
15
#200
05
06
#201
15
#202
05
#203
15
#204
0C
0<
04
05
16
#205
0G
15
#206
05
#207
19
0>
15
#208
05
06
#209
09
0D
15
#210
05
#211
15
#212
05
16
#213
15
#214
05
#215
01
0=
13
15
#216
05
06
#217
03
b110 2
b110 :
15
#218
05
#219
15
#220
05
16
#221
15
#222
05
#223
15
#224
05
06
#225
1<
14
15
#226
05
#227
15
#228
0<
1C
0/
05
16
#229
1G
15
#230
05
#231
19
1>
15
#232
05
06
#233
09
11
1D
15
#234
05
#235
15
#236
05
16
#237
15
#238
05
#239
15
#240
05
06
#241
15
#242
05
#243
15
#244
04
05
16
#245
15
#246
05
#247
15
#248
05
06
#249
15
#250
05
#251
15
#252
05
16
#253
15
#254
05
#255
1=
13
15
#256
05
06
#257
01
0@
b110 B
0=
03
15
#258
05
#259
15
#260
0F
05
16
#261
15
#262
05
#263
15
#264
05
06
#265
14
15
#266
05
#267
15
#268
1;
0?
05
16
#269
15
#270
05
#271
15
#272
05
06
#273
15
#274
05
#275
15
#276
1<
0;
1/
0A
05
16
#277
15
#278
05
#279
15
#280
05
06
#281
15
#282
05
#283
15
#284
0C
b110 0
b110 E
0<
04
05
16
#285
0G
15
#286
05
#287
19
0>
15
#288
05
06
#289
09
11
0D
15
