FIFO/async_fifo/code/dpram.v
module dpram #(
    parameter DATESIZE = 8,
    parameter ADDRSIZE = 4
)(
    input clka,
    input ena,
    input wea,
    input [DATESIZE-1:0] dina,
    input [ADDRSIZE-1:0] addra,

    input clkb,
    input enb,
    input [ADDRSIZE-1:0] addrb,
    output  reg [DATESIZE-1:0]doutb
);
    parameter DEPTH = 1<<ADDRSIZE;
    reg [DATESIZE-1:0] mem [DEPTH-1:0];

    always @(posedge clkb) begin  //read
        if(enb) 
            doutb <= mem[addrb];
    end

    always @(posedge clka) begin //write
        if (ena) begin
            if(wea) 
                mem[addra] <= dina;
        end
    end






endmodule //dpram

FIFO/async_fifo/code/async_fifo.v
module async_fifo #(
    parameter DATESIZE  = 8,
    parameter ADDRSIZE  = 4,
    parameter ALMOST    = 3
) 
(
    input [DATESIZE-1:0] wdata,
    input winc, wclk, w_rstn,
    input rinc, rclk, r_rstn,
    output wire [DATESIZE-1:0] rdata,
    output reg wfull,
    output reg rempty,
    output reg almost_full,
    output reg almost_empty
);
    parameter DEPTH = 1<<ADDRSIZE;
    wire [ADDRSIZE-1 : 0] waddr,raddr;  
    reg  [ADDRSIZE : 0] wptr,rptr;
    
    //read pointer to write clk sync
    reg [ADDRSIZE:0] wq1_rptr,wq2_rptr;
    always @(posedge wclk or negedge w_rstn) begin
        if (!w_rstn) begin
            {wq2_rptr,wq1_rptr} <= 0 ;
        end else begin
            {wq2_rptr,wq1_rptr} <= {wq1_rptr,rptr};
        end
    end

    // write pointer to read clk domain

    reg [ADDRSIZE:0] wq1_wptr,wq2_wptr;
    always @(posedge rclk or negedge r_rstn) begin
        if (!r_rstn) begin
            {wq2_wptr,wq1_wptr} <= 0 ;
        end else begin
            {wq2_wptr,wq1_wptr} <= {wq1_wptr,wptr};
        end
    end


    // full and empty logic
    reg [ADDRSIZE:0] wbin;
    wire [ADDRSIZE:0] wbin_next,wptr_next;
    wire mem_wr;
    assign mem_wr = winc & (!wfull);
    assign waddr = wbin[ADDRSIZE-1:0];
    assign wbin_next = wbin+mem_wr;
    //bin to gray code
    assign wptr_next = (wbin_next>>1) ^ wbin_next;
    //寄存器输出
    always @(posedge wclk or negedge w_rstn ) begin
        if (!w_rstn) begin
            {wptr,wbin} <= 0;
        end else begin
            {wptr,wbin} <= {wptr_next,wbin_next};
        end       
    end

    // full logic  MSB 不同 LSB相同
    //同步过来的读信号为wq2_rptr(gray code),wq2_rptr与下一个wptr的值进行比较
    //因为wq2_rptr是即将要读的，所以是比较下一个wptr，因为这拍完成之后，才符合full
    //例如wq2_rptr=0 此时wptr=7，
    //那么此时如果写数据有效(winc有效)的话，此时7这拍肯定写了，下一拍wptr就是8也就是满，
    //那么此时如果写数据无效(！winc有效)的话，此时7这拍肯定没写（将写），下一拍wptr还是7，也不会满
    //所以提前一拍判断是不是写满
    wire wfull_val;
    assign wfull_val = (wptr_next == {~wq2_rptr[ADDRSIZE:ADDRSIZE-1],wq2_rptr[ADDRSIZE-2:0]} );
    always @(posedge wclk or negedge w_rstn ) begin
        if (!w_rstn) begin
            wfull <= 0;
        end else begin
            wfull  <= wfull_val;
        end
    end

//empty 同理
    reg [ADDRSIZE:0] rbin;
    wire [ADDRSIZE:0] rptr_next, rbin_next;
    always @(posedge rclk or negedge r_rstn)
        if (!r_rstn) begin
            {rbin, rptr} <= 0;
        end
        else {rbin, rptr} <= {rbin_next, rptr_next};
    wire mem_rd;
    assign mem_rd = rinc & (~rempty);
    assign raddr = rbin[ADDRSIZE-1:0];
    assign rbin_next = rbin + mem_rd;
    assign rptr_next = (rbin_next>>1) ^ rbin_next;
    //empty logic
    assign rempty_val = (rptr_next == wq2_wptr);

    always @(posedge rclk or negedge r_rstn) begin
        if (!r_rstn) rempty <= 1'b1;
        else rempty <= rempty_val ;
    end

    //almost full and empty logic
    //需要将同步过来的格雷码转换成二进制去判断将空将满
    //gray to bin
    wire [ADDRSIZE:0] wq2_rptr_bin,wq2_wptr_bin;
    assign wq2_rptr_bin[ADDRSIZE] = wq2_rptr[ADDRSIZE];
    assign wq2_wptr_bin [ADDRSIZE] = wq2_wptr[ADDRSIZE];
    genvar i;
    generate
        for ( i=ADDRSIZE-1 ; i>= 0 ; i=i-1 ) begin
            assign wq2_rptr_bin[i] = wq2_rptr[i] ^ wq2_rptr_bin[i+1];
            assign wq2_wptr_bin[i] = wq2_wptr[i] ^ wq2_wptr_bin[i+1];
        end
    endgenerate

    //almost empty and full
    wire almost_empty_val,almost_full_val;
    //empty
    wire [ADDRSIZE:0] wgap;
    assign wgap = wq2_wptr_bin-rbin;
    assign almost_empty_val = (wgap <= ALMOST);
    always @(posedge rclk or negedge r_rstn) begin
        if (!r_rstn) begin
            almost_empty <= 1'b1;
        end else begin
            almost_empty <= almost_empty_val;
        end
    end


    //full
    wire [ADDRSIZE:0] rcap;
    assign rcap = (wq2_rptr_bin[ADDRSIZE] != wbin[ADDRSIZE]) ? 
                 (wq2_rptr_bin[ADDRSIZE-1:0] - wbin[ADDRSIZE-1:0]) : (DEPTH-(wbin - wq2_rptr_bin)) ;
    assign almost_full_val = (rcap <= ALMOST);
    always @(posedge wclk or negedge w_rstn) begin
        if (!w_rstn) 
            almost_full <= 1'b0;
        else 
            almost_full <= almost_full_val;       
    end     
    dpram #(.ADDRSIZE(ADDRSIZE),.DATESIZE(DATESIZE)) u_dpram(
        .clkb(rclk),
        .enb(mem_rd),
        .addrb(raddr),
        .doutb(rdata),

        .clka(wclk),
        .ena(mem_wr),
        .wea(mem_wr),
        .dina(wdata),
        .addra(waddr)

    );
    
endmodule //async_fifo

FIFO/async_fifo/code/async_fifo_tb.v
`timescale 1ns/1ps
module async_fifo_tb();

    parameter DATESIZE = 8;
    parameter ADDRSIZE = 3;
    parameter ALMOST = 2; 
    reg [DATESIZE-1:0]wdata;
    reg w_rstn;
    reg winc;
    reg rinc;
    reg wclk;
    reg rclk;
    reg r_rstn;
    wire [DATESIZE-1:0]rdata;
    wire wfull;
    wire rempty;
    wire almost_empty;
    wire almost_full;

    reg [3:0]a;
    reg [3:0]b;
    reg [4:0]c;
    reg x;
    initial begin
        $dumpfile("test.vcd");
        $dumpvars;
        for (i=0; i < 8; i = i + 1) begin
        $dumpvars(0, u_async_fifo.u_dpram.mem[i]);
    end
        wdata = 0;
        w_rstn = 0;
        rinc = 0;
        rclk = 0;
        r_rstn = 0;
        wclk = 0;
        winc = 0;
    

        #2;w_rstn = 0; r_rstn = 0;
        #4;w_rstn = 1; r_rstn = 1;

        #6;  winc = 1;
        #35; rinc = 1;
        #10; winc = 0;
        #60; rinc = 0;
        #5;  rinc = 1; winc = 1;
      
        #100;
        $finish();

    end
integer i;
    initial begin
        wait(winc==1);
        //#11;       
        for(i=0;i<=100;i=i+1) begin
            wdata = i;
            @(negedge wclk);
        end 
    end
 
    always #1   wclk = ~wclk;
    always #4   rclk = ~rclk;


    async_fifo #(
    .DATESIZE                       ( DATESIZE     ),
    .ADDRSIZE                       ( ADDRSIZE     ) )
 u_async_fifo(
    .wdata                          ( wdata ),
    .winc                           ( winc  ),
    .wclk                           ( wclk  ),
    .w_rstn                         ( w_rstn),
    .rinc                           ( rinc  ),
    .rclk                           ( rclk  ),
    .r_rstn                         ( r_rstn),
    .rdata                          ( rdata ),
    .rempty                         (rempty),
    .wfull                           (wfull),

    .almost_empty                   (almost_empty),
    .almost_full                     (almost_full)
    
);


endmodule

FIFO/async_fifo/modelsim/sync_fifo_tb.vcd
$date
	Sat Aug 13 15:03:38 2022
$end
$version
	QuestaSim Version 10.6c
$end
$timescale
	1ps
$end

$scope module async_fifo_tb $end
$var parameter 32 ! DATESIZE $end
$var parameter 32 " ADDRSIZE $end
$var parameter 32 # ALMOST $end
$var reg 8 $ wdata [7:0] $end
$var reg 1 % w_rstn $end
$var reg 1 & winc $end
$var reg 1 ' rinc $end
$var reg 1 ( wclk $end
$var reg 1 ) rclk $end
$var reg 1 * r_rstn $end
$var wire 1 + rdata [7] $end
$var wire 1 , rdata [6] $end
$var wire 1 - rdata [5] $end
$var wire 1 . rdata [4] $end
$var wire 1 / rdata [3] $end
$var wire 1 0 rdata [2] $end
$var wire 1 1 rdata [1] $end
$var wire 1 2 rdata [0] $end
$var wire 1 3 wfull $end
$var wire 1 4 rempty $end
$var wire 1 5 almost_empty $end
$var wire 1 6 almost_full $end
$var reg 4 7 a [3:0] $end
$var reg 4 8 b [3:0] $end
$var reg 5 9 c [4:0] $end
$var reg 1 : x $end
$var integer 32 ; i $end

$scope module u_async_fifo $end
$var parameter 32 < DATESIZE $end
$var parameter 32 = ADDRSIZE $end
$var parameter 32 > ALMOST $end
$var parameter 32 ? DEPTH $end
$var wire 1 @ wdata [7] $end
$var wire 1 A wdata [6] $end
$var wire 1 B wdata [5] $end
$var wire 1 C wdata [4] $end
$var wire 1 D wdata [3] $end
$var wire 1 E wdata [2] $end
$var wire 1 F wdata [1] $end
$var wire 1 G wdata [0] $end
$var wire 1 H winc $end
$var wire 1 I wclk $end
$var wire 1 J w_rstn $end
$var wire 1 K rinc $end
$var wire 1 L rclk $end
$var wire 1 M r_rstn $end
$var wire 1 + rdata [7] $end
$var wire 1 , rdata [6] $end
$var wire 1 - rdata [5] $end
$var wire 1 . rdata [4] $end
$var wire 1 / rdata [3] $end
$var wire 1 0 rdata [2] $end
$var wire 1 1 rdata [1] $end
$var wire 1 2 rdata [0] $end
$var reg 1 N wfull $end
$var reg 1 O rempty $end
$var reg 1 P almost_full $end
$var reg 1 Q almost_empty $end
$var wire 1 R waddr [2] $end
$var wire 1 S waddr [1] $end
$var wire 1 T waddr [0] $end
$var wire 1 U raddr [2] $end
$var wire 1 V raddr [1] $end
$var wire 1 W raddr [0] $end
$var reg 4 X wptr [3:0] $end
$var reg 4 Y rptr [3:0] $end
$var reg 4 Z wq1_rptr [3:0] $end
$var reg 4 [ wq2_rptr [3:0] $end
$var reg 4 \ wq1_wptr [3:0] $end
$var reg 4 ] wq2_wptr [3:0] $end
$var reg 4 ^ wbin [3:0] $end
$var wire 1 _ wbin_next [3] $end
$var wire 1 ` wbin_next [2] $end
$var wire 1 a wbin_next [1] $end
$var wire 1 b wbin_next [0] $end
$var wire 1 c wptr_next [3] $end
$var wire 1 d wptr_next [2] $end
$var wire 1 e wptr_next [1] $end
$var wire 1 f wptr_next [0] $end
$var wire 1 g mem_wr $end
$var wire 1 h wfull_val $end
$var reg 4 i rbin [3:0] $end
$var wire 1 j rptr_next [3] $end
$var wire 1 k rptr_next [2] $end
$var wire 1 l rptr_next [1] $end
$var wire 1 m rptr_next [0] $end
$var wire 1 n rbin_next [3] $end
$var wire 1 o rbin_next [2] $end
$var wire 1 p rbin_next [1] $end
$var wire 1 q rbin_next [0] $end
$var wire 1 r mem_rd $end
$var wire 1 s rempty_val $end
$var wire 1 t wq2_rptr_bin [3] $end
$var wire 1 u wq2_rptr_bin [2] $end
$var wire 1 v wq2_rptr_bin [1] $end
$var wire 1 w wq2_rptr_bin [0] $end
$var wire 1 x wq2_wptr_bin [3] $end
$var wire 1 y wq2_wptr_bin [2] $end
$var wire 1 z wq2_wptr_bin [1] $end
$var wire 1 { wq2_wptr_bin [0] $end
$var wire 1 | almost_empty_val $end
$var wire 1 } almost_full_val $end
$var wire 1 ~ wgap [3] $end
$var wire 1 !! wgap [2] $end
$var wire 1 "! wgap [1] $end
$var wire 1 #! wgap [0] $end
$var wire 1 $! rcap [3] $end
$var wire 1 %! rcap [2] $end
$var wire 1 &! rcap [1] $end
$var wire 1 '! rcap [0] $end

$scope begin genblk1[0] $end
$var parameter 32 (! i $end
$upscope $end

$scope begin genblk1[1] $end
$var parameter 32 )! i $end
$upscope $end

$scope begin genblk1[2] $end
$var parameter 32 *! i $end
$upscope $end

$scope module u_dpram $end
$var parameter 32 +! DATESIZE $end
$var parameter 32 ,! ADDRSIZE $end
$var parameter 32 -! DEPTH $end
$var wire 1 I clka $end
$var wire 1 g ena $end
$var wire 1 g wea $end
$var wire 1 @ dina [7] $end
$var wire 1 A dina [6] $end
$var wire 1 B dina [5] $end
$var wire 1 C dina [4] $end
$var wire 1 D dina [3] $end
$var wire 1 E dina [2] $end
$var wire 1 F dina [1] $end
$var wire 1 G dina [0] $end
$var wire 1 R addra [2] $end
$var wire 1 S addra [1] $end
$var wire 1 T addra [0] $end
$var wire 1 L clkb $end
$var wire 1 r enb $end
$var wire 1 U addrb [2] $end
$var wire 1 V addrb [1] $end
$var wire 1 W addrb [0] $end
$var reg 8 .! doutb [7:0] $end
$upscope $end
$upscope $end
$upscope $end
$enddefinitions $end
#0
$dumpvars
b0 $
0%
0&
0'
0(
0)
0*
bx 7
bx 8
bx 9
x:
0N
1O
0P
1Q
b0 X
b0 Y
b0 Z
b0 [
b0 \
b0 ]
b0 ^
b0 i
bx .!
b1000 !
b11 "
b10 #
b1000 <
b11 =
b11 >
b1000 ?
b1000 +!
b11 ,!
b1000 -!
b10 *!
b1 )!
b0 (!
bx ;
x2
x1
x0
x/
x.
x-
x,
x+
03
14
15
06
0T
0S
0R
0W
0V
0U
0b
0a
0`
0_
0f
0e
0d
0c
0g
0h
0m
0l
0k
0j
0q
0p
0o
0n
0r
1s
0w
0v
0u
0t
0{
0z
0y
0x
1|
0}
0#!
0"!
0!!
0~
0'!
0&!
0%!
1$!
0M
0L
0K
0J
0I
0H
0G
0F
0E
0D
0C
0B
0A
0@
$end
#1000
1(
1I
#2000
0(
0I
#3000
1(
1I
#4000
1)
0(
1L
0I
#5000
1(
1I
#6000
1%
1*
0(
1J
1M
0I
#7000
1(
1I
#8000
0)
0(
0L
0I
#9000
1(
1I
#10000
0(
0I
#11000
1&
1(
1H
1g
1b
1f
1I
b0 ;
b1 ^
b1 X
1T
0b
1a
1'!
1&!
1%!
0$!
1e
#12000
1)
0(
1L
0I
b1 ;
b1 $
1G
b1 \
#13000
1(
1I
b10 ^
b11 X
0T
1S
1b
0'!
0f
#14000
0(
0I
b10 ;
b10 $
0G
1F
#15000
1(
1I
b11 ^
b10 X
1T
0b
0a
1`
1'!
0&!
1d
#16000
0)
0(
0L
0I
b11 ;
b11 $
1G
#17000
1(
1I
b100 ^
b110 X
0T
0S
1R
1b
0'!
1f
#18000
0(
0I
b100 ;
b100 $
0G
0F
1E
#19000
1(
1I
b101 ^
b111 X
1T
0b
1a
1'!
1&!
0%!
0e
1}
#20000
1)
0(
1L
0I
b101 ;
b101 $
1G
b111 \
b1 ]
1{
0s
1#!
#21000
1(
1I
b110 ^
b101 X
1P
0T
1S
1b
0'!
16
0f
#22000
0(
0I
b110 ;
b110 $
0G
1F
#23000
1(
1I
b111 ^
b100 X
1T
0b
0a
0`
1_
1'!
0&!
1c
1h
#24000
0)
0(
0L
0I
b111 ;
b111 $
1G
#25000
1(
1I
b1000 ^
b1100 X
1N
0g
0T
0S
0R
0'!
13
#26000
0(
0I
b1000 ;
b1000 $
0G
0F
0E
1D
#27000
1(
1I
#28000
1)
0(
1L
0I
b1001 ;
b1001 $
1G
b1100 \
b111 ]
0O
1z
1y
04
1"!
1!!
0{
0z
0|
0#!
0"!
1{
1#!
#29000
1(
1I
#30000
0(
0I
b1010 ;
b1010 $
0G
1F
#31000
1(
1I
#32000
0)
0(
0L
0I
b1011 ;
b1011 $
1G
#33000
1(
1I
#34000
0(
0I
b1100 ;
b1100 $
0G
0F
1E
#35000
1(
1I
#36000
1)
0(
1L
0I
b1101 ;
b1101 $
1G
b1100 ]
0Q
0{
1z
1x
05
0#!
1"!
1~
1{
0y
1#!
0!!
0z
0"!
0{
0#!
#37000
1(
1I
#38000
0(
0I
b1110 ;
b1110 $
0G
1F
#39000
1(
1I
#40000
0)
0(
0L
0I
b1111 ;
b1111 $
1G
#41000
1(
1I
#42000
0(
0I
b10000 ;
b10000 $
0G
0F
0E
0D
1C
#43000
1(
1I
#44000
1)
0(
1L
0I
b10001 ;
b10001 $
1G
#45000
1(
1I
#46000
1'
0(
1K
1r
1q
1m
0I
b10010 ;
b10010 $
0G
1F
#47000
1(
1I
#48000
0)
0(
0L
0I
b10011 ;
b10011 $
1G
#49000
1(
1I
#50000
0(
0I
b10100 ;
b10100 $
0G
0F
1E
#51000
1(
1I
#52000
1)
0(
1L
0I
b10101 ;
b10101 $
1G
b1 Y
b1 i
b0 .!
02
01
00
0/
0.
0-
0,
0+
1W
0q
1p
1#!
1"!
1!!
0~
1l
#53000
1(
1I
b1 Z
#54000
0(
0I
b10110 ;
b10110 $
0G
1F
#55000
1(
1I
b1 [
1w
0h
1'!
#56000
0&
0)
0(
0H
0L
0I
b10111 ;
b10111 $
1G
#57000
1(
1I
0N
03
#58000
0(
0I
b11000 ;
b11000 $
0G
0F
0E
1D
#59000
1(
1I
#60000
1)
0(
1L
0I
b11001 ;
b11001 $
1G
b11 Y
b10 i
b1 .!
12
0W
1V
1q
0#!
0m
#61000
1(
1I
b11 Z
#62000
0(
0I
b11010 ;
b11010 $
0G
1F
#63000
1(
1I
b11 [
1v
1&!
0w
0'!
#64000
0)
0(
0L
0I
b11011 ;
b11011 $
1G
#65000
1(
1I
#66000
0(
0I
b11100 ;
b11100 $
0G
0F
1E
#67000
1(
1I
#68000
1)
0(
1L
0I
b11101 ;
b11101 $
1G
b10 Y
b11 i
b10 .!
02
11
1W
0q
0p
1o
1#!
0"!
1k
#69000
1(
1I
b10 Z
#70000
0(
0I
b11110 ;
b11110 $
0G
1F
#71000
1(
1I
b10 [
1w
1'!
#72000
0)
0(
0L
0I
b11111 ;
b11111 $
1G
#73000
1(
1I
#74000
0(
0I
b100000 ;
b100000 $
0G
0F
0E
0D
0C
1B
#75000
1(
1I
#76000
1)
0(
1L
0I
b100001 ;
b100001 $
1G
b110 Y
b100 i
b11 .!
12
0W
0V
1U
1q
0#!
1m
#77000
1(
1I
b110 Z
#78000
0(
0I
b100010 ;
b100010 $
0G
1F
#79000
1(
1I
b110 [
1u
1%!
0v
0}
0&!
0w
0'!
#80000
0)
0(
0L
0I
b100011 ;
b100011 $
1G
#81000
1(
1I
0P
06
#82000
0(
0I
b100100 ;
b100100 $
0G
0F
1E
#83000
1(
1I
#84000
1)
0(
1L
0I
b100101 ;
b100101 $
1G
b111 Y
b101 i
b100 .!
02
01
10
1W
0q
1p
1#!
1"!
0!!
0l
1|
#85000
1(
1I
b111 Z
#86000
0(
0I
b100110 ;
b100110 $
0G
1F
#87000
1(
1I
b111 [
1w
1'!
#88000
0)
0(
0L
0I
b100111 ;
b100111 $
1G
#89000
1(
1I
#90000
0(
0I
b101000 ;
b101000 $
0G
0F
0E
1D
#91000
1(
1I
#92000
1)
0(
1L
0I
b101001 ;
b101001 $
1G
b101 Y
b110 i
1Q
b101 .!
15
12
0W
1V
1q
0#!
0m
#93000
1(
1I
b101 Z
#94000
0(
0I
b101010 ;
b101010 $
0G
1F
#95000
1(
1I
b101 [
1v
1&!
0w
0'!
#96000
0)
0(
0L
0I
b101011 ;
b101011 $
1G
#97000
1(
1I
#98000
0(
0I
b101100 ;
b101100 $
0G
0F
1E
#99000
1(
1I
#100000
1)
0(
1L
0I
b101101 ;
b101101 $
1G
b100 Y
b111 i
b110 .!
02
11
1W
0q
0p
0o
1n
1#!
0"!
1j
1s
#101000
1(
1I
b100 Z
#102000
0(
0I
b101110 ;
b101110 $
0G
1F
#103000
1(
1I
b100 [
1w
1'!
#104000
0)
0(
0L
0I
b101111 ;
b101111 $
1G
#105000
1(
1I
#106000
0(
0I
b110000 ;
b110000 $
0G
0F
0E
0D
1C
#107000
1(
1I
#108000
1)
0(
1L
0I
b110001 ;
b110001 $
1G
b1100 Y
b1000 i
1O
b111 .!
0r
14
12
0W
0V
0U
0#!
#109000
1(
1I
b1100 Z
#110000
0(
0I
b110010 ;
b110010 $
0G
1F
#111000
1(
1I
b1100 [
1t
1$!
0u
0%!
0v
0&!
0w
0'!
#112000
0)
0(
0L
0I
b110011 ;
b110011 $
1G
#113000
1(
1I
#114000
0(
0I
b110100 ;
b110100 $
0G
0F
1E
#115000
1(
1I
#116000
0'
1)
0(
0K
1L
0I
b110101 ;
b110101 $
1G
#117000
1(
1I
#118000
0(
0I
b110110 ;
b110110 $
0G
1F
#119000
1(
1I
#120000
0)
0(
0L
0I
b110111 ;
b110111 $
1G
#121000
1'
1&
1(
1K
1H
1g
1b
1f
1I
b1001 ^
b1101 X
1T
0b
1a
1'!
1&!
1%!
0$!
1e
#122000
0(
0I
b111000 ;
b111000 $
0G
0F
0E
1D
#123000
1(
1I
b1010 ^
b1111 X
0T
1S
1b
0'!
0f
#124000
1)
0(
1L
0I
b111001 ;
b111001 $
1G
b1111 \
#125000
1(
1I
b1011 ^
b1110 X
1T
0b
0a
1`
1'!
0&!
0d
#126000
0(
0I
b111010 ;
b111010 $
0G
1F
#127000
1(
1I
b1100 ^
b1010 X
0T
0S
1R
1b
0'!
1f
#128000
0)
0(
0L
0I
b111011 ;
b111011 $
1G
#129000
1(
1I
b1101 ^
b1011 X
1T
0b
1a
1'!
1&!
0%!
0e
1}
#130000
0(
0I
b111100 ;
b111100 $
0G
0F
1E
#131000
1(
1I
b1110 ^
b1001 X
1P
0T
1S
1b
0'!
16
0f
#132000
1)
0(
1L
0I
b111101 ;
b111101 $
1G
b1001 \
b1111 ]
1{
1z
0s
1#!
1"!
0{
0#!
#133000
1(
1I
b1111 ^
b1000 X
1T
0b
0a
0`
0_
1'!
0&!
0c
1h
#134000
0(
0I
b111110 ;
b111110 $
0G
1F
#135000
1(
1I
b0 ^
b0 X
1N
0g
0T
0S
0R
0'!
13
#136000
0)
0(
0L
0I
b111111 ;
b111111 $
1G
#137000
1(
1I
#138000
0(
0I
b1000000 ;
b1000000 $
0G
0F
0E
0D
0C
0B
1A
#139000
1(
1I
#140000
1)
0(
1L
0I
b1000001 ;
b1000001 $
1G
b0 \
b1001 ]
0O
1r
0z
1y
04
1q
1{
1z
1m
0"!
1!!
1#!
1"!
0{
0|
0#!
#141000
1(
1I
#142000
0(
0I
b1000010 ;
b1000010 $
0G
1F
#143000
1(
1I
#144000
0)
0(
0L
0I
b1000011 ;
b1000011 $
1G
#145000
1(
1I
#146000
0(
0I
b1000100 ;
b1000100 $
0G
0F
1E
#147000
1(
1I
#148000
1)
0(
1L
0I
b1000101 ;
b1000101 $
1G
b0 ]
b1101 Y
b1001 i
0Q
b110111 .!
1{
0x
05
1.
1-
1W
0q
1p
1#!
0"!
0y
1l
0#!
1"!
1~
0!!
0z
0"!
0{
1#!
1"!
1!!
0~
#149000
1(
1I
b1101 Z
#150000
0(
0I
b1000110 ;
b1000110 $
0G
1F
#151000
1(
1I
b1101 [
1w
0h
1'!
#152000
0)
0(
0L
0I
b1000111 ;
b1000111 $
1G
#153000
1(
1I
0N
1g
03
1b
1f
1h
#154000
0(
0I
b1001000 ;
b1001000 $
0G
0F
0E
1D
#155000
1(
1I
b1 ^
b1 X
1N
0g
1T
0'!
13
#156000
1)
0(
1L
0I
b1001001 ;
b1001001 $
1G
b1 \
b1111 Y
b1010 i
b111000 .!
02
01
00
1/
0W
1V
1q
0#!
0m
#157000
1(
1I
b1111 Z
#158000
0(
0I
b1001010 ;
b1001010 $
0G
1F
#159000
1(
1I
b1111 [
1v
0h
1&!
0w
1'!
0&!
#160000
0)
0(
0L
0I
b1001011 ;
b1001011 $
1G
#161000
1(
1I
0N
1g
03
0b
1a
1e
1h
#162000
0(
0I
b1001100 ;
b1001100 $
0G
0F
1E
#163000
1(
1I
b10 ^
b11 X
1N
0g
0T
1S
0'!
13
#164000
1)
0(
1L
0I
b1001101 ;
b1001101 $
1G
b11 \
b1 ]
b1110 Y
b1011 i
b111001 .!
1{
12
1W
0q
0p
1o
1#!
0"!
0k
0#!
1"!
#165000
1(
1I
b1110 Z
#166000
0(
0I
b1001110 ;
b1001110 $
0G
1F
#167000
1(
1I
b1110 [
1w
0h
1'!
#168000
0)
0(
0L
0I
b1001111 ;
b1001111 $
1G
#169000
1(
1I
0N
1g
03
1b
0f
1h
#170000
0(
0I
b1010000 ;
b1010000 $
0G
0F
0E
0D
1C
#171000
1(
1I
b11 ^
b10 X
1N
0g
1T
0'!
13
#172000
1)
0(
1L
0I
b1010001 ;
b1010001 $
1G
b10 \
b11 ]
b1010 Y
b1100 i
b111010 .!
1z
02
11
0W
0V
1U
1q
1#!
0"!
0{
1m
1"!
0#!
#173000
1(
1I
b1010 Z
#174000
0(
0I
b1010010 ;
b1010010 $
0G
1F
#175000
1(
1I
b1010 [
1u
0h
1%!
0v
0}
1&!
0%!
0w
1}
1'!
0&!
#176000
0)
0(
0L
0I
b1010011 ;
b1010011 $
1G
#177000
1(
1I
0N
1g
03
0b
0a
1`
1d
1h
#178000
0(
0I
b1010100 ;
b1010100 $
0G
0F
1E
#179000
1(
1I
b100 ^
b110 X
1N
0g
0T
0S
1R
0'!
13
#180000
1)
0(
1L
0I
b1010101 ;
b1010101 $
1G
b110 \
b10 ]
b1011 Y
b1101 i
b111011 .!
1{
12
1W
0q
1p
1#!
0"!
0l
0#!
1"!
#181000
1(
1I
b1011 Z
#182000
0(
0I
b1010110 ;
b1010110 $
0G
1F
#183000
1(
1I
b1011 [
1w
0h
1'!
#184000
0)
0(
0L
0I
b1010111 ;
b1010111 $
1G
#185000
1(
1I
0N
1g
03
1b
1f
1h
#186000
0(
0I
b1011000 ;
b1011000 $
0G
0F
0E
1D
#187000
1(
1I
b101 ^
b111 X
1N
0g
1T
0'!
13
#188000
1)
0(
1L
0I
b1011001 ;
b1011001 $
1G
b111 \
b110 ]
b1001 Y
b1110 i
b111100 .!
1y
02
01
10
0W
1V
1q
1#!
0"!
0z
0m
0!!
1~
1"!
1!!
0~
0{
0#!
#189000
1(
1I
b1001 Z
#190000
0(
0I
b1011010 ;
b1011010 $
0G
1F
#191000
1(
1I
b1001 [
1v
0h
1&!
0w
1'!
0&!
#192000
0)
0(
0L
0I
b1011011 ;
b1011011 $
1G
#193000
1(
1I
0N
1g
03
0b
1a
0e
1h
#194000
0(
0I
b1011100 ;
b1011100 $
0G
0F
1E
#195000
1(
1I
b110 ^
b101 X
1N
0g
0T
1S
0'!
13
#196000
1)
0(
1L
0I
b1011101 ;
b1011101 $
1G
b101 \
b111 ]
b1000 Y
b1111 i
b111101 .!
1{
12
1W
0q
0p
0o
0n
1#!
0"!
0j
0#!
1"!
#197000
1(
1I
b1000 Z
#198000
0(
0I
b1011110 ;
b1011110 $
0G
1F
#199000
1(
1I
b1000 [
1w
0h
1'!
#200000
0)
0(
0L
0I
b1011111 ;
b1011111 $
1G
#201000
1(
1I
0N
1g
03
1b
0f
1h
#202000
0(
0I
b1100000 ;
b1100000 $
0G
0F
0E
0D
0C
1B
#203000
1(
1I
b111 ^
b100 X
1N
0g
1T
0'!
13
#204000
1)
0(
1L
0I
b1100001 ;
b1100001 $
1G
b100 \
b101 ]
b0 Y
b0 i
b111110 .!
1z
02
11
0W
0V
0U
1q
1#!
0"!
0{
1m
1"!
0#!
#205000
1(
1I
b0 Z
#206000
0(
0I
b1100010 ;
b1100010 $
0G
1F
#207000
1(
1I
b0 [
0t
0h
1$!
0u
0}
1%!
0$!
0v
1&!
0%!
0w
1}
1'!
0&!
#208000
0)
0(
0L
0I
b1100011 ;
b1100011 $
1G
#209000
1(
1I
0N
1g
03
0b
0a
0`
1_
1c
1h
#210000
0(
0I
b1100100 ;
b1100100 $
0G
0F
1E
#211000
1(
1I
b1000 ^
b1100 X
1N
0g
0T
0S
0R
0'!
13
#212000
1)
0(
1L
0I
b1100101 ;
b1100 \
b100 ]
b1 Y
b1 i
b1001000 .!
1{
01
00
0.
0-
1,
1W
0q
1p
1#!
0"!
1l
0#!
1"!
#213000
1(
1I
b1 Z
#214000
0(
0I
#215000
1(
1I
b1 [
1w
0h
1'!
#216000
0)
0(
0L
0I
#217000
1(
1I
0N
1g
03
1b
1f
1h
#218000
0(
0I
#219000
1(
1I
b1001 ^
b1101 X
1N
0g
1T
0'!
13
#220000
1)
0(
1L
0I
b1101 \
b1100 ]
b11 Y
b10 i
b1001100 .!
1x
10
0W
1V
1q
1#!
0"!
0y
0m
1~
0!!
0z
1"!
1!!
0~
0{
0#!
