mcp/code/sync2.v
module sync2 (
    input clk,
    input rstn,
    input din,
    
    output  dout
);
   

    reg sync0,sync1 ;

    always @(posedge clk or negedge rstn) begin
        if(~rstn)
            sync0 <= 1'b0;
        else 
            sync0 <= din;    
    end

    always @(posedge clk or negedge rstn) begin
        if (~rstn) begin
            sync1 <= 1'b0;
        end
        else
            sync1 <= sync0 ;     
    end

    assign  dout = sync1;

endmodule

mcp/code/mcp.v
module mcp #(
    parameter DWIDTH = 8
)
 (
    input clk_a,
    input [DWIDTH-1:0]adatain,
    input asend,
    input rstn_a,
    output aready,

    input clk_b,
    input rstn_b,
    input bload,
    output bvalid,
    output reg [DWIDTH-1:0] bdata
);

//-----------------clk_a domain-----------------------//
    wire din_cap; // 1 cycle pluse
    reg [DWIDTH-1:0] adata;
    reg a_en;

    assign din_cap = asend & aready;
    always @(posedge clk_a ) begin
        if (din_cap) 
            adata <= adatain;
    end

    //pluse--->level
    always @(posedge clk_a or negedge rstn_a) begin
        if(~rstn_a)
            a_en <= 0;
        else if (din_cap)
            a_en <= ~a_en;    
    end


    //level --> pluse
    wire b_ack_sync2;
    reg  b_ack_sync3;
    wire a_ack;
    reg   b_ack;

    sync2 b_ack_1 (
        .clk  ( clk_a  ),
        .rstn ( rstn_a ),
        .din  ( b_ack  ),
        .dout ( b_ack_sync2 ) 
    );

    always @(posedge clk_a or negedge rstn_a) begin
        if(~rstn_a) 
            b_ack_sync3 <= 0;
        else 
            b_ack_sync3 <= b_ack_sync2;    
    end

    assign a_ack = b_ack_sync2 ^ b_ack_sync3;

    //FSM
    /*
    a_fsm afsm (
        .clk_a  ( clk_a  ),
        .rstn_a ( rstn_a ),
        .asend  ( asend  ),
        .a_ack  ( a_ack  ),
        .aready ( aready )

    );*/

    reg aready_m;
    always @(posedge clk_a or negedge rstn_a) begin
       if(~rstn_a) 
            aready_m <= 1;
        else if (asend) begin
            aready_m <= 0;
        end  else if (a_ack) begin
            aready_m <= 1;
        end
    end
    assign aready = aready_m;


//-------------------clk_b domain----------------------------//
    wire  a_en_sync2;
    reg   a_en_sync3;
    wire  b_en;
    wire  bload_data;
    

    // level-->pluse
    sync2 a_en_1 (
        .clk(clk_b),
        .rstn(rstn_b),
        .din (a_en),
        .dout(a_en_sync2)
    );
    
    always @(posedge clk_b or negedge rstn_b) begin
        if(~rstn_b)
            a_en_sync3 <= 0;
        else 
            a_en_sync3 <= a_en_sync2;
    end

    assign b_en = a_en_sync2 ^ a_en_sync3; 
//FSM
 /*   b_fsm bfsm (
        .clk_b  (clk_b),
        .rstn_b ( rstn_b),
        .b_en   ( b_en  ),
        .bload  ( bload ),
        .bvalid ( bvalid )
    );  */

    reg bvalid_m ;
    always @(posedge clk_b or negedge rstn_b) begin
        if (~rstn_b)
            bvalid_m <= 0;
        else if (b_en) begin
            bvalid_m <= 1;
        end else if (bload) begin
            bvalid_m <= 0;
        end
    end
    assign bvalid = bvalid_m;


    assign bload_data = bvalid & bload;//pluse

    always @(posedge clk_b ) begin
        if (bload_data)
            bdata <= adata;
    end

    always @(posedge clk_b or negedge rstn_b) begin
        if(~rstn_b)
            b_ack <= 0;
        else if (bload_data)
            b_ack <= ~b_ack;    
    end




endmodule //mcp

mcp/code/mcp_tb.v
module mcp_tb ();
    parameter  DWIDTH = 8;
    reg clk_a;
    reg [DWIDTH-1:0] adatain;
    reg asend;
    reg rstn_a;
    wire aready;

    reg clk_b;
    reg rstn_b;
    reg bload;
    wire bvalid;
    wire  [DWIDTH-1:0] bdata;

    always #1 clk_a = ~clk_a;
    always #4 clk_b = ~clk_b;
    initial begin
        clk_a = 0;
        clk_b = 0;
        asend = 0;
        rstn_a = 0;
        rstn_b = 0;
        adatain = 0;
        bload  = 0;

        #1;rstn_a = 1;rstn_b = 1;
        @(posedge clk_a)#0.1;
        asend = 1;
        @(posedge clk_a)#0.1;
        asend = 0;
        adatain = 8'd1;
        //wait(b_en == 1); bload = 1;
        repeat(4) @(posedge clk_a);
        @(posedge clk_b);
        bload = 1;
        repeat(3) @(posedge clk_b);
        bload = 0;



        //wait(a_ack == 1);
        @(posedge clk_b);
        repeat(2) @(posedge clk_a)#0.1;
        asend   = 1;
        @(posedge clk_a)#0.1;
        adatain = 8'd2;
         asend = 0;
        //wait(b_en == 1); bload = 1;
        repeat(4) @(posedge clk_a);
        bload = 1;
        repeat(3) @(posedge clk_b);
        bload = 0;

        @(posedge clk_b);
        repeat(2) @(posedge clk_a);#0.1
        asend   = 1;
        @(posedge clk_a);#0.1
        adatain = 8'd3;
        asend = 0;
        //wait(b_en == 1); bload = 1;
        repeat(4) @(posedge clk_a);
        bload = 1;
        repeat(3) @(posedge clk_b);
        bload = 0;

        @(posedge clk_b);
        repeat(2) @(posedge clk_a);#0.1
        asend   = 1;
        @(posedge clk_a);#0.1
        adatain = 8'd4;
         asend = 0;
        //wait(b_en == 1); bload = 1;
        repeat(4) @(posedge clk_a);
        bload = 1;
        repeat(3) @(posedge clk_b);
        bload = 0;

        @(posedge clk_b);
        repeat(2) @(posedge clk_a);#0.1
        asend   = 1;
        @(posedge clk_a);#0.1
        adatain = 8'd5;
         asend = 0;
        //wait(b_en == 1); bload = 1;
        repeat(4) @(posedge clk_a);
        bload = 1;
        repeat(3) @(posedge clk_b);
        bload = 0;

        @(posedge clk_b);
        repeat(2) @(posedge clk_a);
        asend   = 1;
        @(posedge clk_a);#0.1
        adatain = 8'd6;
         asend = 0;
        //wait(b_en == 1); bload = 1;
        repeat(4) @(posedge clk_a);
        bload = 1;
        repeat(3) @(posedge clk_b);
        bload = 0;

        @(posedge clk_b);
        repeat(2) @(posedge clk_a);#0.1
        asend   = 1;
        @(posedge clk_a);#0.1
        //adatain = 8'd7;
         asend = 0;
        //wait(b_en == 1); bload = 1;
        repeat(4) @(posedge clk_a);
        bload = 1;
        repeat(3) @(posedge clk_b);
        bload = 0;



        #200
        $finish();

        
    end

    initial begin
		$dumpfile("test.vcd");
        $dumpvars;
	end

    mcp u_mcp (
        .clk_a   (clk_a),
        .adatain (adatain),
        .asend   (asend),
        .rstn_a  (rstn_a),
        .aready  (aready),

        .clk_b   (clk_b),
        .rstn_b  (rstn_b),
        .bload   (bload),
        .bvalid  (bvalid),
        .bdata   (bdata)
    );


endmodule //mcp_tb

mcp/modelsim/mcp_tb.vcd
$date
	Tue Jul 19 22:36:46 2022
$end
$version
	QuestaSim Version 10.6c
$end
$timescale
	1ns
$end

$scope module mcp_tb $end
$var parameter 32 ! DWIDTH $end
$var reg 1 " clk_a $end
$var reg 8 # adatain [7:0] $end
$var reg 1 $ asend $end
$var reg 1 % rstn_a $end
$var wire 1 & aready $end
$var reg 1 ' clk_b $end
$var reg 1 ( rstn_b $end
$var reg 1 ) bload $end
$var wire 1 * bvalid $end
$var wire 1 + bdata [7] $end
$var wire 1 , bdata [6] $end
$var wire 1 - bdata [5] $end
$var wire 1 . bdata [4] $end
$var wire 1 / bdata [3] $end
$var wire 1 0 bdata [2] $end
$var wire 1 1 bdata [1] $end
$var wire 1 2 bdata [0] $end

$scope module u_mcp $end
$var parameter 32 3 DWIDTH $end
$var wire 1 4 clk_a $end
$var wire 1 5 adatain [7] $end
$var wire 1 6 adatain [6] $end
$var wire 1 7 adatain [5] $end
$var wire 1 8 adatain [4] $end
$var wire 1 9 adatain [3] $end
$var wire 1 : adatain [2] $end
$var wire 1 ; adatain [1] $end
$var wire 1 < adatain [0] $end
$var wire 1 = asend $end
$var wire 1 > rstn_a $end
$var wire 1 & aready $end
$var wire 1 ? clk_b $end
$var wire 1 @ rstn_b $end
$var wire 1 A bload $end
$var wire 1 * bvalid $end
$var reg 8 B bdata [7:0] $end
$var wire 1 C din_cap $end
$var reg 8 D adata [7:0] $end
$var reg 1 E a_en $end
$var wire 1 F b_ack_sync2 $end
$var reg 1 G b_ack_sync3 $end
$var wire 1 H a_ack $end
$var reg 1 I b_ack $end
$var reg 1 J aready_m $end
$var wire 1 K a_en_sync2 $end
$var reg 1 L a_en_sync3 $end
$var wire 1 M b_en $end
$var wire 1 N bload_data $end
$var reg 1 O bvalid_m $end

$scope module b_ack_1 $end
$var wire 1 4 clk $end
$var wire 1 > rstn $end
$var wire 1 P din $end
$var wire 1 F dout $end
$var reg 1 Q sync0 $end
$var reg 1 R sync1 $end
$upscope $end

$scope module a_en_1 $end
$var wire 1 ? clk $end
$var wire 1 @ rstn $end
$var wire 1 S din $end
$var wire 1 K dout $end
$var reg 1 T sync0 $end
$var reg 1 U sync1 $end
$upscope $end
$upscope $end
$upscope $end
$enddefinitions $end
#0
$dumpvars
0"
b0 #
0$
0%
0'
0(
0)
bx B
bx D
0E
0G
0I
0Q
0R
1J
0L
0T
0U
0O
b1000 !
b1000 3
1&
0*
x2
x1
x0
x/
x.
x-
x,
x+
0C
0F
0H
0K
0M
0N
0A
0@
0?
0>
0=
0<
0;
0:
09
08
07
06
05
04
0S
0P
$end
#1
1"
1%
1(
14
1>
1@
#2
0"
04
#3
1"
14
1$
1=
1C
#4
1'
0"
1?
04
#5
1"
14
0$
b1 #
0=
1<
0C
b0 D
1E
0J
1S
0&
#6
0"
04
#7
1"
14
#8
0'
0"
0?
04
#9
1"
14
#10
0"
04
#11
1"
14
#12
1'
0"
1?
04
1T
#13
1"
14
#14
0"
04
#15
1"
14
#16
0'
0"
0?
04
#17
1"
14
#18
0"
04
#19
1"
14
#20
1'
0"
1?
04
1)
1A
1U
1K
1M
#21
1"
14
#22
0"
04
#23
1"
14
#24
0'
0"
0?
04
#25
1"
14
#26
0"
04
#27
1"
14
#28
1'
0"
1?
04
1L
1O
0M
1*
1N
#29
1"
14
#30
0"
04
#31
1"
14
#32
0'
0"
0?
04
#33
1"
14
#34
0"
04
#35
1"
14
#36
1'
0"
1?
04
0O
1I
b0 B
0*
1P
02
01
00
0/
0.
0-
0,
0+
0N
#37
1"
14
1Q
#38
0"
04
#39
1"
14
1R
1F
1H
#40
0'
0"
0?
04
#41
1"
14
1G
1J
0H
1&
#42
0"
04
#43
1"
14
#44
1'
0"
1?
04
0)
0A
#45
1"
14
#46
0"
04
#47
1"
14
#48
0'
0"
0?
04
#49
1"
14
#50
0"
04
#51
1"
14
#52
1'
0"
1?
04
#53
1"
14
#54
0"
04
#55
1"
14
1$
1=
1C
#56
0'
0"
0?
04
#57
1"
14
b10 #
0$
0<
1;
0=
0C
b1 D
0E
0J
0S
0&
#58
0"
04
#59
1"
14
#60
1'
0"
1?
04
0T
#61
1"
14
#62
0"
04
#63
1"
14
#64
0'
0"
0?
04
#65
1"
14
1)
1A
#66
0"
04
#67
1"
14
#68
1'
0"
1?
04
0U
0K
1M
#69
1"
14
#70
0"
04
#71
1"
14
#72
0'
0"
0?
04
#73
1"
14
#74
0"
04
#75
1"
14
#76
1'
0"
1?
04
0L
1O
0M
1*
1N
#77
1"
14
#78
0"
04
#79
1"
14
#80
0'
0"
0?
04
#81
1"
14
#82
0"
04
#83
1"
14
#84
1'
0"
1?
04
0)
0A
0N
0O
0I
b1 B
0*
0P
12
#85
1"
14
0Q
#86
0"
04
#87
1"
14
0R
0F
1H
#88
0'
0"
0?
04
#89
1"
14
0G
1J
0H
1&
#90
0"
04
#91
1"
14
#92
1'
0"
1?
04
#93
1"
14
#94
0"
04
#95
1"
14
1$
1=
1C
#96
0'
0"
0?
04
#97
1"
14
b11 #
0$
1<
0=
0C
b10 D
1E
0J
1S
0&
#98
0"
04
#99
1"
14
#100
1'
0"
1?
04
1T
#101
1"
14
#102
0"
04
#103
1"
14
#104
0'
0"
0?
04
#105
1"
14
1)
1A
#106
0"
04
#107
1"
14
#108
1'
0"
1?
04
1U
1K
1M
#109
1"
14
#110
0"
04
#111
1"
14
#112
0'
0"
0?
04
#113
1"
14
#114
0"
04
#115
1"
14
#116
1'
0"
1?
04
1L
1O
0M
1*
1N
#117
1"
14
#118
0"
04
#119
1"
14
#120
0'
0"
0?
04
#121
1"
14
#122
0"
04
#123
1"
14
#124
1'
0"
1?
04
0)
0A
0N
0O
1I
b10 B
0*
1P
02
11
#125
1"
14
1Q
#126
0"
04
#127
1"
14
1R
1F
1H
#128
0'
0"
0?
04
#129
1"
14
1G
1J
0H
1&
#130
0"
04
#131
1"
14
#132
1'
0"
1?
04
#133
1"
14
#134
0"
04
#135
1"
14
1$
1=
1C
#136
0'
0"
0?
04
#137
1"
14
b100 #
0$
0<
0;
1:
0=
0C
b11 D
0E
0J
0S
0&
#138
0"
04
#139
1"
14
#140
1'
0"
1?
04
0T
#141
1"
14
#142
0"
04
#143
1"
14
#144
0'
0"
0?
04
#145
1"
14
1)
1A
#146
0"
04
#147
1"
14
#148
1'
0"
1?
04
0U
0K
1M
#149
1"
14
#150
0"
04
#151
1"
14
#152
0'
0"
0?
04
#153
1"
14
#154
0"
04
#155
1"
14
#156
1'
0"
1?
04
0L
1O
0M
1*
1N
#157
1"
14
#158
0"
04
#159
1"
14
#160
0'
0"
0?
04
#161
1"
14
#162
0"
04
#163
1"
14
#164
1'
0"
1?
04
0)
0A
0N
0O
0I
b11 B
0*
0P
12
#165
1"
14
0Q
#166
0"
04
#167
1"
14
0R
0F
1H
#168
0'
0"
0?
04
#169
1"
14
0G
1J
0H
1&
#170
0"
04
#171
1"
14
#172
1'
0"
1?
04
#173
1"
14
#174
0"
04
#175
1"
14
1$
1=
1C
#176
0'
0"
0?
04
#177
1"
14
b101 #
0$
1<
0=
0C
b100 D
1E
0J
1S
0&
#178
0"
04
#179
1"
14
#180
1'
0"
1?
04
1T
#181
1"
14
#182
0"
04
#183
1"
14
#184
0'
0"
0?
04
#185
1"
14
1)
1A
#186
0"
04
#187
1"
14
#188
1'
0"
1?
04
1U
1K
1M
#189
1"
14
#190
0"
04
#191
1"
14
#192
0'
0"
0?
04
#193
1"
14
#194
0"
04
#195
1"
14
#196
1'
0"
1?
04
1L
1O
0M
1*
1N
#197
1"
14
#198
0"
04
#199
1"
14
#200
0'
0"
0?
04
#201
1"
14
#202
0"
04
#203
1"
14
#204
1'
0"
1?
04
0)
0A
0N
0O
1I
b100 B
0*
1P
02
01
10
#205
1"
14
1Q
#206
0"
04
#207
1"
14
1R
1F
1H
#208
0'
0"
0?
04
#209
1"
14
1G
1J
0H
1&
#210
0"
04
#211
1"
14
#212
1'
0"
1?
04
#213
1"
14
#214
0"
04
#215
1"
14
1$
1=
1C
#216
0'
0"
0?
04
#217
1"
14
b110 #
0$
0<
1;
0=
0C
b101 D
0E
0J
0S
0&
#218
0"
04
#219
1"
14
#220
1'
0"
1?
04
0T
#221
1"
14
#222
0"
04
#223
1"
14
#224
0'
0"
0?
04
#225
1"
14
1)
1A
#226
0"
04
#227
1"
14
#228
1'
0"
1?
04
0U
0K
1M
#229
1"
14
#230
0"
04
#231
1"
14
#232
0'
0"
0?
04
#233
1"
14
#234
0"
04
#235
1"
14
#236
1'
0"
1?
04
0L
1O
0M
1*
1N
#237
1"
14
#238
0"
04
#239
1"
14
#240
0'
0"
0?
04
#241
1"
14
#242
0"
04
#243
1"
14
#244
1'
0"
1?
04
0)
0A
0N
0O
0I
b101 B
0*
0P
12
#245
1"
14
0Q
#246
0"
04
#247
1"
14
0R
0F
1H
#248
0'
0"
0?
04
#249
1"
14
0G
1J
0H
1&
#250
0"
04
#251
1"
14
#252
1'
0"
1?
04
#253
1"
14
#254
0"
04
#255
1"
14
1$
1=
1C
#256
0'
0"
0?
04
#257
1"
14
0$
0=
0C
b110 D
1E
0J
1S
0&
#258
0"
04
#259
1"
14
#260
1'
0"
1?
04
1T
#261
1"
14
#262
0"
04
#263
1"
14
#264
0'
0"
0?
04
#265
1"
14
1)
1A
#266
0"
04
#267
1"
14
#268
1'
0"
1?
04
1U
1K
1M
#269
1"
14
#270
0"
04
#271
1"
14
#272
0'
0"
0?
04
#273
1"
14
#274
0"
04
#275
1"
14
#276
1'
0"
1?
04
1L
1O
0M
1*
1N
#277
1"
14
#278
0"
04
#279
1"
14
#280
0'
0"
0?
04
#281
1"
14
#282
0"
04
#283
1"
14
#284
1'
0"
1?
04
0)
0A
0N
0O
1I
b110 B
0*
1P
02
11
#285
1"
14
1Q
#286
0"
04
#287
1"
14
1R
1F
1H
#288
0'
0"
0?
04
#289
1"
14
1G
1J
0H
1&
