handshake/hs_buf/code/nofsm_ready_hs.v
module nofsm_ready_hs_buf  #(
    parameter DATA_WD = 32
)(
    input                       clk,
    input                       rstn,

    input                       valid_in,
    input  [DATA_WD-1 : 0]      data_in,
    output                      ready_in,

    output                      valid_out,
    output [DATA_WD-1 : 0]      data_out,
    input                       ready_out
    
);

reg                 valid_out_r;//bypaass
reg  [DATA_WD-1:0]  data_out_r;//缓存数据
reg                 ready_out_r;
wire                fire_in;
wire                fire_out;

parameter EMPTY = 2'b0, FULL = 2'b1;
reg        [1:0]    c_state,n_state; 



assign data_out = valid_out_r ? data_out_r : data_in;
assign valid_out = valid_out_r || valid_in;//直通信号(valid) + reg signal (valid_out_r)
assign ready_in = ready_out_r || !valid_out_r; //保证empty(直通)时候 ready_in一直是1


assign fire_in = valid_in && ready_in;
assign fire_out = valid_out && ready_out;

always @(posedge clk or negedge rstn) begin
    if(!rstn) 
        valid_out_r <= 1'b0;
    else begin
        if (fire_in && !fire_out) begin
            valid_out_r <= valid_out;
            data_out_r  <= data_in;
        end else if(!fire_in && fire_out) begin
            valid_out_r <= 1'b0;
        end
    end
            
end



always @(posedge clk or negedge rstn) begin
    if(!rstn)
        ready_out_r <= 1'b0;
    else
        ready_out_r <= ready_out;    
end




endmodule //nofsm_ready_hs

handshake/hs_buf/code/tb_hs_buf.v
module tb_hs_buf ();

localparam HAL_CYCLE = 5;
localparam DATA_WD = 4;

reg clk;
reg rstn;

reg                  valid_in;
reg  [DATA_WD-1 : 0] cnt_in;
reg                  ready_out;

wire [DATA_WD-1 : 0] data_in;
wire                 ready_in;
wire                 fire_in;
wire                 fire_out;
wire                 valid_out;
wire [DATA_WD-1 : 0] data_out;

assign data_in = cnt_in;

assign fire_in = valid_in && ready_in;
assign fire_out = valid_out && ready_out;

initial begin
    $dumpfile("test.vcd");
    $dumpvars;
end

initial begin
    clk = 0;
    forever #5 clk = ~clk;
end

initial begin
    rstn = 0;
    #100 rstn = 1;
    #5000 $finish;
end

nofsm_ready_hs_buf #(
    .DATA_WD(DATA_WD)
) hs_buf_ins(
    .clk(clk),
    .rstn(rstn),
    .valid_in(valid_in),
    .data_in(data_in),
    .ready_in(ready_in),
    .valid_out(valid_out),
    .data_out(data_out),
    .ready_out(ready_out)
);


localparam RANDOM_FIRE = 1'b1;

generate if (RANDOM_FIRE) begin // random fire

    always @(posedge clk or negedge rstn) begin
        if (!rstn) begin
            valid_in <= 1'b0;
            cnt_in <= 'b0;
        end
        else begin
            if (!valid_in) begin
                valid_in <= $random;
            end
            else if (fire_in) begin
                valid_in <= $random;
                cnt_in <= cnt_in + 1'b1;
            end
        end
    end

    always @(posedge clk or negedge rstn) begin
        if (!rstn) begin
            ready_out <= 1'b1;
        end
        else begin
            ready_out <= $random;
        end
    end

end
else begin // fire always

    always @(posedge clk or negedge rstn) begin
        if (!rstn) begin
            valid_in <= 1'b0;
            cnt_in <= 'b0;
        end
        else begin
            valid_in <= 1'b1;
            if (fire_in) begin
                cnt_in <= cnt_in + 1'b1;
            end
        end
    end

    always @(posedge clk or negedge rstn) begin
        if (!rstn) begin
            ready_out <= 1'b1;
        end
        else begin
            ready_out <= 1'b1;
        end
    end

end
endgenerate

endmodule

handshake/hs_buf/sim/test.vcd
$date
	Sun Sep 10 00:49:10 2023
$end
$version
	Icarus Verilog
$end
$timescale
	1s
$end
$scope module tb_hs_buf $end
$var wire 4 ! data_in [3:0] $end
$var wire 1 " fire_in $end
$var wire 1 # fire_out $end
$var wire 1 $ valid_out $end
$var wire 1 % ready_in $end
$var wire 4 & data_out [3:0] $end
$var reg 1 ' clk $end
$var reg 4 ( cnt_in [3:0] $end
$var reg 1 ) ready_out $end
$var reg 1 * rstn $end
$var reg 1 + valid_in $end
$scope begin genblk1 $end
$upscope $end
$scope module hs_buf_ins $end
$var wire 1 ' clk $end
$var wire 4 , data_in [3:0] $end
$var wire 1 - fire_in $end
$var wire 1 . fire_out $end
$var wire 1 % ready_in $end
$var wire 1 ) ready_out $end
$var wire 1 * rstn $end
$var wire 1 + valid_in $end
$var wire 1 $ valid_out $end
$var wire 4 / data_out [3:0] $end
$var reg 4 0 data_out_r [3:0] $end
$var reg 1 1 ready_out_r $end
$var reg 1 2 valid_out_r $end
$upscope $end
$upscope $end
$enddefinitions $end
#0
$dumpvars
02
01
bx 0
b0 /
0.
0-
b0 ,
0+
0*
1)
b0 (
0'
b0 &
1%
0$
0#
0"
b0 !
$end
#5
1'
#10
0'
#15
1'
#20
0'
#25
1'
#30
0'
#35
1'
#40
0'
#45
1'
#50
0'
#55
1'
#60
0'
#65
1'
#70
0'
#75
1'
#80
0'
#85
1'
#90
0'
#95
1'
#100
0'
1*
#105
11
1'
#110
0'
#115
1.
1#
1$
1-
1"
1+
1'
#120
0'
#125
b1 &
b1 /
b1 !
b1 (
b1 ,
1'
#130
0'
#135
0.
0#
b10 &
b10 /
0$
0-
0"
b10 !
b10 (
b10 ,
0+
1'
#140
0'
#145
1.
1#
1$
1-
1"
1+
1'
#150
0'
#155
b11 &
b11 /
0.
0#
b11 !
b11 (
b11 ,
0)
1'
#160
0'
#165
0-
0"
0%
01
b11 0
12
b100 !
b100 (
b100 ,
1'
#170
0'
#175
1.
1#
1)
1'
#180
0'
#185
1-
1"
b100 &
b100 /
1%
0.
0#
11
02
0)
1'
#190
0'
#195
0-
0"
1.
1#
0%
b101 !
b101 (
b101 ,
0+
1)
b100 0
12
01
1'
#200
0'
#205
1-
1"
b101 &
b101 /
1%
11
02
1+
1'
#210
0'
#215
b110 &
b110 /
0.
0#
b110 !
b110 (
b110 ,
0)
1'
#220
0'
#225
0%
0-
0"
01
b110 0
12
b111 !
b111 (
b111 ,
0+
1'
#230
0'
#235
1+
1'
#240
0'
#245
1'
#250
0'
#255
1.
1#
1)
1'
#260
0'
#265
1-
1"
b111 &
b111 /
1%
11
02
1'
#270
0'
#275
b1000 &
b1000 /
b1000 !
b1000 (
b1000 ,
1'
#280
0'
#285
0.
0#
b1001 &
b1001 /
0$
0-
0"
0)
b1001 !
b1001 (
b1001 ,
0+
1'
#290
0'
#295
01
1'
#300
0'
#305
1$
1-
1"
1+
1'
#310
0'
#315
0-
0"
1.
1#
0%
b1010 !
b1010 (
b1010 ,
1)
b1001 0
12
1'
#320
0'
#325
1-
1"
b1010 &
b1010 /
1%
11
02
1'
#330
0'
#335
b1011 &
b1011 /
b1011 !
b1011 (
b1011 ,
1'
#340
0'
#345
0.
0#
b1100 &
b1100 /
0$
0-
0"
0)
b1100 !
b1100 (
b1100 ,
0+
1'
#350
0'
#355
1.
1#
1$
1-
1"
1+
1)
01
1'
#360
0'
#365
0.
0#
b1101 &
b1101 /
11
0)
b1101 !
b1101 (
b1101 ,
1'
#370
0'
#375
0-
0"
0%
b1110 !
b1110 (
b1110 ,
0+
b1101 0
12
01
1'
#380
0'
#385
1'
#390
0'
#395
1.
1#
1)
1'
#400
0'
#405
0.
0#
b1110 &
b1110 /
1%
0$
11
02
1'
#410
0'
#415
1'
#420
0'
#425
0)
1'
#430
0'
#435
01
1'
#440
0'
#445
1.
1#
1$
1-
1"
1)
1+
1'
#450
0'
#455
b1111 &
b1111 /
b1111 !
b1111 (
b1111 ,
11
1'
#460
0'
#465
0.
0#
b0 &
b0 /
0)
b0 !
b0 (
b0 ,
1'
#470
0'
#475
0-
0"
0%
b1 !
b1 (
b1 ,
b0 0
12
01
1'
#480
0'
#485
1.
1#
1)
1'
#490
0'
#495
1-
1"
b1 &
b1 /
1%
02
11
1'
#500
0'
#505
0.
0#
b10 &
b10 /
0$
0-
0"
0)
b10 !
b10 (
b10 ,
0+
1'
#510
0'
#515
1.
1#
1$
1-
1"
1+
1)
01
1'
#520
0'
#525
0.
0#
b11 &
b11 /
0$
0-
0"
11
b11 !
b11 (
b11 ,
0+
1'
#530
0'
#535
1'
#540
0'
#545
1.
1#
1$
1-
1"
1+
1'
#550
0'
#555
0.
0#
b100 &
b100 /
0$
0-
0"
b100 !
b100 (
b100 ,
0+
1'
#560
0'
#565
1.
1#
1$
1-
1"
1+
1'
#570
0'
#575
b101 &
b101 /
0$
0-
0"
0.
0#
b101 !
b101 (
b101 ,
0+
0)
1'
#580
0'
#585
01
1'
#590
0'
#595
1.
1#
1$
1-
1"
1+
1)
1'
#600
0'
#605
0.
0#
b110 &
b110 /
0$
0-
0"
11
0)
b110 !
b110 (
b110 ,
0+
1'
#610
0'
#615
1.
1#
1$
1-
1"
1+
1)
01
1'
#620
0'
#625
b111 &
b111 /
11
b111 !
b111 (
b111 ,
1'
#630
0'
#635
0.
0#
b1000 &
b1000 /
0$
0-
0"
b1000 !
b1000 (
b1000 ,
0+
1'
#640
0'
#645
1.
1#
1$
1-
1"
1+
1'
#650
0'
#655
0.
0#
b1001 &
b1001 /
0$
0-
0"
b1001 !
b1001 (
b1001 ,
0+
1'
#660
0'
#665
0)
1'
#670
0'
#675
01
1'
#680
0'
#685
1'
#690
0'
#695
1.
1#
1$
1-
1"
1+
1)
1'
#700
0'
#705
b1010 &
b1010 /
11
b1010 !
b1010 (
b1010 ,
1'
#710
0'
#715
0.
0#
b1011 &
b1011 /
0$
0-
0"
b1011 !
b1011 (
b1011 ,
0+
1'
#720
0'
#725
1.
1#
1$
1-
1"
1+
1'
#730
0'
#735
b1100 &
b1100 /
0$
0-
0"
0.
0#
b1100 !
b1100 (
b1100 ,
0+
0)
1'
#740
0'
#745
1.
1#
1$
1-
1"
01
1)
1+
1'
#750
0'
#755
b1101 &
b1101 /
0.
0#
b1101 !
b1101 (
b1101 ,
0)
11
1'
#760
0'
#765
0-
0"
0%
1.
1#
01
b1101 0
12
1)
b1110 !
b1110 (
b1110 ,
1'
#770
0'
#775
1-
1"
b1110 &
b1110 /
1%
02
11
1'
#780
0'
#785
0.
0#
b1111 &
b1111 /
0$
0-
0"
0)
b1111 !
b1111 (
b1111 ,
0+
1'
#790
0'
#795
1$
1-
1"
1+
01
1'
#800
0'
#805
0%
0-
0"
b1111 0
12
b0 !
b0 (
b0 ,
0+
1'
#810
0'
#815
1+
1'
#820
0'
#825
1.
1#
1)
1'
#830
0'
#835
1-
1"
0.
0#
b0 &
b0 /
1%
0)
02
11
1'
#840
0'
#845
0%
1.
1#
0-
0"
01
b0 0
12
1)
b1 !
b1 (
b1 ,
0+
1'
#850
0'
#855
0.
0#
b1 &
b1 /
0$
1%
0)
02
11
1'
#860
0'
#865
01
1)
1'
#870
0'
#875
0)
11
1'
#880
0'
#885
1$
1-
1"
01
1+
1'
#890
0'
#895
0-
0"
1.
1#
0%
b10 !
b10 (
b10 ,
1)
b1 0
12
1'
#900
0'
#905
1-
1"
b10 &
b10 /
1%
11
02
1'
#910
0'
#915
b11 &
b11 /
b11 !
b11 (
b11 ,
1'
#920
0'
#925
0.
0#
b100 &
b100 /
0$
0-
0"
0)
b100 !
b100 (
b100 ,
0+
1'
#930
0'
#935
1$
1-
1"
1+
01
1'
#940
0'
#945
0%
0-
0"
b100 0
12
b101 !
b101 (
b101 ,
0+
1'
#950
0'
#955
1.
1#
1+
1)
1'
#960
0'
#965
1-
1"
b101 &
b101 /
1%
0.
0#
11
02
0)
1'
#970
0'
#975
0-
0"
0%
b110 !
b110 (
b110 ,
0+
b101 0
12
01
1'
#980
0'
#985
1.
1#
1)
1+
1'
#990
0'
#995
1-
1"
0.
0#
b110 &
b110 /
1%
0)
02
11
1'
#1000
0'
#1005
0%
0-
0"
01
b110 0
12
b111 !
b111 (
b111 ,
0+
1'
#1010
0'
#1015
1.
1#
1+
1)
1'
#1020
0'
#1025
1-
1"
b111 &
b111 /
1%
0.
0#
11
02
0)
1'
#1030
0'
#1035
0-
0"
0%
b1000 !
b1000 (
b1000 ,
0+
b111 0
12
01
1'
#1040
0'
#1045
1+
1'
#1050
0'
#1055
1'
#1060
0'
#1065
1.
1#
1)
1'
#1070
0'
#1075
1-
1"
0.
0#
b1000 &
b1000 /
1%
0)
02
11
1'
#1080
0'
#1085
0%
0-
0"
01
b1000 0
12
b1001 !
b1001 (
b1001 ,
0+
1'
#1090
0'
#1095
1.
1#
1)
1'
#1100
0'
#1105
1-
1"
b1001 &
b1001 /
1%
11
02
1+
1'
#1110
0'
#1115
b1010 &
b1010 /
0$
0-
0"
0.
0#
b1010 !
b1010 (
b1010 ,
0+
0)
1'
#1120
0'
#1125
01
1'
#1130
0'
#1135
1)
1'
#1140
0'
#1145
11
0)
1'
#1150
0'
#1155
1$
1-
1"
1+
01
1'
#1160
0'
#1165
0-
0"
0%
1.
1#
b1010 0
12
1)
b1011 !
b1011 (
b1011 ,
1'
#1170
0'
#1175
1-
1"
0.
0#
b1011 &
b1011 /
1%
0)
02
11
1'
#1180
0'
#1185
0-
0"
0%
1.
1#
01
b1011 0
12
1)
b1100 !
b1100 (
b1100 ,
1'
#1190
0'
#1195
1-
1"
b1100 &
b1100 /
1%
02
11
1'
#1200
0'
#1205
0.
0#
b1101 &
b1101 /
0$
0-
0"
0)
b1101 !
b1101 (
b1101 ,
0+
1'
#1210
0'
#1215
1.
1#
1$
1-
1"
1+
1)
01
1'
#1220
0'
#1225
b1110 &
b1110 /
11
b1110 !
b1110 (
b1110 ,
1'
#1230
0'
#1235
0.
0#
b1111 &
b1111 /
0$
0-
0"
b1111 !
b1111 (
b1111 ,
0+
1'
#1240
0'
#1245
1.
1#
1$
1-
1"
1+
1'
#1250
0'
#1255
b0 &
b0 /
0$
0-
0"
0.
0#
b0 !
b0 (
b0 ,
0+
0)
1'
#1260
0'
#1265
01
1'
#1270
0'
#1275
1.
1#
1$
1-
1"
1+
1)
1'
#1280
0'
#1285
0.
0#
b1 &
b1 /
0$
0-
0"
11
0)
b1 !
b1 (
b1 ,
0+
1'
#1290
0'
#1295
1)
01
1'
#1300
0'
#1305
11
1'
#1310
0'
#1315
0)
1'
#1320
0'
#1325
1$
1-
1"
01
1+
1'
#1330
0'
#1335
0-
0"
0%
b10 !
b10 (
b10 ,
b1 0
12
1'
#1340
0'
#1345
1.
1#
1)
1'
#1350
0'
#1355
1-
1"
b10 &
b10 /
1%
02
11
1'
#1360
0'
#1365
0.
0#
b11 &
b11 /
0$
0-
0"
0)
b11 !
b11 (
b11 ,
0+
1'
#1370
0'
#1375
1$
1-
1"
1+
01
1'
#1380
0'
#1385
0%
0-
0"
b11 0
12
b100 !
b100 (
b100 ,
0+
1'
#1390
0'
#1395
1.
1#
1)
1'
#1400
0'
#1405
b100 &
b100 /
1%
0$
0.
0#
11
02
0)
1'
#1410
0'
#1415
1$
1-
1"
1+
01
1'
#1420
0'
#1425
0%
0-
0"
b100 0
12
b101 !
b101 (
b101 ,
0+
1'
#1430
0'
#1435
1+
1'
#1440
0'
#1445
1.
1#
1)
1'
#1450
0'
#1455
1-
1"
0.
0#
b101 &
b101 /
1%
0)
02
11
1'
#1460
0'
#1465
0-
0"
0%
1.
1#
01
b101 0
12
1)
b110 !
b110 (
b110 ,
1'
#1470
0'
#1475
1-
1"
b110 &
b110 /
1%
02
11
1'
#1480
0'
#1485
0.
0#
b111 &
b111 /
0)
b111 !
b111 (
b111 ,
1'
#1490
0'
#1495
0-
0"
1.
1#
0%
b1000 !
b1000 (
b1000 ,
1)
b111 0
12
01
1'
#1500
0'
#1505
1-
1"
b1000 &
b1000 /
1%
11
02
1'
#1510
0'
#1515
b1001 &
b1001 /
0$
0-
0"
0.
0#
b1001 !
b1001 (
b1001 ,
0+
0)
1'
#1520
0'
#1525
1$
1-
1"
01
1+
1'
#1530
0'
#1535
0-
0"
0%
b1010 !
b1010 (
b1010 ,
b1001 0
12
1'
#1540
0'
#1545
1.
1#
1)
1'
#1550
0'
#1555
1-
1"
0.
0#
b1010 &
b1010 /
1%
0)
02
11
1'
#1560
0'
#1565
0%
1.
1#
0-
0"
01
b1010 0
12
1)
b1011 !
b1011 (
b1011 ,
0+
1'
#1570
0'
#1575
0.
0#
b1011 &
b1011 /
0$
1%
0)
02
11
1'
#1580
0'
#1585
1$
1-
1"
01
1+
1'
#1590
0'
#1595
0-
0"
1.
1#
0%
b1100 !
b1100 (
b1100 ,
1)
b1011 0
12
1'
#1600
0'
#1605
1-
1"
b1100 &
b1100 /
1%
0.
0#
11
02
0)
1'
#1610
0'
#1615
0-
0"
1.
1#
0%
b1101 !
b1101 (
b1101 ,
0+
1)
b1100 0
12
01
1'
#1620
0'
#1625
1-
1"
b1101 &
b1101 /
1%
0.
0#
11
02
0)
1+
1'
#1630
0'
#1635
0-
0"
0%
b1110 !
b1110 (
b1110 ,
b1101 0
12
01
1'
#1640
0'
#1645
1'
#1650
0'
#1655
1'
#1660
0'
#1665
1'
#1670
0'
#1675
1.
1#
1)
1'
#1680
0'
#1685
1-
1"
b1110 &
b1110 /
1%
11
02
1'
#1690
0'
#1695
b1111 &
b1111 /
b1111 !
b1111 (
b1111 ,
1'
#1700
0'
#1705
0.
0#
b0 &
b0 /
0)
b0 !
b0 (
b0 ,
1'
#1710
0'
#1715
0-
0"
1.
1#
0%
b1 !
b1 (
b1 ,
1)
b0 0
12
01
1'
#1720
0'
#1725
1-
1"
b1 &
b1 /
1%
11
02
1'
#1730
0'
#1735
b10 &
b10 /
0$
0-
0"
0.
0#
b10 !
b10 (
b10 ,
0+
0)
1'
#1740
0'
#1745
01
1'
#1750
0'
#1755
1'
#1760
0'
#1765
1.
1#
1$
1-
1"
1)
1+
1'
#1770
0'
#1775
b11 &
b11 /
b11 !
b11 (
b11 ,
11
1'
#1780
0'
#1785
b100 &
b100 /
b100 !
b100 (
b100 ,
1'
#1790
0'
#1795
0.
0#
b101 &
b101 /
0$
0-
0"
b101 !
b101 (
b101 ,
0+
1'
#1800
0'
#1805
1.
1#
1$
1-
1"
1+
1'
#1810
0'
#1815
b110 &
b110 /
b110 !
b110 (
b110 ,
1'
#1820
0'
#1825
b111 &
b111 /
b111 !
b111 (
b111 ,
1'
#1830
0'
#1835
b1000 &
b1000 /
b1000 !
b1000 (
b1000 ,
1'
#1840
0'
#1845
0.
0#
b1001 &
b1001 /
0$
0-
0"
0)
b1001 !
b1001 (
b1001 ,
0+
1'
#1850
0'
#1855
1.
1#
1$
1-
1"
1+
1)
01
1'
#1860
0'
#1865
0.
0#
b1010 &
b1010 /
0$
0-
0"
11
0)
b1010 !
b1010 (
b1010 ,
0+
1'
#1870
0'
#1875
01
1'
#1880
0'
#1885
1$
1-
1"
1+
1'
#1890
0'
#1895
0-
0"
0%
b1011 !
b1011 (
b1011 ,
0+
b1010 0
12
1'
#1900
0'
#1905
1'
#1910
0'
#1915
1+
1'
#1920
0'
#1925
1'
#1930
0'
#1935
1'
#1940
0'
#1945
1.
1#
1)
1'
#1950
0'
#1955
1-
1"
0.
0#
b1011 &
b1011 /
1%
0)
02
11
1'
#1960
0'
#1965
0%
0-
0"
01
b1011 0
12
b1100 !
b1100 (
b1100 ,
0+
1'
#1970
0'
#1975
1+
1'
#1980
0'
#1985
1.
1#
1)
1'
#1990
0'
#1995
1-
1"
b1100 &
b1100 /
1%
02
11
1'
#2000
0'
#2005
b1101 &
b1101 /
b1101 !
b1101 (
b1101 ,
1'
#2010
0'
#2015
b1110 &
b1110 /
0.
0#
b1110 !
b1110 (
b1110 ,
0)
1'
#2020
0'
#2025
0-
0"
0%
1.
1#
01
b1110 0
12
1)
b1111 !
b1111 (
b1111 ,
1'
#2030
0'
#2035
1-
1"
0.
0#
b1111 &
b1111 /
1%
0)
02
11
1'
#2040
0'
#2045
0-
0"
0%
01
b1111 0
12
b0 !
b0 (
b0 ,
1'
#2050
0'
#2055
1'
#2060
0'
#2065
1.
1#
1)
1'
#2070
0'
#2075
1-
1"
b0 &
b0 /
1%
02
11
1'
#2080
0'
#2085
0.
0#
b1 &
b1 /
0$
0-
0"
b1 !
b1 (
b1 ,
0+
1'
#2090
0'
#2095
0)
1'
#2100
0'
#2105
1$
1-
1"
01
1+
1'
#2110
0'
#2115
0-
0"
0%
b10 !
b10 (
b10 ,
0+
b1 0
12
1'
#2120
0'
#2125
1.
1#
1)
1'
#2130
0'
#2135
1-
1"
b10 &
b10 /
1%
1+
02
11
1'
#2140
0'
#2145
0.
0#
b11 &
b11 /
0)
b11 !
b11 (
b11 ,
1'
#2150
0'
#2155
0-
0"
1.
1#
0%
b100 !
b100 (
b100 ,
1)
b11 0
12
01
1'
#2160
0'
#2165
1-
1"
b100 &
b100 /
1%
11
02
1'
#2170
0'
#2175
b101 &
b101 /
b101 !
b101 (
b101 ,
1'
#2180
0'
#2185
b110 &
b110 /
b110 !
b110 (
b110 ,
1'
#2190
0'
#2195
b111 &
b111 /
0.
0#
b111 !
b111 (
b111 ,
0)
1'
#2200
0'
#2205
0%
1.
1#
0-
0"
01
b111 0
12
1)
b1000 !
b1000 (
b1000 ,
0+
1'
#2210
0'
#2215
0.
0#
b1000 &
b1000 /
0$
1%
0)
02
11
1'
#2220
0'
#2225
1$
1-
1"
01
1+
1'
#2230
0'
#2235
0-
0"
0%
b1001 !
b1001 (
b1001 ,
0+
b1000 0
12
1'
#2240
0'
#2245
1'
#2250
0'
#2255
1.
1#
1)
1'
#2260
0'
#2265
b1001 &
b1001 /
1%
0$
0.
0#
11
02
0)
1'
#2270
0'
#2275
01
1'
#2280
0'
#2285
1)
1'
#2290
0'
#2295
1$
1-
1"
1+
0)
11
1'
#2300
0'
#2305
0%
0-
0"
01
b1001 0
12
b1010 !
b1010 (
b1010 ,
0+
1'
#2310
0'
#2315
1.
1#
1)
1'
#2320
0'
#2325
1-
1"
b1010 &
b1010 /
1%
11
02
1+
1'
#2330
0'
#2335
b1011 &
b1011 /
0.
0#
b1011 !
b1011 (
b1011 ,
0)
1'
#2340
0'
#2345
0%
1.
1#
0-
0"
01
b1011 0
12
1)
b1100 !
b1100 (
b1100 ,
0+
1'
#2350
0'
#2355
0.
0#
b1100 &
b1100 /
0$
1%
0)
02
11
1'
#2360
0'
#2365
01
1'
#2370
0'
#2375
1)
1'
#2380
0'
#2385
1$
1-
1"
11
0)
1+
1'
#2390
0'
#2395
0-
0"
1.
1#
0%
b1101 !
b1101 (
b1101 ,
1)
b1100 0
12
01
1'
#2400
0'
#2405
1-
1"
b1101 &
b1101 /
1%
0.
0#
11
02
0)
1'
#2410
0'
#2415
0-
0"
1.
1#
0%
b1110 !
b1110 (
b1110 ,
0+
1)
b1101 0
12
01
1'
#2420
0'
#2425
1-
1"
b1110 &
b1110 /
1%
11
02
1+
1'
#2430
0'
#2435
0.
0#
b1111 &
b1111 /
0$
0-
0"
b1111 !
b1111 (
b1111 ,
0+
1'
#2440
0'
#2445
1.
1#
1$
1-
1"
1+
1'
#2450
0'
#2455
b0 &
b0 /
0$
0-
0"
0.
0#
b0 !
b0 (
b0 ,
0+
0)
1'
#2460
0'
#2465
1.
1#
1$
1-
1"
01
1)
1+
1'
#2470
0'
#2475
b1 &
b1 /
0$
0-
0"
0.
0#
b1 !
b1 (
b1 ,
0+
0)
11
1'
#2480
0'
#2485
1.
1#
1$
1-
1"
01
1)
1+
1'
#2490
0'
#2495
b10 &
b10 /
0$
0-
0"
0.
0#
b10 !
b10 (
b10 ,
0+
0)
11
1'
#2500
0'
#2505
1$
1-
1"
01
1+
1'
#2510
0'
#2515
0-
0"
0%
b11 !
b11 (
b11 ,
b10 0
12
1'
#2520
0'
#2525
1.
1#
1)
1'
#2530
0'
#2535
1-
1"
0.
0#
b11 &
b11 /
1%
0)
02
11
1'
#2540
0'
#2545
0%
1.
1#
0-
0"
01
b11 0
12
1)
b100 !
b100 (
b100 ,
0+
1'
#2550
0'
#2555
0.
0#
b100 &
b100 /
0$
1%
0)
02
11
1'
#2560
0'
#2565
1.
1#
1$
1-
1"
01
1)
1+
1'
#2570
0'
#2575
b101 &
b101 /
0.
0#
b101 !
b101 (
b101 ,
0)
11
1'
#2580
0'
#2585
0%
1.
1#
0-
0"
01
b101 0
12
1)
b110 !
b110 (
b110 ,
0+
1'
#2590
0'
#2595
0.
0#
b110 &
b110 /
0$
1%
02
11
1'
#2600
0'
#2605
1.
1#
1$
1-
1"
1+
1'
#2610
0'
#2615
0.
0#
b111 &
b111 /
0$
0-
0"
b111 !
b111 (
b111 ,
0+
1'
#2620
0'
#2625
1.
1#
1$
1-
1"
1+
1'
#2630
0'
#2635
0.
0#
b1000 &
b1000 /
0$
0-
0"
b1000 !
b1000 (
b1000 ,
0+
1'
#2640
0'
#2645
1'
#2650
0'
#2655
0)
1'
#2660
0'
#2665
1$
1-
1"
01
1+
1'
#2670
0'
#2675
0-
0"
0%
b1001 !
b1001 (
b1001 ,
b1000 0
12
1'
#2680
0'
#2685
1.
1#
1)
1'
#2690
0'
#2695
1-
1"
0.
0#
b1001 &
b1001 /
1%
0)
02
11
1'
#2700
0'
#2705
0-
0"
0%
01
b1001 0
12
b1010 !
b1010 (
b1010 ,
1'
#2710
0'
#2715
1.
1#
1)
1'
#2720
0'
#2725
1-
1"
b1010 &
b1010 /
1%
11
02
1'
#2730
0'
#2735
b1011 &
b1011 /
b1011 !
b1011 (
b1011 ,
1'
#2740
0'
#2745
0.
0#
b1100 &
b1100 /
0$
0-
0"
0)
b1100 !
b1100 (
b1100 ,
0+
1'
#2750
0'
#2755
1)
01
1'
#2760
0'
#2765
1$
1-
1"
11
0)
1+
1'
#2770
0'
#2775
0-
0"
1.
1#
0%
b1101 !
b1101 (
b1101 ,
1)
b1100 0
12
01
1'
#2780
0'
#2785
1-
1"
b1101 &
b1101 /
1%
0.
0#
11
02
0)
1'
#2790
0'
#2795
0-
0"
0%
b1110 !
b1110 (
b1110 ,
b1101 0
12
01
1'
#2800
0'
#2805
1.
1#
1)
1'
#2810
0'
#2815
1-
1"
b1110 &
b1110 /
1%
02
11
1'
#2820
0'
#2825
0.
0#
b1111 &
b1111 /
0$
0-
0"
0)
b1111 !
b1111 (
b1111 ,
0+
1'
#2830
0'
#2835
1)
01
1'
#2840
0'
#2845
11
1'
#2850
0'
#2855
1.
1#
1$
1-
1"
1+
1'
#2860
0'
#2865
0.
0#
b0 &
b0 /
0$
0-
0"
b0 !
b0 (
b0 ,
0+
1'
#2870
0'
#2875
1'
#2880
0'
#2885
0)
1'
#2890
0'
#2895
1.
1#
1$
1-
1"
1+
1)
01
1'
#2900
0'
#2905
0.
0#
b1 &
b1 /
11
0)
b1 !
b1 (
b1 ,
1'
#2910
0'
#2915
0-
0"
0%
b10 !
b10 (
b10 ,
0+
b1 0
12
01
1'
#2920
0'
#2925
1.
1#
1)
1+
1'
#2930
0'
#2935
1-
1"
b10 &
b10 /
1%
02
11
1'
#2940
0'
#2945
0.
0#
b11 &
b11 /
0)
b11 !
b11 (
b11 ,
1'
#2950
0'
#2955
0-
0"
1.
1#
0%
b100 !
b100 (
b100 ,
1)
b11 0
12
01
1'
#2960
0'
#2965
1-
1"
b100 &
b100 /
1%
11
02
1'
#2970
0'
#2975
b101 &
b101 /
b101 !
b101 (
b101 ,
1'
#2980
0'
#2985
b110 &
b110 /
b110 !
b110 (
b110 ,
1'
#2990
0'
#2995
b111 &
b111 /
0.
0#
b111 !
b111 (
b111 ,
0)
1'
#3000
0'
#3005
0%
0-
0"
01
b111 0
12
b1000 !
b1000 (
b1000 ,
0+
1'
#3010
0'
#3015
1+
1'
#3020
0'
#3025
1.
1#
1)
1'
#3030
0'
#3035
1-
1"
b1000 &
b1000 /
1%
02
11
1'
#3040
0'
#3045
b1001 &
b1001 /
b1001 !
b1001 (
b1001 ,
1'
#3050
0'
#3055
b1010 &
b1010 /
b1010 !
b1010 (
b1010 ,
1'
#3060
0'
#3065
b1011 &
b1011 /
b1011 !
b1011 (
b1011 ,
1'
#3070
0'
#3075
b1100 &
b1100 /
0$
0-
0"
0.
0#
b1100 !
b1100 (
b1100 ,
0+
0)
1'
#3080
0'
#3085
01
1)
1'
#3090
0'
#3095
0)
11
1'
#3100
0'
#3105
01
1)
1'
#3110
0'
#3115
11
1'
#3120
0'
#3125
0)
1'
#3130
0'
#3135
1.
1#
1$
1-
1"
1+
1)
01
1'
#3140
0'
#3145
0.
0#
b1101 &
b1101 /
0$
0-
0"
11
b1101 !
b1101 (
b1101 ,
0+
1'
#3150
0'
#3155
1$
1-
1"
1+
0)
1'
#3160
0'
#3165
0%
0-
0"
01
b1101 0
12
b1110 !
b1110 (
b1110 ,
0+
1'
#3170
0'
#3175
1+
1'
#3180
0'
#3185
1.
1#
1)
1'
#3190
0'
#3195
1-
1"
b1110 &
b1110 /
1%
02
11
1'
#3200
0'
#3205
0.
0#
b1111 &
b1111 /
0$
0-
0"
b1111 !
b1111 (
b1111 ,
0+
1'
#3210
0'
#3215
1$
1-
1"
1+
0)
1'
#3220
0'
#3225
0%
1.
1#
0-
0"
01
b1111 0
12
1)
b0 !
b0 (
b0 ,
0+
1'
#3230
0'
#3235
0.
0#
b0 &
b0 /
0$
1%
02
11
1'
#3240
0'
#3245
0)
1'
#3250
0'
#3255
1$
1-
1"
1+
01
1'
#3260
0'
#3265
0-
0"
0%
b0 0
12
b1 !
b1 (
b1 ,
1'
#3270
0'
#3275
1'
#3280
0'
#3285
1.
1#
1)
1'
#3290
0'
#3295
1-
1"
0.
0#
b1 &
b1 /
1%
0)
02
11
1'
#3300
0'
#3305
0-
0"
0%
01
b1 0
12
b10 !
b10 (
b10 ,
1'
#3310
0'
#3315
1.
1#
1)
1'
#3320
0'
#3325
1-
1"
b10 &
b10 /
1%
11
02
1'
#3330
0'
#3335
b11 &
b11 /
0.
0#
b11 !
b11 (
b11 ,
0)
1'
#3340
0'
#3345
0-
0"
0%
01
b11 0
12
b100 !
b100 (
b100 ,
1'
#3350
0'
#3355
1'
#3360
0'
#3365
1'
#3370
0'
#3375
1'
#3380
0'
#3385
1.
1#
1)
1'
#3390
0'
