sky/SHA1/code/sha1.v
module sha1 (
    input           clk,
    input           rstn,
    input           din_vld,//16T
    input  [31:0]   din,
    input           use_prec_cv,
    output reg      busy,
    output [159:0]  dout,
    output reg      dout_vld //1T
);
parameter   H0 = 32'h67452301,
            H1 = 32'hEFCDAB89,
            H2 = 32'h98BADCFE,
            H3 = 32'h10325476,
            H4 = 32'hC3D2E1F0;
            //K0 = 32'h5A827999,
            //K1 = 32'h6ED9EBA1,
            //K2 = 32'h8F1BBCDC,
            //K3 = 32'hCA62C1D6;
//-------------------------W(t) generation------------------------//
reg din_vld_d;
reg  [6:0]   w_cnt;
reg  [31:0]  w_reg [15:0];
reg          w_busy;

wire [31:0] r0,r1,r2,r3,r4,r5,r6,r7,r8,r9,r10,r11,r12,r13,r14,r15;
//assign r0 = w_reg[0];
//assign r1 = w_reg[1];
//assign r2 = w_reg[2];
//assign r3 = w_reg[3];
//assign r4 = w_reg[4];
//assign r5 = w_reg[5];
//assign r6 = w_reg[6];
//assign r7 = w_reg[7];
//assign r8 = w_reg[8];
//assign r9 = w_reg[9];
//assign r10 = w_reg[10];
//assign r11 = w_reg[11];
//assign r12 = w_reg[12];
//assign r13 = w_reg[13];
//assign r14 = w_reg[14];
//assign r15 = w_reg[15];


wire [31:0] next_reg;
wire [31:0] next_reg_xor;
assign next_reg_xor = w_reg[13]^w_reg[8]^w_reg[2]^w_reg[0];
assign next_reg = {next_reg_xor[30:0],next_reg_xor[31]};

always@(posedge clk or negedge rstn) begin
    if (!rstn) begin
        w_cnt <= 'b0;
    end else if (din_vld || w_busy) begin
        w_cnt <= w_cnt + 1;
        if (w_cnt == 'd79) begin
            w_cnt <= 'b0;
        end
    end
end

always@(posedge clk or negedge rstn) begin
    if (!rstn) begin
        w_busy <= 1'b0;//enable
    end else if (din_vld) begin
        w_busy <= 1'b1;
    end else if (w_cnt == 'd79) begin
        w_busy <= 1'b0;
    end
end

generate
    genvar i;
    for (i = 0; i < 15; i = i+1) begin
        always@(posedge clk or negedge rstn) begin
            if (!rstn) begin
                w_reg[i] <= 'b0;
            end else begin
                w_reg[i] <= w_reg[i+1];
            end
        end
    end

endgenerate

always@(posedge clk or negedge rstn) begin
    if (!rstn) begin
        w_reg[15] <= 'b0;
    end else if (din_vld) begin
        w_reg[15] <= din;
    end else if (w_busy) begin
        w_reg[15] <= next_reg;
    end 
    
end

always@(posedge clk or negedge rstn) begin
    if (!rstn) begin
        din_vld_d <= 0;
    end else begin
        din_vld_d <= din_vld;
    end
end

// -------------------------------------------------------
// -- 核心计算
// -------------------------------------------------------
reg [31:0] h0,h1,h2,h3,h4;
assign dout = {h0,h1,h2,h3,h4};

reg [31:0] A_reg,B_reg,C_reg,D_reg,E_reg;
wire [31:0] A_next;
reg [31:0] k;
reg [31:0] fx;
reg     a_e_busy;
reg     a_e_busy_d;
assign A_next = {A_reg[26:0],A_reg[31:27]} + fx + E_reg + w_reg[15] + k;


always@(posedge clk or negedge rstn) begin
    if (!rstn) begin
        A_reg <= H0;
        B_reg <= H1;
        C_reg <= H2;
        D_reg <= H3;
        E_reg <= H4;
    end else if (din_vld && !din_vld_d) begin
        if (use_prec_cv) begin
            A_reg <= h0;
            B_reg <= h1;
            C_reg <= h2;
            D_reg <= h3;
            E_reg <= h4;
        end else  begin
            A_reg <= H0;
            B_reg <= H1;
            C_reg <= H2;
            D_reg <= H3;
            E_reg <= H4;
        end
    end else if (a_e_busy) begin
        A_reg <= A_next;
        B_reg <= A_reg;
        C_reg <= {B_reg[1:0],B_reg[31:2]};
        D_reg <= C_reg;
        E_reg <= D_reg;
    end
end
reg [1:0] stage_cal;
always@(posedge clk or negedge rstn) begin
    if (!rstn) begin
        stage_cal <= 'b0;
    end else if (din_vld && !din_vld_d) begin
        stage_cal <= 'b0;
    end else if ((w_cnt=='d20) || (w_cnt=='d40) || (w_cnt=='d60)) begin
        stage_cal <= stage_cal + 1;
    end
end
always @(*) begin
    case (stage_cal)
        'd0 : 
            begin
                k = 32'h5A827999;
                fx = (B_reg & C_reg) |((~B_reg) & D_reg);
            end
        'd1 :
            begin
                k = 32'h6ED9EBA1;
                fx = (B_reg ^ C_reg ^ D_reg);
            end
        'd2 :
            begin
                k = 32'h8F1BBCDC;
                fx = (B_reg & C_reg) |(B_reg & D_reg) | (C_reg & D_reg);
            end
        'd3 :
            begin
                k = 32'hCA62C1D6;
                fx = (B_reg ^ C_reg ^ D_reg);
            end
    endcase
end


always@(posedge clk or negedge rstn) begin
    if (!rstn) begin
        {a_e_busy_d,a_e_busy} <= 'b0;
    end else begin
        {a_e_busy_d,a_e_busy} <= {a_e_busy,din_vld|w_busy};
    end
end

always@(posedge clk or negedge rstn) begin
    if (!rstn) begin
        h0 <= H0;
        h1 <= H1;
        h2 <= H2;
        h3 <= H3;
        h4 <= H4;
    end else if (din_vld && (!din_vld_d)) begin
        if (use_prec_cv) begin
            h0 <= H0;
            h1 <= H1;
            h2 <= H2;
            h3 <= H3;
            h4 <= H4;
        end
    end else if (!a_e_busy && a_e_busy_d) begin
        //`ifndef _SHA_STAND_ALGORUTHM_
        //    h0 <= A_reg;
        //    h1 <= B_reg;
        //    h2 <= C_reg;
        //    h3 <= D_reg;
         //   h4 <= E_reg;
        //`else 
            h0 <= A_reg + H0;
            h1 <= B_reg + H1;
            h2 <= C_reg + H2;
            h3 <= D_reg + H3;
            h4 <= E_reg + H4;
        //`endif 
    end
end


always@(posedge clk or negedge rstn) begin
    if (!rstn) begin
        dout_vld <= 1'b0;
    end else if (!a_e_busy && a_e_busy_d) begin
        dout_vld <= 1'b1;
    end else begin
        dout_vld <= 1'b0;
    end
end

always@(posedge clk or negedge rstn) begin
    if (!rstn) begin
        busy <= 1'b0;
    end else if (din_vld && !din_vld_d) begin
        busy <= 1'b1;
    end else if (!a_e_busy && a_e_busy_d) begin
        busy <= 1'b0;
    end
end












endmodule //sha1

sky/SHA1/code/tb_sha1.v
`timescale  1ns / 1ps

module tb_sha1;      

// sha1 Parameters
parameter PERIOD = 10          ;
parameter MAX_TEST = 4;

// sha1 Inputs
reg   clk        ;
reg   rstn       ;
reg   din_vld    ;
reg   [31:0]  din;
reg   use_prec_cv;

// sha1 Outputs
wire  busy         ;
wire  [159:0]  dout;
wire  dout_vld     ;
integer i,tcnt;
reg [7:0]   b0, b1, b2, b3;
reg [159:0] expected_result, cv, cv_next;

integer fp_din, fp_dout;
reg start;
//integer j;

initial
begin
    clk = 0;
    forever #(PERIOD/2)  clk=~clk;
end
initial
begin
    rstn = 0;
    repeat(4) @(posedge clk);
    #1 rstn  =  1;
end
initial begin
    $dumpfile("test.vcd");
    $dumpvars;
    for (i=0; i < 16; i = i + 1) begin
        $dumpvars(0, u_sha1.w_reg[i]);
    end
end

sha1 u_sha1 (
    .clk                     ( clk                  ),
    .rstn                    ( rstn                 ),
    .din_vld                 ( din_vld              ),
    .din                     ( din          [31:0]  ),
    .use_prec_cv             ( use_prec_cv          ),

    .busy                    ( busy                 ),
    .dout                    ( dout         [159:0] ),
    .dout_vld                ( dout_vld             )
);
initial begin
    cv = 160'h67452301_EFCDAB89_98BADCFE_10325476_C3D2E1F0;
    use_prec_cv = 1'b0;
    start = 0; din_vld = 0;

    fp_din = $fopen("../cmodel/sha_1/sha_in.bin","rb");
    fp_dout = $fopen("../cmodel/sha_1/sha_out.bin","rb");
    
    if (fp_din == 0) begin
        $display("Sim ERROR : FILE ../cmodel/sha_1/sha_in.bin don't exist which is needed by %m .");
        $finish();
    end

    if (fp_dout == 0) begin
        $display("Sim ERROR : FILE ../cmodel/sha_1/sha_out.bin don't exist which is needed by %m .");    
        $finish();
    end

    @(posedge clk);
    @(negedge clk);
    repeat(6) @(posedge clk);

    for ( tcnt=0; tcnt<MAX_TEST; tcnt=tcnt+1) begin
        
        for (i=0; i<16; i=i+1) begin
            b0 = $fgetc(fp_din);
            b1 = $fgetc(fp_din);
            b2 = $fgetc(fp_din);
            b3 = $fgetc(fp_din);
            #1;
            din = {b0,b1,b2,b3};
            din_vld = 1;
            @(posedge clk);
        end
        #1;
        din_vld = 0;
        start = 1;
        @(posedge clk);#1;
        start = 0;

        @(posedge dout_vld);
        //@(posedge clk);

        for (i=0; i<5; i=i+1) begin
            b0 = $fgetc(fp_dout);
            b1 = $fgetc(fp_dout);
            b2 = $fgetc(fp_dout);
            b3 = $fgetc(fp_dout);
            expected_result = (expected_result<<32)|{b3,b2,b1,b0};
        end
        @(posedge clk);
        if (expected_result !== dout) begin
            #1;
            $display("SHA-1 fail at test : %d \n",tcnt);
            $stop();
        end    
    end

    
    $display("SHA-1 test pass!\n : %d \n",tcnt);
    $finish();

end



endmodule

sky/SHA1/sim/test.vcd
$date
	Mon Aug 21 10:59:49 2023
$end
$version
	Icarus Verilog
$end
$timescale
	1ps
$end
$scope module tb_sha1 $end
$var wire 1 ! dout_vld $end
$var wire 160 " dout [159:0] $end
$var wire 1 # busy $end
$var reg 8 $ b0 [7:0] $end
$var reg 8 % b1 [7:0] $end
$var reg 8 & b2 [7:0] $end
$var reg 8 ' b3 [7:0] $end
$var reg 1 ( clk $end
$var reg 160 ) cv [159:0] $end
$var reg 32 * din [31:0] $end
$var reg 1 + din_vld $end
$var reg 160 , expected_result [159:0] $end
$var reg 1 - rstn $end
$var reg 1 . start $end
$var reg 1 / use_prec_cv $end
$var integer 32 0 fp_din [31:0] $end
$var integer 32 1 fp_dout [31:0] $end
$var integer 32 2 i [31:0] $end
$var integer 32 3 tcnt [31:0] $end
$scope module u_sha1 $end
$var wire 1 ( clk $end
$var wire 32 4 din [31:0] $end
$var wire 1 + din_vld $end
$var wire 32 5 next_reg_xor [31:0] $end
$var wire 1 - rstn $end
$var wire 1 / use_prec_cv $end
$var wire 32 6 next_reg [31:0] $end
$var wire 160 7 dout [159:0] $end
$var wire 32 8 A_next [31:0] $end
$var reg 32 9 A_reg [31:0] $end
$var reg 32 : B_reg [31:0] $end
$var reg 32 ; C_reg [31:0] $end
$var reg 32 < D_reg [31:0] $end
$var reg 32 = E_reg [31:0] $end
$var reg 1 > a_e_busy $end
$var reg 1 ? a_e_busy_d $end
$var reg 1 # busy $end
$var reg 1 @ din_vld_d $end
$var reg 1 ! dout_vld $end
$var reg 32 A fx [31:0] $end
$var reg 32 B h0 [31:0] $end
$var reg 32 C h1 [31:0] $end
$var reg 32 D h2 [31:0] $end
$var reg 32 E h3 [31:0] $end
$var reg 32 F h4 [31:0] $end
$var reg 32 G k [31:0] $end
$var reg 2 H stage_cal [1:0] $end
$var reg 1 I w_busy $end
$var reg 7 J w_cnt [6:0] $end
$scope begin genblk1[0] $end
$upscope $end
$scope begin genblk1[1] $end
$upscope $end
$scope begin genblk1[2] $end
$upscope $end
$scope begin genblk1[3] $end
$upscope $end
$scope begin genblk1[4] $end
$upscope $end
$scope begin genblk1[5] $end
$upscope $end
$scope begin genblk1[6] $end
$upscope $end
$scope begin genblk1[7] $end
$upscope $end
$scope begin genblk1[8] $end
$upscope $end
$scope begin genblk1[9] $end
$upscope $end
$scope begin genblk1[10] $end
$upscope $end
$scope begin genblk1[11] $end
$upscope $end
$scope begin genblk1[12] $end
$upscope $end
$scope begin genblk1[13] $end
$upscope $end
$scope begin genblk1[14] $end
$upscope $end
$upscope $end
$upscope $end
$scope module tb_sha1 $end
$scope module u_sha1 $end
$var reg 32 K \w_reg[0] [31:0] $end
$upscope $end
$upscope $end
$scope module tb_sha1 $end
$scope module u_sha1 $end
$var reg 32 L \w_reg[1] [31:0] $end
$upscope $end
$upscope $end
$scope module tb_sha1 $end
$scope module u_sha1 $end
$var reg 32 M \w_reg[2] [31:0] $end
$upscope $end
$upscope $end
$scope module tb_sha1 $end
$scope module u_sha1 $end
$var reg 32 N \w_reg[3] [31:0] $end
$upscope $end
$upscope $end
$scope module tb_sha1 $end
$scope module u_sha1 $end
$var reg 32 O \w_reg[4] [31:0] $end
$upscope $end
$upscope $end
$scope module tb_sha1 $end
$scope module u_sha1 $end
$var reg 32 P \w_reg[5] [31:0] $end
$upscope $end
$upscope $end
$scope module tb_sha1 $end
$scope module u_sha1 $end
$var reg 32 Q \w_reg[6] [31:0] $end
$upscope $end
$upscope $end
$scope module tb_sha1 $end
$scope module u_sha1 $end
$var reg 32 R \w_reg[7] [31:0] $end
$upscope $end
$upscope $end
$scope module tb_sha1 $end
$scope module u_sha1 $end
$var reg 32 S \w_reg[8] [31:0] $end
$upscope $end
$upscope $end
$scope module tb_sha1 $end
$scope module u_sha1 $end
$var reg 32 T \w_reg[9] [31:0] $end
$upscope $end
$upscope $end
$scope module tb_sha1 $end
$scope module u_sha1 $end
$var reg 32 U \w_reg[10] [31:0] $end
$upscope $end
$upscope $end
$scope module tb_sha1 $end
$scope module u_sha1 $end
$var reg 32 V \w_reg[11] [31:0] $end
$upscope $end
$upscope $end
$scope module tb_sha1 $end
$scope module u_sha1 $end
$var reg 32 W \w_reg[12] [31:0] $end
$upscope $end
$upscope $end
$scope module tb_sha1 $end
$scope module u_sha1 $end
$var reg 32 X \w_reg[13] [31:0] $end
$upscope $end
$upscope $end
$scope module tb_sha1 $end
$scope module u_sha1 $end
$var reg 32 Y \w_reg[14] [31:0] $end
$upscope $end
$upscope $end
$scope module tb_sha1 $end
$scope module u_sha1 $end
$var reg 32 Z \w_reg[15] [31:0] $end
$upscope $end
$upscope $end
$enddefinitions $end
#0
$dumpvars
b0 Z
b0 Y
b0 X
b0 W
b0 V
b0 U
b0 T
b0 S
b0 R
b0 Q
b0 P
b0 O
b0 N
b0 M
b0 L
b0 K
b0 J
0I
b0 H
b1011010100000100111100110011001 G
b11000011110100101110000111110000 F
b10000001100100101010001110110 E
b10011000101110101101110011111110 D
b11101111110011011010101110001001 C
b1100111010001010010001100000001 B
b10011000101110101101110011111110 A
0@
0?
0>
b11000011110100101110000111110000 =
b10000001100100101010001110110 <
b10011000101110101101110011111110 ;
b11101111110011011010101110001001 :
b1100111010001010010001100000001 9
b10011111101101001001100010110011 8
b110011101000101001000110000000111101111110011011010101110001001100110001011101011011100111111100001000000110010010101000111011011000011110100101110000111110000 7
b0 6
b0 5
bx 4
bx 3
b10000 2
b10000000000000000000000000000100 1
b10000000000000000000000000000011 0
0/
0.
0-
bx ,
0+
bx *
b110011101000101001000110000000111101111110011011010101110001001100110001011101011011100111111100001000000110010010101000111011011000011110100101110000111110000 )
0(
bx '
bx &
bx %
bx $
0#
b110011101000101001000110000000111101111110011011010101110001001100110001011101011011100111111100001000000110010010101000111011011000011110100101110000111110000 "
0!
$end
#5000
b0 Z
b0 Y
b0 X
b0 W
b0 V
b0 U
b0 T
b0 S
b0 R
b0 Q
b0 P
b0 O
b0 N
b0 M
b0 L
b0 K
1(
#10000
0(
#15000
b0 K
b0 L
b0 M
b0 N
b0 O
b0 P
b0 Q
b0 R
b0 S
b0 T
b0 U
b0 V
b0 W
b0 X
b0 Y
b0 Z
1(
#20000
0(
#25000
b0 Z
b0 Y
b0 X
b0 W
b0 V
b0 U
b0 T
b0 S
b0 R
b0 Q
b0 P
b0 O
b0 N
b0 M
b0 L
b0 K
1(
#30000
0(
#35000
b0 K
b0 L
b0 M
b0 N
b0 O
b0 P
b0 Q
b0 R
b0 S
b0 T
b0 U
b0 V
b0 W
b0 X
b0 Y
b0 Z
1(
#36000
1-
#40000
0(
#45000
b0 Y
b0 X
b0 W
b0 V
b0 U
b0 T
b0 S
b0 R
b0 Q
b0 P
b0 O
b0 N
b0 M
b0 L
b0 K
1(
#50000
0(
#55000
b0 K
b0 L
b0 M
b0 N
b0 O
b0 P
b0 Q
b0 R
b0 S
b0 T
b0 U
b0 V
b0 W
b0 X
b0 Y
1(
#60000
0(
#65000
b0 Y
b0 X
b0 W
b0 V
b0 U
b0 T
b0 S
b0 R
b0 Q
b0 P
b0 O
b0 N
b0 M
b0 L
b0 K
b10000000 '
b1100011 &
b1100010 %
b1100001 $
b0 2
b0 3
1(
#66000
1+
b1100001011000100110001110000000 *
b1100001011000100110001110000000 4
#70000
0(
#75000
b0 K
b0 L
b0 M
b0 N
b0 O
b0 P
b0 Q
b0 R
b0 S
b0 T
b0 U
b0 V
b0 W
b0 X
b0 Y
b1 J
1I
b1100001011000100110001110000000 Z
b1000101101111110000110011 8
1@
1>
1#
b0 '
b0 &
b0 %
b0 $
b1 2
1(
#76000
b0 *
b0 4
#80000
0(
#85000
b11111011111110111111111011111110 A
1?
b10000001100100101010001110110 =
b10011000101110101101110011111110 <
b1111011111100110110101011100010 ;
b1100111010001010010001100000001 :
b1000101101111110000110011 9
b0 Z
b10001001100100000101001101101101 8
b10 J
b1100001011000100110001110000000 Y
b0 X
b0 W
b0 V
b0 U
b0 T
b0 S
b0 R
b0 Q
b0 P
b0 O
b0 N
b0 M
b0 L
b0 K
b10 2
1(
#90000
0(
#95000
b11000010110001001100011100000000 6
b1100001011000100110001110000000 5
b1111011111100010100101011000000 A
b0 K
b0 L
b0 M
b0 N
b0 O
b0 P
b0 Q
b0 R
b0 S
b0 T
b0 U
b0 V
b0 W
b1100001011000100110001110000000 X
b0 Y
b11 J
b0 Z
b10100001001110010000111100001000 8
b10011000101110101101110011111110 =
b1111011111100110110101011100010 <
b1011001110100010100100011000000 ;
b1000101101111110000110011 :
b10001001100100000101001101101101 9
b11 2
1(
#100000
0(
#105000
b0 6
b0 5
b11010000010000010001101110001100 A
b11001101110110001110000100011011 8
b1111011111100110110101011100010 =
b1011001110100010100100011000000 <
b11000000010001011011111100001100 ;
b10001001100100000101001101101101 :
b10100001001110010000111100001000 9
b0 Z
b100 J
b0 Y
b0 X
b1100001011000100110001110000000 W
b0 V
b0 U
b0 T
b0 S
b0 R
b0 Q
b0 P
b0 O
b0 N
b0 M
b0 L
b0 K
b100 2
1(
#110000
0(
#115000
b1100000011001001011010000001100 A
b0 K
b0 L
b0 M
b0 N
b0 O
b0 P
b0 Q
b0 R
b0 S
b0 T
b0 U
b1100001011000100110001110000000 V
b0 W
b0 X
b0 Y
b101 J
b0 Z
b11001111110101001001100111011110 8
b1011001110100010100100011000000 =
b11000000010001011011111100001100 <
b1100010011001000001010011011011 ;
b10100001001110010000111100001000 :
b11001101110110001110000100011011 9
b101 2
1(
#120000
0(
#125000
b101010011011000101010111000010 A
b111111110001111100101001000000 8
b11000000010001011011111100001100 =
b1100010011001000001010011011011 <
b101000010011100100001111000010 ;
b11001101110110001110000100011011 :
b11001111110101001001100111011110 9
b0 Z
b110 J
b0 Y
b0 X
b0 W
b0 V
b1100001011000100110001110000000 U
b0 T
b0 S
b0 R
b0 Q
b0 P
b0 O
b0 N
b0 M
b0 L
b0 K
b110 2
1(
#130000
0(
#135000
b11100011010111100101101001000110 A
b0 K
b0 L
b0 M
b0 N
b0 O
b0 P
b0 Q
b0 R
b0 S
b1100001011000100110001110000000 T
b0 U
b0 V
b0 W
b0 X
b0 Y
b111 J
b0 Z
b10011001001111100011000011000001 8
b1100010011001000001010011011011 =
b101000010011100100001111000010 <
b11110011011101100011100001000110 ;
b11001111110101001001100111011110 :
b111111110001111100101001000000 9
b111 2
1(
#140000
0(
#145000
b11000010110001001100011100000000 6
b1100001011000100110001110000000 5
b11110011111101010011001001000110 A
b10011110100011000000011111010100 8
b101000010011100100001111000010 =
b11110011011101100011100001000110 <
b10110011111101010010011001110111 ;
b111111110001111100101001000000 :
b10011001001111100011000011000001 9
b0 Z
b1000 J
b0 Y
b0 X
b0 W
b0 V
b0 U
b0 T
b1100001011000100110001110000000 S
b0 R
b0 Q
b0 P
b0 O
b0 N
b0 M
b0 L
b0 K
b1000 2
1(
#150000
0(
#155000
b0 6
b0 5
b101011111100010011011010110110 A
b0 K
b0 L
b0 M
b0 N
b0 O
b0 P
b0 Q
b1100001011000100110001110000000 R
b0 S
b0 T
b0 U
b0 V
b0 W
b0 X
b0 Y
b1001 J
b0 Z
b1001011011010101110001100101000 8
b11110011011101100011100001000110 =
b10110011111101010010011001110111 <
b1111111100011111001010010000 ;
b10011001001111100011000011000001 :
b10011110100011000000011111010100 9
b1001 2
1(
#160000
0(
#165000
b111011111011111010000010000 A
b10000011010100011111100100101001 8
b10110011111101010010011001110111 =
b1111111100011111001010010000 <
b1100110010011111000110000110000 ;
b10011110100011000000011111010100 :
b1001011011010101110001100101000 9
b0 Z
b1010 J
b0 Y
b0 X
b0 W
b0 V
b0 U
b0 T
b0 S
b0 R
b1100001011000100110001110000000 Q
b0 P
b0 O
b0 N
b0 M
b0 L
b0 K
b1010 2
1(
#170000
0(
#175000
b100111001001110000110100110000 A
b0 K
b0 L
b0 M
b0 N
b0 O
b1100001011000100110001110000000 P
b0 Q
b0 R
b0 S
b0 T
b0 U
b0 V
b0 W
b0 X
b0 Y
b1011 J
b0 Z
b11111011110110101001111010001001 8
b1111111100011111001010010000 =
b1100110010011111000110000110000 <
b100111101000110000000111110101 ;
b1001011011010101110001100101000 :
b10000011010100011111100100101001 9
b1011 2
1(
#180000
0(
#185000
b100110111100101011100011011100 A
b1100011000110001000111111100100 8
b1100110010011111000110000110000 =
b100111101000110000000111110101 <
b10010110110101011100011001010 ;
b10000011010100011111100100101001 :
b11111011110110101001111010001001 9
b0 Z
b1100 J
b0 Y
b0 X
b0 W
b0 V
b0 U
b0 T
b0 S
b0 R
b0 Q
b0 P
b1100001011000100110001110000000 O
b0 N
b0 M
b0 L
b0 K
b1100 2
1(
#190000
0(
#195000
b1100000110100000011111001001010 A
b0 K
b0 L
b0 M
b1100001011000100110001110000000 N
b0 O
b0 P
b0 Q
b0 R
b0 S
b0 T
b0 U
b0 V
b0 W
b0 X
b0 Y
b1101 J
b0 Z
b1000110000001111011011001100100 8
b100111101000110000000111110101 =
b10010110110101011100011001010 <
b1100000110101000111111001001010 ;
b11111011110110101001111010001001 :
b1100011000110001000111111100100 9
b1101 2
1(
#200000
0(
#205000
b11000010110001001100011100000000 6
b1100001011000100110001110000000 5
b1100010110101001111011110101010 A
b10010001001010001111011010010101 8
b10010110110101011100011001010 =
b1100000110101000111111001001010 <
b1111110111101101010011110100010 ;
b1100011000110001000111111100100 :
b1000110000001111011011001100100 9
b0 Z
b1110 J
b0 Y
b0 X
b0 W
b0 V
b0 U
b0 T
b0 S
b0 R
b0 Q
b0 P
b0 O
b0 N
b1100001011000100110001110000000 M
b0 L
b0 K
b1110 2
1(
#210000
0(
#215000
b0 6
b0 5
b111000111101100010001111100010 A
b0 K
b1100001011000100110001110000000 L
b0 M
b0 N
b0 O
b0 P
b0 Q
b0 R
b0 S
b0 T
b0 U
b0 V
b0 W
b0 X
b0 Y
b1111 J
b0 Z
b11001011010111110111001110111 8
b1100000110101000111111001001010 =
b1111110111101101010011110100010 <
b11000110001100010001111111001 ;
b1000110000001111011011001100100 :
b10010001001010001111011010010101 9
b11000 '
b1111 2
1(
#216000
b11000 *
b11000 4
#220000
0(
#225000
b11000010110001001100011100000000 6
b11001110001101110010111111001 A
b1100001011000100110001110000000 5
b1111110111101101010011110100010 =
b11000110001100010001111111001 <
b10001100000011110110110011001 ;
b10010001001010001111011010010101 :
b11001011010111110111001110111 9
b11000 Z
b100000101111011101011000101111 8
b10000 J
b0 Y
b0 X
b0 W
b0 V
b0 U
b0 T
b0 S
b0 R
b0 Q
b0 P
b0 O
b0 N
b0 M
b0 L
b1100001011000100110001110000000 K
b10000 2
1(
#226000
1.
0+
#230000
0(
#235000
b0 6
b0 5
b110010100010110110101101 A
b0 K
b0 L
b0 M
b0 N
b0 O
b0 P
b0 Q
b0 R
b0 S
b0 T
b0 U
b0 V
b0 W
b0 X
b11000 Y
b10001 J
b11000010110001001100011100000000 Z
0@
b1001110100100100101100000100011 8
b11000110001100010001111111001 =
b10001100000011110110110011001 <
b1100100010010100011110110100101 ;
b11001011010111110111001110111 :
b100000101111011101011000101111 9
1(
#236000
0.
#240000
0(
#245000
b110000 6
b11000 5
b1000100010110101111101110001101 A
b10001100000011110110110011001 =
b1100100010010100011110110100101 <
b11000110010110101111101110011101 ;
b100000101111011101011000101111 :
b1001110100100100101100000100011 9
b0 Z
b10000010101010100110011100101000 8
b10010 J
b11000010110001001100011100000000 Y
b11000 X
b0 W
b0 V
b0 U
b0 T
b0 S
b0 R
b0 Q
b0 P
b0 O
b0 N
b0 M
b0 L
b0 K
1(
#250000
0(
#255000
b10000101100010011000111000000001 6
b11000010110001001100011100000000 5
b11001000010010101111001110011111 A
b0 K
b0 L
b0 M
b0 N
b0 O
b0 P
b0 Q
b0 R
b0 S
b0 T
b0 U
b0 V
b11000 W
b11000010110001001100011100000000 X
b0 Y
b10011 J
b110000 Z
b11011100011001001001000000011101 8
b1100100010010100011110110100101 =
b11000110010110101111101110011101 <
b11001000001011110111010110001011 ;
b1001110100100100101100000100011 :
b10000010101010100110011100101000 9
1(
#260000
0(
#265000
b0 6
b0 5
b11001010101001010001011010001011 A
b11000110010110101111101110011101 =
b11001000001011110111010110001011 <
b11010011101001001001011000001000 ;
b10000010101010100110011100101000 :
b11011100011001001001000000011101 9
b10000101100010011000111000000001 Z
b11111101100111100001110101111101 8
b10100 J
b110000 Y
b0 X
b11000010110001001100011100000000 W
b11000 V
b0 U
b0 T
b0 S
b0 R
b0 Q
b0 P
b0 O
b0 N
b0 M
b0 L
b0 K
1(
#270000
0(
#275000
b1100000 6
b110000 5
b101111011010101001111111011111 A
b1101110110110011110101110100001 G
b0 K
b0 L
b0 M
b0 N
b0 O
b0 P
b0 Q
b0 R
b0 S
b0 T
b11000 U
b11000010110001001100011100000000 V
b0 W
b110000 X
b10000101100010011000111000000001 Y
b10101 J
b0 Z
b11010001101111011000011001010 8
b11001000001011110111010110001011 =
b11010011101001001001011000001000 <
b100000101010101001100111001010 ;
b11011100011001001001000000011101 :
b11111101100111100001110101111101 9
b1 H
1(
#280000
0(
#285000
b1011000100110001110000000011 6
b10000101100010011000111000000001 5
b10101010001011011010000010110000 A
b11010011101001001001011000001000 =
b100000101010101001100111001010 <
b1110111000110010010010000000111 ;
b11111101100111100001110101111101 :
b11010001101111011000011001010 9
b1100000 Z
b110011101000100011101111111100 8
b10110 J
b0 Y
b10000101100010011000111000000001 X
b110000 W
b0 V
b11000010110001001100011100000000 U
b11000 T
b0 S
b0 R
b0 Q
b0 P
b0 O
b0 N
b0 M
b0 L
b0 K
1(
#290000
0(
#295000
b110000 6
b11000 5
b10010010010010001001110010010 A
b0 K
b0 L
b0 M
b0 N
b0 O
b0 P
b0 Q
b0 R
b11000 S
b11000010110001001100011100000000 T
b0 U
b110000 V
b10000101100010011000111000000001 W
b0 X
b1100000 Y
b10111 J
b1011000100110001110000000011 Z
b100001001010000011010010000110 8
b100000101010101001100111001010 =
b1110111000110010010010000000111 <
b1111111011001111000011101011111 ;
b11010001101111011000011001010 :
b110011101000100011101111111100 9
1(
#300000
0(
#305000
b10000101100010011000111011000001 6
b11000010110001001100011101100000 5
b11001010010010000101000010010001 A
b1110111000110010010010000000111 =
b1111111011001111000011101011111 <
b10000110100011011110110000110010 ;
b110011101000100011101111111100 :
b100001001010000011010010000110 9
b110000 Z
b11010101010000011111000100101101 8
b11000 J
b1011000100110001110000000011 Y
b1100000 X
b0 W
b10000101100010011000111000000001 V
b110000 U
b0 T
b11000010110001001100011100000000 S
b11000 R
b0 Q
b0 P
b0 O
b0 N
b0 M
b0 L
b0 K
1(
#310000
0(
#315000
b10110001001100011100000000110 6
b1011000100110001110000000011 5
b10101011010011010101011001001011 A
b0 K
b0 L
b0 M
b0 N
b0 O
b0 P
b11000 Q
b11000010110001001100011100000000 R
b0 S
b110000 T
b10000101100010011000111000000001 U
b0 V
b1100000 W
b1011000100110001110000000011 X
b110000 Y
b11001 J
b10000101100010011000111011000001 Z
b11000111010101100111110111000110 8
b1111111011001111000011101011111 =
b10000110100011011110110000110010 <
b1100111010001000111011111111 ;
b100001001010000011010010000110 :
b11010101010000011111000100101101 9
1(
#320000
0(
#325000
b0 6
b0 5
b1010001111000110111001011110011 A
b10000110100011011110110000110010 =
b1100111010001000111011111111 <
b10001000010010100000110100100001 ;
b11010101010000011111000100101101 :
b11000111010101100111110111000110 9
b10110001001100011100000000110 Z
b1001000010000010011101110100100 8
b11010 J
b10000101100010011000111011000001 Y
b110000 X
b1011000100110001110000000011 W
b1100000 V
b0 U
b10000101100010011000111000000001 T
b110000 S
b0 R
b11000010110001001100011100000000 Q
b11000 P
b0 O
b0 N
b0 M
b0 L
b0 K
1(
#330000
0(
#335000
b110000000 6
b11000000 5
b111010010011000000110010101100 A
b0 K
b0 L
b0 M
b0 N
b11000 O
b11000010110001001100011100000000 P
b0 Q
b110000 R
b10000101100010011000111000000001 S
b0 T
b1100000 U
b1011000100110001110000000011 V
b110000 W
b10000101100010011000111011000001 X
b10110001001100011100000000110 Y
b11011 J
b0 Z
b10111110001101011111101111010101 8
b1100111010001000111011111111 =
b10001000010010100000110100100001 <
b1110101010100000111110001001011 ;
b11000111010101100111110111000110 :
b1001000010000010011101110100100 9
1(
#340000
0(
#345000
b101100010011000111000000001100 6
b10110001001100011100000000110 5
b10001100110001001101100010011110 A
b10001000010010100000110100100001 =
b1110101010100000111110001001011 <
b10110001110101011001111101110001 ;
b1001000010000010011101110100100 :
b10111110001101011111101111010101 9
b110000000 Z
b1001010101010000100110110010111 8
b11100 J
b0 Y
b10110001001100011100000000110 X
b10000101100010011000111011000001 W
b110000 V
b1011000100110001110000000011 U
b1100000 T
b0 S
b10000101100010011000111000000001 R
b110000 Q
b0 P
b11000010110001001100011100000000 O
b11000 N
b0 M
b0 L
b0 K
1(
#350000
0(
