FIFO/async_fifo_高性能/code/async_cmp.v
module async_cmp #(
    parameter ADDRSIZE = 4
)
(
    input [ADDRSIZE-1:0] rptr,wptr,
    input w_rstn,
    output aempty_n,afull_n
);
    reg direct;
    wire dirset_n,dirclr;
    //wptr--->rptr-->afull---direct=1
    assign dirset_n = ~((wptr[ADDRSIZE-1] ^ rptr[ADDRSIZE-2]) & (~(wptr[ADDRSIZE-2] ^ rptr[ADDRSIZE-1])));
    //rptr-->wptr-->aempty--direct=0
    assign dirclr = (((wptr[ADDRSIZE-2]) ^ (rptr[ADDRSIZE-1])) & (~(wptr[ADDRSIZE-1] ^ rptr[ADDRSIZE-2])));
    
    wire rst;
    assign rst = ~(~w_rstn|dirclr);//dirclr有效时，rst=0,立即复位,无效时，rst=w_rstn。

    always @(negedge rst or negedge dirset_n ) begin
        if(!rst) 
            direct <= 0;
        else if (!dirset_n)
            direct <= 1;
        else    
            direct <= 0;
    end

    wire cmp_flag;
    assign cmp_flag = (rptr == wptr);
    assign aempty_n = ~(cmp_flag & (~direct));
    assign afull_n  = ~(cmp_flag & direct);

endmodule //async_cmp

sky/FIFO/async_fifo_高性能/code/async_fifo_2.v
module async_fifo_2 #(
    parameter DATESIZE  = 8,
    parameter ADDRSIZE  = 4
) 
(
    input [DATESIZE-1:0] wdata,
    input winc, wclk, w_rstn,
    input rinc, rclk, r_rstn,
    output  [DATESIZE-1:0] rdata,
    output reg wfull,
    output reg rempty
   
);

// RTL Verilog memory model
    wire [ADDRSIZE-1 : 0] waddr,raddr; 
    reg  [ADDRSIZE-1 : 0] wptr,rptr;

    localparam DEPTH = 1<<ADDRSIZE;
    reg [DATESIZE-1:0] mem [0:DEPTH-1];
    
    assign rdata = mem[raddr];
    always @(posedge wclk)
        if (winc && !wfull) mem[waddr] <= wdata;
      
    //COM
    async_cmp #(.ADDRSIZE(ADDRSIZE)) u_async_cmp  (
            .wptr(wptr),
            .rptr(rptr),
            .w_rstn(w_rstn),

            .aempty_n(aempty_n),
            .afull_n(afull_n)       
    );

    //异步信号需要先异步复位同步释放
    //aempty_n
    reg sync_r1;
    always @(posedge rclk or negedge aempty_n) begin
        if(~aempty_n)
            {rempty,sync_r1} = 2'b11;
        else 
            {rempty,sync_r1} = {sync_r1,~aempty_n};
    end

    reg sync_w1;
    always @(posedge rclk or negedge afull_n or negedge w_rstn) begin
        if (~w_rstn) 
            {wfull,sync_w1} = 2'b00;
        if(~afull_n) 
            {wfull,sync_w1} = 2'b11;
        else 
            {wfull,sync_w1} = {sync_w1,~afull_n} ;
    end
  
    reg [ADDRSIZE-1:0] wbin;
    wire [ADDRSIZE-1:0] wbin_next,wptr_next;
    wire mem_wr;
    assign mem_wr = winc & (!wfull);
    assign waddr = wbin;//写地址
    assign wbin_next = wbin+mem_wr;
    assign wptr_next = (wbin_next>>1) ^ wbin_next;// bin to gray code
    
    always @(posedge wclk or negedge w_rstn ) begin//reg output
        if (!w_rstn) begin
            {wptr,wbin} <= 0;
        end else begin
            {wptr,wbin} <= {wptr_next,wbin_next};
        end       
    end
    
    //empty 同理
    reg [ADDRSIZE-1:0] rbin;
    wire [ADDRSIZE-1:0] rptr_next, rbin_next;
    always @(posedge rclk or negedge r_rstn)
        if (!r_rstn) begin
            {rbin, rptr} <= 0;
        end
        else {rbin, rptr} <= {rbin_next, rptr_next};
    wire mem_rd;
    assign mem_rd = rinc & (~rempty);
    assign raddr = rbin;
    assign rbin_next = rbin + mem_rd;
    assign rptr_next = (rbin_next>>1) ^ rbin_next;

    
    





endmodule //async_fifo_2

sky/FIFO/async_fifo_高性能/code/async_fifo_2_tb.v
module async_fifo_2_tb ();

    parameter DATESIZE = 8;
    parameter ADDRSIZE = 3;
    
    reg [DATESIZE-1:0]wdata;
    reg w_rstn;
    reg winc;
    reg rinc;
    reg wclk;
    reg rclk;
    reg r_rstn;
    wire [DATESIZE-1:0]rdata;

    wire wfull;
    wire rempty;

    reg [3:0]a;
    reg [3:0]b;
    reg [4:0]c;
    reg x;
    initial begin
        $dumpfile("sync_fifo_tb.vcd");
        $dumpvars;
        wdata = 0;
        w_rstn = 0;
        rinc = 0;
        rclk = 0;
        r_rstn = 0;
        wclk = 0;
        winc = 0;


        #2;w_rstn = 0; r_rstn = 0;
        #4;w_rstn = 1; r_rstn = 1;

        #5;  winc = 1;
        #70; rinc = 1;
        #10; winc = 0;
        #100; rinc = 0;
        #10;  rinc = 1; winc = 1;
    
        #100;
        $finish();

    end
    integer i;
    initial begin
        wait(winc==1);
        //#11;       
        for(i=0;i<=100;i=i+1) begin
            wdata = i;
            @(posedge wclk);
        end 
    end

    always #1   wclk = ~wclk;
    always #4   rclk = ~rclk;


    async_fifo_2 #(
    .DATESIZE                       ( DATESIZE     ),
    .ADDRSIZE                       ( ADDRSIZE     ) )
    u_async_fifo_2(
    .wdata                          ( wdata ),
    .winc                           ( winc  ),
    .wclk                           ( wclk  ),
    .w_rstn                         ( w_rstn),
    .rinc                           ( rinc  ),
    .rclk                           ( rclk  ),
    .r_rstn                         ( r_rstn),
    .rdata                          ( rdata ),
    .wfull                          ( wfull ),
    .rempty                         ( rempty)
    
    );




endmodule //async_fifo_2_tb

FIFO/async_fifo_高性能/modelsim/sync_fifo_tb.vcd
$date
	Wed Jul 13 12:26:17 2022
$end
$version
	QuestaSim Version 10.6c
$end
$timescale
	1ns
$end

$scope module async_fifo_2_tb $end
$var parameter 32 ! DATESIZE $end
$var parameter 32 " ADDRSIZE $end
$var reg 8 # wdata [7:0] $end
$var reg 1 $ w_rstn $end
$var reg 1 % winc $end
$var reg 1 & rinc $end
$var reg 1 ' wclk $end
$var reg 1 ( rclk $end
$var reg 1 ) r_rstn $end
$var wire 1 * rdata [7] $end
$var wire 1 + rdata [6] $end
$var wire 1 , rdata [5] $end
$var wire 1 - rdata [4] $end
$var wire 1 . rdata [3] $end
$var wire 1 / rdata [2] $end
$var wire 1 0 rdata [1] $end
$var wire 1 1 rdata [0] $end
$var wire 1 2 wfull $end
$var wire 1 3 rempty $end
$var reg 4 4 a [3:0] $end
$var reg 4 5 b [3:0] $end
$var reg 5 6 c [4:0] $end
$var reg 1 7 x $end
$var integer 32 8 i $end

$scope module u_async_fifo_2 $end
$var parameter 32 9 DATESIZE $end
$var parameter 32 : ADDRSIZE $end
$var parameter 32 ; DEPTH $end
$var wire 1 < wdata [7] $end
$var wire 1 = wdata [6] $end
$var wire 1 > wdata [5] $end
$var wire 1 ? wdata [4] $end
$var wire 1 @ wdata [3] $end
$var wire 1 A wdata [2] $end
$var wire 1 B wdata [1] $end
$var wire 1 C wdata [0] $end
$var wire 1 D winc $end
$var wire 1 E wclk $end
$var wire 1 F w_rstn $end
$var wire 1 G rinc $end
$var wire 1 H rclk $end
$var wire 1 I r_rstn $end
$var wire 1 * rdata [7] $end
$var wire 1 + rdata [6] $end
$var wire 1 , rdata [5] $end
$var wire 1 - rdata [4] $end
$var wire 1 . rdata [3] $end
$var wire 1 / rdata [2] $end
$var wire 1 0 rdata [1] $end
$var wire 1 1 rdata [0] $end
$var reg 1 J wfull $end
$var reg 1 K rempty $end
$var wire 1 L waddr [2] $end
$var wire 1 M waddr [1] $end
$var wire 1 N waddr [0] $end
$var wire 1 O raddr [2] $end
$var wire 1 P raddr [1] $end
$var wire 1 Q raddr [0] $end
$var reg 3 R wptr [2:0] $end
$var reg 3 S rptr [2:0] $end
$var wire 1 T aempty_n $end
$var wire 1 U afull_n $end
$var reg 1 V sync_r1 $end
$var reg 1 W sync_w1 $end
$var reg 3 X wbin [2:0] $end
$var wire 1 Y wbin_next [2] $end
$var wire 1 Z wbin_next [1] $end
$var wire 1 [ wbin_next [0] $end
$var wire 1 \ wptr_next [2] $end
$var wire 1 ] wptr_next [1] $end
$var wire 1 ^ wptr_next [0] $end
$var wire 1 _ mem_wr $end
$var reg 3 ` rbin [2:0] $end
$var wire 1 a rptr_next [2] $end
$var wire 1 b rptr_next [1] $end
$var wire 1 c rptr_next [0] $end
$var wire 1 d rbin_next [2] $end
$var wire 1 e rbin_next [1] $end
$var wire 1 f rbin_next [0] $end
$var wire 1 g mem_rd $end

$scope module u_async_cmp $end
$var parameter 32 h ADDRSIZE $end
$var wire 1 i rptr [2] $end
$var wire 1 j rptr [1] $end
$var wire 1 k rptr [0] $end
$var wire 1 l wptr [2] $end
$var wire 1 m wptr [1] $end
$var wire 1 n wptr [0] $end
$var wire 1 F w_rstn $end
$var wire 1 T aempty_n $end
$var wire 1 U afull_n $end
$var reg 1 o direct $end
$var wire 1 p dirset_n $end
$var wire 1 q dirclr $end
$var wire 1 r rst $end
$var wire 1 s cmp_flag $end
$upscope $end
$upscope $end
$upscope $end
$enddefinitions $end
#0
$dumpvars
b0 #
0$
0%
0&
0'
0(
0)
bx 4
bx 5
bx 6
x7
0J
1K
b0 R
b0 S
0o
1V
xW
b0 X
b0 `
b1000 !
b11 "
b1000 9
b11 :
b1000 ;
b11 h
bx 8
x1
x0
x/
x.
x-
x,
x+
x*
02
13
0N
0M
0L
0Q
0P
0O
0T
1U
1p
0q
0r
1s
0[
0Z
0Y
0^
0]
0\
0_
0c
0b
0a
0f
0e
0d
0g
0I
0H
0G
0F
0E
0D
0C
0B
0A
0@
0?
0>
0=
0<
0k
0j
0i
0n
0m
0l
$end
#1
1'
1E
#2
0'
0E
#3
1'
1E
#4
1(
0'
1H
0E
0W
#5
1'
1E
#6
1$
1)
0'
1F
1I
0E
1r
#7
1'
1E
#8
0(
0'
0H
0E
#9
1'
1E
#10
0'
0E
#11
1%
1'
1D
1_
1[
1^
1E
b0 8
b1 X
b1 R
1n
1N
0[
1Z
01
00
0/
0.
0-
0,
0+
0*
0s
1]
1T
#12
1(
0'
1H
0E
0V
#13
1'
1E
b1 8
b1 #
1C
b10 X
b11 R
1m
0N
1M
1[
1q
0^
0r
#14
0'
0E
#15
1'
1E
b10 8
b10 #
0C
1B
b11 X
b10 R
0n
1N
0[
0Z
1Y
1\
#16
0(
0'
0H
0E
#17
1'
1E
b11 8
b11 #
1C
b100 X
b110 R
1l
0N
0M
1L
1[
0q
1^
1r
#18
0'
0E
#19
1'
1E
b100 8
b100 #
0C
0B
1A
b101 X
b111 R
1n
1N
0[
1Z
0]
#20
1(
0'
1H
0E
0K
03
#21
1'
1E
b101 8
b101 #
1C
b110 X
b101 R
0m
0N
1M
1[
0^
0p
1o
#22
0'
0E
#23
1'
1E
b110 8
b110 #
0C
1B
b111 X
b100 R
0n
1N
0[
0Z
0Y
0\
#24
0(
0'
0H
0E
#25
1'
1E
b111 8
b111 #
1C
b0 X
b0 R
0l
0N
0M
0L
1[
1s
1^
1p
0U
1W
1J
0_
12
0[
0^
#26
0'
0E
#27
1'
1E
b1000 8
b1000 #
0C
0B
0A
1@
#28
1(
0'
1H
0E
#29
1'
1E
b1001 8
b1001 #
1C
#30
0'
0E
#31
1'
1E
b1010 8
b1010 #
0C
1B
#32
0(
0'
0H
0E
#33
1'
1E
b1011 8
b1011 #
1C
#34
0'
0E
#35
1'
1E
b1100 8
b1100 #
0C
0B
1A
#36
1(
0'
1H
0E
#37
1'
1E
b1101 8
b1101 #
1C
#38
0'
0E
#39
1'
1E
b1110 8
b1110 #
0C
1B
#40
0(
0'
0H
0E
#41
1'
1E
b1111 8
b1111 #
1C
#42
0'
0E
#43
1'
1E
b10000 8
b10000 #
0C
0B
0A
0@
1?
#44
1(
0'
1H
0E
#45
1'
1E
b10001 8
b10001 #
1C
#46
0'
0E
#47
1'
1E
b10010 8
b10010 #
0C
1B
#48
0(
0'
0H
0E
#49
1'
1E
b10011 8
b10011 #
1C
#50
0'
0E
#51
1'
1E
b10100 8
b10100 #
0C
0B
1A
#52
1(
0'
1H
0E
#53
1'
1E
b10101 8
b10101 #
1C
#54
0'
0E
#55
1'
1E
b10110 8
b10110 #
0C
1B
#56
0(
0'
0H
0E
#57
1'
1E
b10111 8
b10111 #
1C
#58
0'
0E
#59
1'
1E
b11000 8
b11000 #
0C
0B
0A
1@
#60
1(
0'
1H
0E
#61
1'
1E
b11001 8
b11001 #
1C
#62
0'
0E
#63
1'
1E
b11010 8
b11010 #
0C
1B
#64
0(
0'
0H
0E
#65
1'
1E
b11011 8
b11011 #
1C
#66
0'
0E
#67
1'
1E
b11100 8
b11100 #
0C
0B
1A
#68
1(
0'
1H
0E
#69
1'
1E
b11101 8
b11101 #
1C
#70
0'
0E
#71
1'
1E
b11110 8
b11110 #
0C
1B
#72
0(
0'
0H
0E
#73
1'
1E
b11111 8
b11111 #
1C
#74
0'
0E
#75
1'
1E
b100000 8
b100000 #
0C
0B
0A
0@
0?
1>
#76
1(
0'
1H
0E
#77
1'
1E
b100001 8
b100001 #
1C
#78
0'
0E
#79
1'
1E
b100010 8
b100010 #
0C
1B
#80
0(
0'
0H
0E
#81
1&
1'
1G
1g
1f
1c
1E
b100011 8
b100011 #
1C
#82
0'
0E
#83
1'
1E
b100100 8
b100100 #
0C
0B
1A
#84
1(
0'
1H
0E
b1 S
b1 `
1Q
0f
1e
1k
1b
0s
1U
#85
1'
1E
b100101 8
b100101 #
1C
#86
0'
0E
#87
1'
1E
b100110 8
b100110 #
0C
1B
#88
0(
0'
0H
0E
#89
1'
1E
b100111 8
b100111 #
1C
#90
0'
0E
#91
0%
1'
0D
1E
b101000 8
b101000 #
0C
0B
0A
1@
#92
1(
0'
1H
0E
0W
b11 S
b10 `
0Q
1P
1f
1j
0c
11
0p
#93
1'
1E
b101001 8
b101001 #
1C
#94
0'
0E
#95
1'
1E
b101010 8
b101010 #
0C
1B
#96
0(
0'
0H
0E
#97
1'
1E
b101011 8
b101011 #
1C
#98
0'
0E
#99
1'
1E
b101100 8
b101100 #
0C
0B
1A
#100
1(
0'
1H
0E
0J
02
b10 S
b11 `
1Q
0f
0e
1d
0k
1a
01
10
#101
1'
1E
b101101 8
b101101 #
1C
#102
0'
0E
#103
1'
1E
b101110 8
b101110 #
0C
1B
#104
0(
0'
0H
0E
#105
1'
1E
b101111 8
b101111 #
1C
#106
0'
0E
#107
1'
1E
b110000 8
b110000 #
0C
0B
0A
0@
1?
#108
1(
0'
1H
0E
b110 S
b100 `
0Q
0P
1O
1f
1i
1c
11
1p
#109
1'
1E
b110001 8
b110001 #
1C
#110
0'
0E
#111
1'
1E
b110010 8
b110010 #
0C
1B
#112
0(
0'
0H
0E
#113
1'
1E
b110011 8
b110011 #
1C
#114
0'
0E
#115
1'
1E
b110100 8
b110100 #
0C
0B
1A
#116
1(
0'
1H
0E
b111 S
b101 `
1Q
0f
1e
1k
0b
01
00
1/
#117
1'
1E
b110101 8
b110101 #
1C
#118
0'
0E
#119
1'
1E
b110110 8
b110110 #
0C
1B
#120
0(
0'
0H
0E
#121
1'
1E
b110111 8
b110111 #
1C
#122
0'
0E
#123
1'
1E
b111000 8
b111000 #
0C
0B
0A
1@
#124
1(
0'
1H
0E
b101 S
b110 `
0Q
1P
1f
0j
1q
0c
11
0r
0o
#125
1'
1E
b111001 8
b111001 #
1C
#126
0'
0E
#127
1'
1E
b111010 8
b111010 #
0C
1B
#128
0(
0'
0H
0E
#129
1'
1E
b111011 8
b111011 #
1C
#130
0'
0E
#131
1'
1E
b111100 8
b111100 #
0C
0B
1A
#132
1(
0'
1H
0E
b100 S
b111 `
1Q
0f
0e
0d
0k
0a
01
10
#133
1'
1E
b111101 8
b111101 #
1C
#134
0'
0E
#135
1'
1E
b111110 8
b111110 #
0C
1B
#136
0(
0'
0H
0E
#137
1'
1E
b111111 8
b111111 #
1C
#138
0'
0E
#139
1'
1E
b1000000 8
b1000000 #
0C
0B
0A
0@
0?
0>
1=
#140
1(
0'
1H
0E
b0 S
b0 `
0Q
0P
0O
1f
0i
0q
1c
00
0/
1s
1r
0T
1V
1K
0g
13
0f
0c
#141
1'
1E
b1000001 8
b1000001 #
1C
#142
0'
0E
#143
1'
1E
b1000010 8
b1000010 #
0C
1B
#144
0(
0'
0H
0E
#145
1'
1E
b1000011 8
b1000011 #
1C
#146
0'
0E
#147
1'
1E
b1000100 8
b1000100 #
0C
0B
1A
#148
1(
0'
1H
0E
#149
1'
1E
b1000101 8
b1000101 #
1C
#150
0'
0E
#151
1'
1E
b1000110 8
b1000110 #
0C
1B
#152
0(
0'
0H
0E
#153
1'
1E
b1000111 8
b1000111 #
1C
#154
0'
0E
#155
1'
1E
b1001000 8
b1001000 #
0C
0B
0A
1@
#156
1(
0'
1H
0E
#157
1'
1E
b1001001 8
b1001001 #
1C
#158
0'
0E
#159
1'
1E
b1001010 8
b1001010 #
0C
1B
#160
0(
0'
0H
0E
#161
1'
1E
b1001011 8
b1001011 #
1C
#162
0'
0E
#163
1'
1E
b1001100 8
b1001100 #
0C
0B
1A
#164
1(
0'
1H
0E
#165
1'
1E
b1001101 8
b1001101 #
1C
#166
0'
0E
#167
1'
1E
b1001110 8
b1001110 #
0C
1B
#168
0(
0'
0H
0E
#169
1'
1E
b1001111 8
b1001111 #
1C
#170
0'
0E
#171
1'
1E
b1010000 8
b1010000 #
0C
0B
0A
0@
1?
#172
1(
0'
1H
0E
#173
1'
1E
b1010001 8
b1010001 #
1C
#174
0'
0E
#175
1'
1E
b1010010 8
b1010010 #
0C
1B
#176
0(
0'
0H
0E
#177
1'
1E
b1010011 8
b1010011 #
1C
#178
0'
0E
#179
1'
1E
b1010100 8
b1010100 #
0C
0B
1A
#180
1(
0'
1H
0E
#181
1'
1E
b1010101 8
b1010101 #
1C
#182
0'
0E
#183
1'
1E
b1010110 8
b1010110 #
0C
1B
#184
0(
0'
0H
0E
#185
1'
1E
b1010111 8
b1010111 #
1C
#186
0'
0E
#187
1'
1E
b1011000 8
b1011000 #
0C
0B
0A
1@
#188
1(
0'
1H
0E
#189
1'
1E
b1011001 8
b1011001 #
1C
#190
0'
0E
#191
0&
1'
0G
1E
b1011010 8
b1011010 #
0C
1B
#192
0(
0'
0H
0E
#193
1'
1E
b1011011 8
b1011011 #
1C
#194
0'
0E
#195
1'
1E
b1011100 8
b1011100 #
0C
0B
1A
#196
1(
0'
1H
0E
#197
1'
1E
b1011101 8
b1011101 #
1C
#198
0'
0E
#199
1'
1E
b1011110 8
b1011110 #
0C
1B
#200
0(
0'
0H
0E
#201
1&
1%
1'
1G
1D
1_
1[
1^
1E
b1011111 8
b1011111 #
1C
b1 X
b1 R
1n
1N
0[
1Z
10
1/
1.
1-
1+
0s
1]
1T
#202
0'
0E
#203
1'
1E
b1100000 8
b1100000 #
0C
0B
0A
0@
0?
1>
b10 X
b11 R
1m
0N
1M
1[
1q
0^
0r
#204
1(
0'
1H
0E
0V
#205
1'
1E
b1100001 8
b1100001 #
1C
b11 X
b10 R
0n
1N
0[
0Z
1Y
1\
#206
0'
0E
#207
1'
1E
b1100010 8
b1100010 #
0C
1B
b100 X
b110 R
1l
0N
0M
1L
1[
0q
1^
1r
#208
0(
0'
0H
0E
#209
1'
1E
b1100011 8
b1100011 #
1C
b101 X
b111 R
1n
1N
0[
1Z
0]
#210
0'
0E
#211
1'
1E
b1100100 8
b1100100 #
0C
0B
1A
b110 X
b101 R
0m
0N
1M
1[
0^
0p
1o
#212
1(
0'
1H
0E
0K
1g
03
1f
1c
#213
1'
1E
b1100101 8
b111 X
b100 R
0n
1N
0[
0Z
0Y
0\
#214
0'
0E
#215
1'
1E
b0 X
b0 R
0l
0N
0M
0L
1[
1s
1^
1p
0U
1W
1J
0_
12
0[
0^
#216
0(
0'
0H
0E
#217
1'
1E
#218
0'
0E
#219
1'
1E
#220
1(
0'
1H
0E
b1 S
b1 `
1Q
0f
1e
1k
1b
11
0s
1U
#221
1'
1E
#222
0'
0E
#223
1'
1E
#224
0(
0'
0H
0E
#225
1'
1E
#226
0'
0E
#227
1'
1E
#228
1(
0'
1H
0E
0W
b11 S
b10 `
0Q
1P
1f
1j
0c
01
00
0/
0.
0-
1,
0p
#229
1'
1E
#230
0'
0E
#231
1'
1E
#232
0(
0'
0H
0E
#233
1'
1E
#234
0'
0E
#235
1'
1E
#236
1(
0'
1H
0E
0J
1_
02
1[
1^
b10 S
b11 `
1Q
0f
0e
1d
0k
1a
11
#237
1'
1E
b1 X
b1 R
1n
1N
0[
1Z
1]
#238
0'
0E
#239
1'
1E
b10 X
b11 R
1m
0N
1M
1[
0^
1p
#240
0(
0'
0H
0E
#241
1'
1E
b11 X
b10 R
0n
1N
0[
0Z
1Y
1s
1\
0U
1W
1J
0_
12
1[
1Z
0Y
0\
#242
0'
0E
#243
1'
1E
#244
1(
0'
1H
0E
b110 S
b100 `
0Q
0P
1O
1f
1i
1c
01
10
0s
0p
1U
#245
1'
1E
#246
0'
0E
#247
1'
1E
#248
0(
0'
0H
0E
#249
1'
1E
#250
0'
0E
#251
1'
1E
#252
1(
0'
1H
0E
0W
b111 S
b101 `
1Q
0f
1e
1k
0b
11
#253
1'
1E
#254
0'
0E
#255
1'
1E
#256
0(
0'
0H
0E
#257
1'
1E
#258
0'
0E
#259
1'
1E
#260
1(
0'
1H
0E
0J
1_
02
0[
0Z
1Y
1\
b101 S
b110 `
0Q
1P
1f
0j
0c
01
00
1/
1p
#261
1'
1E
b100 X
b110 R
1l
0N
0M
1L
1[
1^
0p
#262
0'
0E
#263
1'
1E
b101 X
b111 R
1n
1N
0[
1Z
0]
#264
0(
0'
0H
0E
#265
1'
1E
b110 X
b101 R
0m
0N
1M
1[
1s
0^
1p
0U
1W
1J
0_
12
0[
1^
#266
0'
0E
#267
1'
1E
#268
1(
0'
1H
0E
b100 S
b111 `
1Q
0f
0e
0d
0k
0a
0s
1U
#269
1'
1E
#270
0'
0E
#271
1'
1E
#272
0(
0'
0H
0E
#273
1'
1E
#274
0'
0E
#275
1'
1E
#276
1(
0'
1H
0E
0W
b0 S
b0 `
0Q
0P
0O
1f
0i
1c
0p
#277
1'
1E
#278
0'
0E
#279
1'
1E
#280
0(
0'
0H
0E
#281
1'
1E
#282
0'
0E
#283
1'
1E
#284
1(
0'
1H
0E
0J
1_
02
1[
0^
b1 S
b1 `
1Q
0f
1e
1k
1b
#285
1'
1E
b111 X
b100 R
0n
1N
0[
0Z
0Y
0\
#286
0'
0E
#287
1'
1E
b0 X
b0 R
0l
0N
0M
0L
1[
1^
1p
#288
0(
0'
0H
0E
#289
1'
1E
b1 X
b1 R
1n
1N
0[
1Z
1s
1]
0U
1W
1J
0_
12
1[
0Z
0]
#290
0'
0E
#291
1'
1E
#292
1(
0'
1H
0E
b11 S
b10 `
0Q
1P
1f
1j
0c
0s
0p
1U
#293
1'
1E
#294
0'
0E
#295
1'
1E
#296
0(
0'
0H
0E
#297
1'
1E
#298
0'
0E
#299
1'
1E
#300
1(
0'
1H
0E
0W
b10 S
b11 `
1Q
0f
0e
1d
0k
1a
